{"num_rooms": 5, "room_types": [{"name": "bedroom", "min_size": [200, 200], "max_size": [200, 500], "color": [0, 0, 255], "privacy": "private"}, {"name": "bathroom", "min_size": [150, 200], "max_size": [150, 250], "color": [255, 155, 20], "privacy": "private"}, {"name": "bedroom", "min_size": [200, 200], "max_size": [200, 500], "color": [0, 0, 255], "privacy": "private"}, {"name": "bathroom", "min_size": [150, 200], "max_size": [150, 250], "color": [255, 155, 20], "privacy": "private"}, {"name": "bathroom", "min_size": [150, 200], "max_size": [150, 250], "color": [255, 155, 20], "privacy": "private"}], "slicing_tree_root": {"value": "V", "cut_percentage": 0.30056939701939017, "children": [{"value": "H", "cut_percentage": 0.6136388454503142, "children": [{"value": 2, "cut_percentage": 0.5194799230593059, "children": [], "room_type": {"name": "bathroom", "min_size": [150, 200], "max_size": [150, 250], "color": [255, 155, 20], "privacy": "private"}}, {"value": 5, "cut_percentage": 0.37376608750857393, "children": [], "room_type": {"name": "bedroom", "min_size": [200, 200], "max_size": [200, 500], "color": [0, 0, 255], "privacy": "private"}}], "room_type": null}, {"value": "V", "cut_percentage": 0.7098897614821633, "children": [{"value": "H", "cut_percentage": 0.20918257563379705, "children": [{"value": 4, "cut_percentage": 0.5507690621695321, "children": [], "room_type": {"name": "bathroom", "min_size": [150, 200], "max_size": [150, 250], "color": [255, 155, 20], "privacy": "private"}}, {"value": 1, "cut_percentage": 0.5485155499134747, "children": [], "room_type": {"name": "bedroom", "min_size": [200, 200], "max_size": [200, 500], "color": [0, 0, 255], "privacy": "private"}}], "room_type": null}, {"value": 3, "cut_percentage": 0.6430151812707887, "children": [], "room_type": {"name": "bedroom", "min_size": [200, 200], "max_size": [200, 500], "color": [0, 0, 255], "privacy": "private"}}], "room_type": null}], "room_type": null}, "rooms": [{"node": {"value": 2, "cut_percentage": 0.5194799230593059, "children": [], "room_type": {"name": "bathroom", "min_size": [150, 200], "max_size": [150, 250], "color": [255, 155, 20], "privacy": "private"}}, "rect": [0, 0, 300, 490], "neighbors": [{"value": 5, "cut_percentage": 0.37376608750857393, "children": [], "room_type": {"name": "bedroom", "min_size": [200, 200], "max_size": [200, 500], "color": [0, 0, 255], "privacy": "private"}}, {"value": 4, "cut_percentage": 0.5507690621695321, "children": [], "room_type": {"name": "bathroom", "min_size": [150, 200], "max_size": [150, 250], "color": [255, 155, 20], "privacy": "private"}}, {"value": 1, "cut_percentage": 0.5485155499134747, "children": [], "room_type": {"name": "bedroom", "min_size": [200, 200], "max_size": [200, 500], "color": [0, 0, 255], "privacy": "private"}}], "objects": [{"name": "Toilet", "object_type": {"name": "Toilet", "effect": {"bladder": 60}}, "interaction_time": 0.3, "position": [75.0, 122.5]}, {"name": "Shower", "object_type": {"name": "Shower", "effect": {"hygiene": 60}}, "interaction_time": 0.1, "position": [225.0, 367.5]}], "doors": [{"position": [150.0, 490], "orientation": "horizontal", "room1": {"value": 2, "cut_percentage": 0.5194799230593059, "children": [], "room_type": {"name": "bathroom", "min_size": [150, 200], "max_size": [150, 250], "color": [255, 155, 20], "privacy": "private"}}, "room2": {"value": 5, "cut_percentage": 0.37376608750857393, "children": [], "room_type": {"name": "bedroom", "min_size": [200, 200], "max_size": [200, 500], "color": [0, 0, 255], "privacy": "private"}}}, {"position": [300, 83.5], "orientation": "vertical", "room1": {"value": 4, "cut_percentage": 0.5507690621695321, "children": [], "room_type": {"name": "bathroom", "min_size": [150, 200], "max_size": [150, 250], "color": [255, 155, 20], "privacy": "private"}}, "room2": {"value": 2, "cut_percentage": 0.5194799230593059, "children": [], "room_type": {"name": "bathroom", "min_size": [150, 200], "max_size": [150, 250], "color": [255, 155, 20], "privacy": "private"}}}, {"position": [300, 328.5], "orientation": "vertical", "room1": {"value": 1, "cut_percentage": 0.5485155499134747, "children": [], "room_type": {"name": "bedroom", "min_size": [200, 200], "max_size": [200, 500], "color": [0, 0, 255], "privacy": "private"}}, "room2": {"value": 2, "cut_percentage": 0.5194799230593059, "children": [], "room_type": {"name": "bathroom", "min_size": [150, 200], "max_size": [150, 250], "color": [255, 155, 20], "privacy": "private"}}}]}, {"node": {"value": 5, "cut_percentage": 0.37376608750857393, "children": [], "room_type": {"name": "bedroom", "min_size": [200, 200], "max_size": [200, 500], "color": [0, 0, 255], "privacy": "private"}}, "rect": [0, 490, 300, 309], "neighbors": [{"value": 2, "cut_percentage": 0.5194799230593059, "children": [], "room_type": {"name": "bathroom", "min_size": [150, 200], "max_size": [150, 250], "color": [255, 155, 20], "privacy": "private"}}, {"value": 1, "cut_percentage": 0.5485155499134747, "children": [], "room_type": {"name": "bedroom", "min_size": [200, 200], "max_size": [200, 500], "color": [0, 0, 255], "privacy": "private"}}], "objects": [{"name": "Bed", "object_type": {"name": "Bed", "effect": {"energy": 50}}, "interaction_time": 4.7, "position": [75.0, 644.5]}], "doors": [{"position": [150.0, 490], "orientation": "horizontal", "room1": {"value": 2, "cut_percentage": 0.5194799230593059, "children": [], "room_type": {"name": "bathroom", "min_size": [150, 200], "max_size": [150, 250], "color": [255, 155, 20], "privacy": "private"}}, "room2": {"value": 5, "cut_percentage": 0.37376608750857393, "children": [], "room_type": {"name": "bedroom", "min_size": [200, 200], "max_size": [200, 500], "color": [0, 0, 255], "privacy": "private"}}}, {"position": [300, 644.5], "orientation": "vertical", "room1": {"value": 5, "cut_percentage": 0.37376608750857393, "children": [], "room_type": {"name": "bedroom", "min_size": [200, 200], "max_size": [200, 500], "color": [0, 0, 255], "privacy": "private"}}, "room2": {"value": 1, "cut_percentage": 0.5485155499134747, "children": [], "room_type": {"name": "bedroom", "min_size": [200, 200], "max_size": [200, 500], "color": [0, 0, 255], "privacy": "private"}}}]}, {"node": {"value": 4, "cut_percentage": 0.5507690621695321, "children": [], "room_type": {"name": "bathroom", "min_size": [150, 200], "max_size": [150, 250], "color": [255, 155, 20], "privacy": "private"}}, "rect": [300, 0, 496, 167], "neighbors": [{"value": 2, "cut_percentage": 0.5194799230593059, "children": [], "room_type": {"name": "bathroom", "min_size": [150, 200], "max_size": [150, 250], "color": [255, 155, 20], "privacy": "private"}}, {"value": 1, "cut_percentage": 0.5485155499134747, "children": [], "room_type": {"name": "bedroom", "min_size": [200, 200], "max_size": [200, 500], "color": [0, 0, 255], "privacy": "private"}}, {"value": 3, "cut_percentage": 0.6430151812707887, "children": [], "room_type": {"name": "bedroom", "min_size": [200, 200], "max_size": [200, 500], "color": [0, 0, 255], "privacy": "private"}}], "objects": [{"name": "Toilet", "object_type": {"name": "Toilet", "effect": {"bladder": 60}}, "interaction_time": 0.3, "position": [672.0, 125.25]}, {"name": "Shower", "object_type": {"name": "Shower", "effect": {"hygiene": 60}}, "interaction_time": 0.1, "position": [672.0, 41.75]}], "doors": [{"position": [300, 83.5], "orientation": "vertical", "room1": {"value": 4, "cut_percentage": 0.5507690621695321, "children": [], "room_type": {"name": "bathroom", "min_size": [150, 200], "max_size": [150, 250], "color": [255, 155, 20], "privacy": "private"}}, "room2": {"value": 2, "cut_percentage": 0.5194799230593059, "children": [], "room_type": {"name": "bathroom", "min_size": [150, 200], "max_size": [150, 250], "color": [255, 155, 20], "privacy": "private"}}}, {"position": [796, 83.5], "orientation": "vertical", "room1": {"value": 3, "cut_percentage": 0.6430151812707887, "children": [], "room_type": {"name": "bedroom", "min_size": [200, 200], "max_size": [200, 500], "color": [0, 0, 255], "privacy": "private"}}, "room2": {"value": 4, "cut_percentage": 0.5507690621695321, "children": [], "room_type": {"name": "bathroom", "min_size": [150, 200], "max_size": [150, 250], "color": [255, 155, 20], "privacy": "private"}}}]}, {"node": {"value": 1, "cut_percentage": 0.5485155499134747, "children": [], "room_type": {"name": "bedroom", "min_size": [200, 200], "max_size": [200, 500], "color": [0, 0, 255], "privacy": "private"}}, "rect": [300, 167, 496, 632], "neighbors": [{"value": 2, "cut_percentage": 0.5194799230593059, "children": [], "room_type": {"name": "bathroom", "min_size": [150, 200], "max_size": [150, 250], "color": [255, 155, 20], "privacy": "private"}}, {"value": 5, "cut_percentage": 0.37376608750857393, "children": [], "room_type": {"name": "bedroom", "min_size": [200, 200], "max_size": [200, 500], "color": [0, 0, 255], "privacy": "private"}}, {"value": 4, "cut_percentage": 0.5507690621695321, "children": [], "room_type": {"name": "bathroom", "min_size": [150, 200], "max_size": [150, 250], "color": [255, 155, 20], "privacy": "private"}}, {"value": 3, "cut_percentage": 0.6430151812707887, "children": [], "room_type": {"name": "bedroom", "min_size": [200, 200], "max_size": [200, 500], "color": [0, 0, 255], "privacy": "private"}}], "objects": [{"name": "Bed", "object_type": {"name": "Bed", "effect": {"energy": 50}}, "interaction_time": 4.7, "position": [672.0, 325.0]}], "doors": [{"position": [300, 644.5], "orientation": "vertical", "room1": {"value": 5, "cut_percentage": 0.37376608750857393, "children": [], "room_type": {"name": "bedroom", "min_size": [200, 200], "max_size": [200, 500], "color": [0, 0, 255], "privacy": "private"}}, "room2": {"value": 1, "cut_percentage": 0.5485155499134747, "children": [], "room_type": {"name": "bedroom", "min_size": [200, 200], "max_size": [200, 500], "color": [0, 0, 255], "privacy": "private"}}}, {"position": [300, 328.5], "orientation": "vertical", "room1": {"value": 1, "cut_percentage": 0.5485155499134747, "children": [], "room_type": {"name": "bedroom", "min_size": [200, 200], "max_size": [200, 500], "color": [0, 0, 255], "privacy": "private"}}, "room2": {"value": 2, "cut_percentage": 0.5194799230593059, "children": [], "room_type": {"name": "bathroom", "min_size": [150, 200], "max_size": [150, 250], "color": [255, 155, 20], "privacy": "private"}}}]}, {"node": {"value": 3, "cut_percentage": 0.6430151812707887, "children": [], "room_type": {"name": "bedroom", "min_size": [200, 200], "max_size": [200, 500], "color": [0, 0, 255], "privacy": "private"}}, "rect": [796, 0, 202, 800], "neighbors": [{"value": 4, "cut_percentage": 0.5507690621695321, "children": [], "room_type": {"name": "bathroom", "min_size": [150, 200], "max_size": [150, 250], "color": [255, 155, 20], "privacy": "private"}}, {"value": 1, "cut_percentage": 0.5485155499134747, "children": [], "room_type": {"name": "bedroom", "min_size": [200, 200], "max_size": [200, 500], "color": [0, 0, 255], "privacy": "private"}}], "objects": [{"name": "Bed", "object_type": {"name": "Bed", "effect": {"energy": 50}}, "interaction_time": 4.7, "position": [947.5, 600.0]}], "doors": [{"position": [796, 83.5], "orientation": "vertical", "room1": {"value": 3, "cut_percentage": 0.6430151812707887, "children": [], "room_type": {"name": "bedroom", "min_size": [200, 200], "max_size": [200, 500], "color": [0, 0, 255], "privacy": "private"}}, "room2": {"value": 4, "cut_percentage": 0.5507690621695321, "children": [], "room_type": {"name": "bathroom", "min_size": [150, 200], "max_size": [150, 250], "color": [255, 155, 20], "privacy": "private"}}}]}], "doors_list": [{"position": [150.0, 490], "orientation": "horizontal", "room1": {"value": 2, "cut_percentage": 0.5194799230593059, "children": [], "room_type": {"name": "bathroom", "min_size": [150, 200], "max_size": [150, 250], "color": [255, 155, 20], "privacy": "private"}}, "room2": {"value": 5, "cut_percentage": 0.37376608750857393, "children": [], "room_type": {"name": "bedroom", "min_size": [200, 200], "max_size": [200, 500], "color": [0, 0, 255], "privacy": "private"}}}, {"position": [300, 644.5], "orientation": "vertical", "room1": {"value": 5, "cut_percentage": 0.37376608750857393, "children": [], "room_type": {"name": "bedroom", "min_size": [200, 200], "max_size": [200, 500], "color": [0, 0, 255], "privacy": "private"}}, "room2": {"value": 1, "cut_percentage": 0.5485155499134747, "children": [], "room_type": {"name": "bedroom", "min_size": [200, 200], "max_size": [200, 500], "color": [0, 0, 255], "privacy": "private"}}}, {"position": [300, 83.5], "orientation": "vertical", "room1": {"value": 4, "cut_percentage": 0.5507690621695321, "children": [], "room_type": {"name": "bathroom", "min_size": [150, 200], "max_size": [150, 250], "color": [255, 155, 20], "privacy": "private"}}, "room2": {"value": 2, "cut_percentage": 0.5194799230593059, "children": [], "room_type": {"name": "bathroom", "min_size": [150, 200], "max_size": [150, 250], "color": [255, 155, 20], "privacy": "private"}}}, {"position": [300, 328.5], "orientation": "vertical", "room1": {"value": 1, "cut_percentage": 0.5485155499134747, "children": [], "room_type": {"name": "bedroom", "min_size": [200, 200], "max_size": [200, 500], "color": [0, 0, 255], "privacy": "private"}}, "room2": {"value": 2, "cut_percentage": 0.5194799230593059, "children": [], "room_type": {"name": "bathroom", "min_size": [150, 200], "max_size": [150, 250], "color": [255, 155, 20], "privacy": "private"}}}, {"position": [796, 83.5], "orientation": "vertical", "room1": {"value": 3, "cut_percentage": 0.6430151812707887, "children": [], "room_type": {"name": "bedroom", "min_size": [200, 200], "max_size": [200, 500], "color": [0, 0, 255], "privacy": "private"}}, "room2": {"value": 4, "cut_percentage": 0.5507690621695321, "children": [], "room_type": {"name": "bathroom", "min_size": [150, 200], "max_size": [150, 250], "color": [255, 155, 20], "privacy": "private"}}}], "graph": [[{"node": {"value": 2, "cut_percentage": 0.5194799230593059, "children": [], "room_type": {"name": "bathroom", "min_size": [150, 200], "max_size": [150, 250], "color": [255, 155, 20], "privacy": "private"}}, "rect": [0, 0, 300, 490], "neighbors": [{"value": 5, "cut_percentage": 0.37376608750857393, "children": [], "room_type": {"name": "bedroom", "min_size": [200, 200], "max_size": [200, 500], "color": [0, 0, 255], "privacy": "private"}}, {"value": 4, "cut_percentage": 0.5507690621695321, "children": [], "room_type": {"name": "bathroom", "min_size": [150, 200], "max_size": [150, 250], "color": [255, 155, 20], "privacy": "private"}}, {"value": 1, "cut_percentage": 0.5485155499134747, "children": [], "room_type": {"name": "bedroom", "min_size": [200, 200], "max_size": [200, 500], "color": [0, 0, 255], "privacy": "private"}}], "objects": [{"name": "Toilet", "object_type": {"name": "Toilet", "effect": {"bladder": 60}}, "interaction_time": 0.3, "position": [75.0, 122.5]}, {"name": "Shower", "object_type": {"name": "Shower", "effect": {"hygiene": 60}}, "interaction_time": 0.1, "position": [225.0, 367.5]}], "doors": [{"position": [150.0, 490], "orientation": "horizontal", "room1": {"value": 2, "cut_percentage": 0.5194799230593059, "children": [], "room_type": {"name": "bathroom", "min_size": [150, 200], "max_size": [150, 250], "color": [255, 155, 20], "privacy": "private"}}, "room2": {"value": 5, "cut_percentage": 0.37376608750857393, "children": [], "room_type": {"name": "bedroom", "min_size": [200, 200], "max_size": [200, 500], "color": [0, 0, 255], "privacy": "private"}}}, {"position": [300, 83.5], "orientation": "vertical", "room1": {"value": 4, "cut_percentage": 0.5507690621695321, "children": [], "room_type": {"name": "bathroom", "min_size": [150, 200], "max_size": [150, 250], "color": [255, 155, 20], "privacy": "private"}}, "room2": {"value": 2, "cut_percentage": 0.5194799230593059, "children": [], "room_type": {"name": "bathroom", "min_size": [150, 200], "max_size": [150, 250], "color": [255, 155, 20], "privacy": "private"}}}, {"position": [300, 328.5], "orientation": "vertical", "room1": {"value": 1, "cut_percentage": 0.5485155499134747, "children": [], "room_type": {"name": "bedroom", "min_size": [200, 200], "max_size": [200, 500], "color": [0, 0, 255], "privacy": "private"}}, "room2": {"value": 2, "cut_percentage": 0.5194799230593059, "children": [], "room_type": {"name": "bathroom", "min_size": [150, 200], "max_size": [150, 250], "color": [255, 155, 20], "privacy": "private"}}}]}, [{"node": {"value": 5, "cut_percentage": 0.37376608750857393, "children": [], "room_type": {"name": "bedroom", "min_size": [200, 200], "max_size": [200, 500], "color": [0, 0, 255], "privacy": "private"}}, "rect": [0, 490, 300, 309], "neighbors": [{"value": 2, "cut_percentage": 0.5194799230593059, "children": [], "room_type": {"name": "bathroom", "min_size": [150, 200], "max_size": [150, 250], "color": [255, 155, 20], "privacy": "private"}}, {"value": 1, "cut_percentage": 0.5485155499134747, "children": [], "room_type": {"name": "bedroom", "min_size": [200, 200], "max_size": [200, 500], "color": [0, 0, 255], "privacy": "private"}}], "objects": [{"name": "Bed", "object_type": {"name": "Bed", "effect": {"energy": 50}}, "interaction_time": 4.7, "position": [75.0, 644.5]}], "doors": [{"position": [150.0, 490], "orientation": "horizontal", "room1": {"value": 2, "cut_percentage": 0.5194799230593059, "children": [], "room_type": {"name": "bathroom", "min_size": [150, 200], "max_size": [150, 250], "color": [255, 155, 20], "privacy": "private"}}, "room2": {"value": 5, "cut_percentage": 0.37376608750857393, "children": [], "room_type": {"name": "bedroom", "min_size": [200, 200], "max_size": [200, 500], "color": [0, 0, 255], "privacy": "private"}}}, {"position": [300, 644.5], "orientation": "vertical", "room1": {"value": 5, "cut_percentage": 0.37376608750857393, "children": [], "room_type": {"name": "bedroom", "min_size": [200, 200], "max_size": [200, 500], "color": [0, 0, 255], "privacy": "private"}}, "room2": {"value": 1, "cut_percentage": 0.5485155499134747, "children": [], "room_type": {"name": "bedroom", "min_size": [200, 200], "max_size": [200, 500], "color": [0, 0, 255], "privacy": "private"}}}]}, {"node": {"value": 4, "cut_percentage": 0.5507690621695321, "children": [], "room_type": {"name": "bathroom", "min_size": [150, 200], "max_size": [150, 250], "color": [255, 155, 20], "privacy": "private"}}, "rect": [300, 0, 496, 167], "neighbors": [{"value": 2, "cut_percentage": 0.5194799230593059, "children": [], "room_type": {"name": "bathroom", "min_size": [150, 200], "max_size": [150, 250], "color": [255, 155, 20], "privacy": "private"}}, {"value": 1, "cut_percentage": 0.5485155499134747, "children": [], "room_type": {"name": "bedroom", "min_size": [200, 200], "max_size": [200, 500], "color": [0, 0, 255], "privacy": "private"}}, {"value": 3, "cut_percentage": 0.6430151812707887, "children": [], "room_type": {"name": "bedroom", "min_size": [200, 200], "max_size": [200, 500], "color": [0, 0, 255], "privacy": "private"}}], "objects": [{"name": "Toilet", "object_type": {"name": "Toilet", "effect": {"bladder": 60}}, "interaction_time": 0.3, "position": [672.0, 125.25]}, {"name": "Shower", "object_type": {"name": "Shower", "effect": {"hygiene": 60}}, "interaction_time": 0.1, "position": [672.0, 41.75]}], "doors": [{"position": [300, 83.5], "orientation": "vertical", "room1": {"value": 4, "cut_percentage": 0.5507690621695321, "children": [], "room_type": {"name": "bathroom", "min_size": [150, 200], "max_size": [150, 250], "color": [255, 155, 20], "privacy": "private"}}, "room2": {"value": 2, "cut_percentage": 0.5194799230593059, "children": [], "room_type": {"name": "bathroom", "min_size": [150, 200], "max_size": [150, 250], "color": [255, 155, 20], "privacy": "private"}}}, {"position": [796, 83.5], "orientation": "vertical", "room1": {"value": 3, "cut_percentage": 0.6430151812707887, "children": [], "room_type": {"name": "bedroom", "min_size": [200, 200], "max_size": [200, 500], "color": [0, 0, 255], "privacy": "private"}}, "room2": {"value": 4, "cut_percentage": 0.5507690621695321, "children": [], "room_type": {"name": "bathroom", "min_size": [150, 200], "max_size": [150, 250], "color": [255, 155, 20], "privacy": "private"}}}]}, {"node": {"value": 1, "cut_percentage": 0.5485155499134747, "children": [], "room_type": {"name": "bedroom", "min_size": [200, 200], "max_size": [200, 500], "color": [0, 0, 255], "privacy": "private"}}, "rect": [300, 167, 496, 632], "neighbors": [{"value": 2, "cut_percentage": 0.5194799230593059, "children": [], "room_type": {"name": "bathroom", "min_size": [150, 200], "max_size": [150, 250], "color": [255, 155, 20], "privacy": "private"}}, {"value": 5, "cut_percentage": 0.37376608750857393, "children": [], "room_type": {"name": "bedroom", "min_size": [200, 200], "max_size": [200, 500], "color": [0, 0, 255], "privacy": "private"}}, {"value": 4, "cut_percentage": 0.5507690621695321, "children": [], "room_type": {"name": "bathroom", "min_size": [150, 200], "max_size": [150, 250], "color": [255, 155, 20], "privacy": "private"}}, {"value": 3, "cut_percentage": 0.6430151812707887, "children": [], "room_type": {"name": "bedroom", "min_size": [200, 200], "max_size": [200, 500], "color": [0, 0, 255], "privacy": "private"}}], "objects": [{"name": "Bed", "object_type": {"name": "Bed", "effect": {"energy": 50}}, "interaction_time": 4.7, "position": [672.0, 325.0]}], "doors": [{"position": [300, 644.5], "orientation": "vertical", "room1": {"value": 5, "cut_percentage": 0.37376608750857393, "children": [], "room_type": {"name": "bedroom", "min_size": [200, 200], "max_size": [200, 500], "color": [0, 0, 255], "privacy": "private"}}, "room2": {"value": 1, "cut_percentage": 0.5485155499134747, "children": [], "room_type": {"name": "bedroom", "min_size": [200, 200], "max_size": [200, 500], "color": [0, 0, 255], "privacy": "private"}}}, {"position": [300, 328.5], "orientation": "vertical", "room1": {"value": 1, "cut_percentage": 0.5485155499134747, "children": [], "room_type": {"name": "bedroom", "min_size": [200, 200], "max_size": [200, 500], "color": [0, 0, 255], "privacy": "private"}}, "room2": {"value": 2, "cut_percentage": 0.5194799230593059, "children": [], "room_type": {"name": "bathroom", "min_size": [150, 200], "max_size": [150, 250], "color": [255, 155, 20], "privacy": "private"}}}]}]], [{"node": {"value": 5, "cut_percentage": 0.37376608750857393, "children": [], "room_type": {"name": "bedroom", "min_size": [200, 200], "max_size": [200, 500], "color": [0, 0, 255], "privacy": "private"}}, "rect": [0, 490, 300, 309], "neighbors": [{"value": 2, "cut_percentage": 0.5194799230593059, "children": [], "room_type": {"name": "bathroom", "min_size": [150, 200], "max_size": [150, 250], "color": [255, 155, 20], "privacy": "private"}}, {"value": 1, "cut_percentage": 0.5485155499134747, "children": [], "room_type": {"name": "bedroom", "min_size": [200, 200], "max_size": [200, 500], "color": [0, 0, 255], "privacy": "private"}}], "objects": [{"name": "Bed", "object_type": {"name": "Bed", "effect": {"energy": 50}}, "interaction_time": 4.7, "position": [75.0, 644.5]}], "doors": [{"position": [150.0, 490], "orientation": "horizontal", "room1": {"value": 2, "cut_percentage": 0.5194799230593059, "children": [], "room_type": {"name": "bathroom", "min_size": [150, 200], "max_size": [150, 250], "color": [255, 155, 20], "privacy": "private"}}, "room2": {"value": 5, "cut_percentage": 0.37376608750857393, "children": [], "room_type": {"name": "bedroom", "min_size": [200, 200], "max_size": [200, 500], "color": [0, 0, 255], "privacy": "private"}}}, {"position": [300, 644.5], "orientation": "vertical", "room1": {"value": 5, "cut_percentage": 0.37376608750857393, "children": [], "room_type": {"name": "bedroom", "min_size": [200, 200], "max_size": [200, 500], "color": [0, 0, 255], "privacy": "private"}}, "room2": {"value": 1, "cut_percentage": 0.5485155499134747, "children": [], "room_type": {"name": "bedroom", "min_size": [200, 200], "max_size": [200, 500], "color": [0, 0, 255], "privacy": "private"}}}]}, [{"node": {"value": 2, "cut_percentage": 0.5194799230593059, "children": [], "room_type": {"name": "bathroom", "min_size": [150, 200], "max_size": [150, 250], "color": [255, 155, 20], "privacy": "private"}}, "rect": [0, 0, 300, 490], "neighbors": [{"value": 5, "cut_percentage": 0.37376608750857393, "children": [], "room_type": {"name": "bedroom", "min_size": [200, 200], "max_size": [200, 500], "color": [0, 0, 255], "privacy": "private"}}, {"value": 4, "cut_percentage": 0.5507690621695321, "children": [], "room_type": {"name": "bathroom", "min_size": [150, 200], "max_size": [150, 250], "color": [255, 155, 20], "privacy": "private"}}, {"value": 1, "cut_percentage": 0.5485155499134747, "children": [], "room_type": {"name": "bedroom", "min_size": [200, 200], "max_size": [200, 500], "color": [0, 0, 255], "privacy": "private"}}], "objects": [{"name": "Toilet", "object_type": {"name": "Toilet", "effect": {"bladder": 60}}, "interaction_time": 0.3, "position": [75.0, 122.5]}, {"name": "Shower", "object_type": {"name": "Shower", "effect": {"hygiene": 60}}, "interaction_time": 0.1, "position": [225.0, 367.5]}], "doors": [{"position": [150.0, 490], "orientation": "horizontal", "room1": {"value": 2, "cut_percentage": 0.5194799230593059, "children": [], "room_type": {"name": "bathroom", "min_size": [150, 200], "max_size": [150, 250], "color": [255, 155, 20], "privacy": "private"}}, "room2": {"value": 5, "cut_percentage": 0.37376608750857393, "children": [], "room_type": {"name": "bedroom", "min_size": [200, 200], "max_size": [200, 500], "color": [0, 0, 255], "privacy": "private"}}}, {"position": [300, 83.5], "orientation": "vertical", "room1": {"value": 4, "cut_percentage": 0.5507690621695321, "children": [], "room_type": {"name": "bathroom", "min_size": [150, 200], "max_size": [150, 250], "color": [255, 155, 20], "privacy": "private"}}, "room2": {"value": 2, "cut_percentage": 0.5194799230593059, "children": [], "room_type": {"name": "bathroom", "min_size": [150, 200], "max_size": [150, 250], "color": [255, 155, 20], "privacy": "private"}}}, {"position": [300, 328.5], "orientation": "vertical", "room1": {"value": 1, "cut_percentage": 0.5485155499134747, "children": [], "room_type": {"name": "bedroom", "min_size": [200, 200], "max_size": [200, 500], "color": [0, 0, 255], "privacy": "private"}}, "room2": {"value": 2, "cut_percentage": 0.5194799230593059, "children": [], "room_type": {"name": "bathroom", "min_size": [150, 200], "max_size": [150, 250], "color": [255, 155, 20], "privacy": "private"}}}]}, {"node": {"value": 1, "cut_percentage": 0.5485155499134747, "children": [], "room_type": {"name": "bedroom", "min_size": [200, 200], "max_size": [200, 500], "color": [0, 0, 255], "privacy": "private"}}, "rect": [300, 167, 496, 632], "neighbors": [{"value": 2, "cut_percentage": 0.5194799230593059, "children": [], "room_type": {"name": "bathroom", "min_size": [150, 200], "max_size": [150, 250], "color": [255, 155, 20], "privacy": "private"}}, {"value": 5, "cut_percentage": 0.37376608750857393, "children": [], "room_type": {"name": "bedroom", "min_size": [200, 200], "max_size": [200, 500], "color": [0, 0, 255], "privacy": "private"}}, {"value": 4, "cut_percentage": 0.5507690621695321, "children": [], "room_type": {"name": "bathroom", "min_size": [150, 200], "max_size": [150, 250], "color": [255, 155, 20], "privacy": "private"}}, {"value": 3, "cut_percentage": 0.6430151812707887, "children": [], "room_type": {"name": "bedroom", "min_size": [200, 200], "max_size": [200, 500], "color": [0, 0, 255], "privacy": "private"}}], "objects": [{"name": "Bed", "object_type": {"name": "Bed", "effect": {"energy": 50}}, "interaction_time": 4.7, "position": [672.0, 325.0]}], "doors": [{"position": [300, 644.5], "orientation": "vertical", "room1": {"value": 5, "cut_percentage": 0.37376608750857393, "children": [], "room_type": {"name": "bedroom", "min_size": [200, 200], "max_size": [200, 500], "color": [0, 0, 255], "privacy": "private"}}, "room2": {"value": 1, "cut_percentage": 0.5485155499134747, "children": [], "room_type": {"name": "bedroom", "min_size": [200, 200], "max_size": [200, 500], "color": [0, 0, 255], "privacy": "private"}}}, {"position": [300, 328.5], "orientation": "vertical", "room1": {"value": 1, "cut_percentage": 0.5485155499134747, "children": [], "room_type": {"name": "bedroom", "min_size": [200, 200], "max_size": [200, 500], "color": [0, 0, 255], "privacy": "private"}}, "room2": {"value": 2, "cut_percentage": 0.5194799230593059, "children": [], "room_type": {"name": "bathroom", "min_size": [150, 200], "max_size": [150, 250], "color": [255, 155, 20], "privacy": "private"}}}]}]], [{"node": {"value": 4, "cut_percentage": 0.5507690621695321, "children": [], "room_type": {"name": "bathroom", "min_size": [150, 200], "max_size": [150, 250], "color": [255, 155, 20], "privacy": "private"}}, "rect": [300, 0, 496, 167], "neighbors": [{"value": 2, "cut_percentage": 0.5194799230593059, "children": [], "room_type": {"name": "bathroom", "min_size": [150, 200], "max_size": [150, 250], "color": [255, 155, 20], "privacy": "private"}}, {"value": 1, "cut_percentage": 0.5485155499134747, "children": [], "room_type": {"name": "bedroom", "min_size": [200, 200], "max_size": [200, 500], "color": [0, 0, 255], "privacy": "private"}}, {"value": 3, "cut_percentage": 0.6430151812707887, "children": [], "room_type": {"name": "bedroom", "min_size": [200, 200], "max_size": [200, 500], "color": [0, 0, 255], "privacy": "private"}}], "objects": [{"name": "Toilet", "object_type": {"name": "Toilet", "effect": {"bladder": 60}}, "interaction_time": 0.3, "position": [672.0, 125.25]}, {"name": "Shower", "object_type": {"name": "Shower", "effect": {"hygiene": 60}}, "interaction_time": 0.1, "position": [672.0, 41.75]}], "doors": [{"position": [300, 83.5], "orientation": "vertical", "room1": {"value": 4, "cut_percentage": 0.5507690621695321, "children": [], "room_type": {"name": "bathroom", "min_size": [150, 200], "max_size": [150, 250], "color": [255, 155, 20], "privacy": "private"}}, "room2": {"value": 2, "cut_percentage": 0.5194799230593059, "children": [], "room_type": {"name": "bathroom", "min_size": [150, 200], "max_size": [150, 250], "color": [255, 155, 20], "privacy": "private"}}}, {"position": [796, 83.5], "orientation": "vertical", "room1": {"value": 3, "cut_percentage": 0.6430151812707887, "children": [], "room_type": {"name": "bedroom", "min_size": [200, 200], "max_size": [200, 500], "color": [0, 0, 255], "privacy": "private"}}, "room2": {"value": 4, "cut_percentage": 0.5507690621695321, "children": [], "room_type": {"name": "bathroom", "min_size": [150, 200], "max_size": [150, 250], "color": [255, 155, 20], "privacy": "private"}}}]}, [{"node": {"value": 2, "cut_percentage": 0.5194799230593059, "children": [], "room_type": {"name": "bathroom", "min_size": [150, 200], "max_size": [150, 250], "color": [255, 155, 20], "privacy": "private"}}, "rect": [0, 0, 300, 490], "neighbors": [{"value": 5, "cut_percentage": 0.37376608750857393, "children": [], "room_type": {"name": "bedroom", "min_size": [200, 200], "max_size": [200, 500], "color": [0, 0, 255], "privacy": "private"}}, {"value": 4, "cut_percentage": 0.5507690621695321, "children": [], "room_type": {"name": "bathroom", "min_size": [150, 200], "max_size": [150, 250], "color": [255, 155, 20], "privacy": "private"}}, {"value": 1, "cut_percentage": 0.5485155499134747, "children": [], "room_type": {"name": "bedroom", "min_size": [200, 200], "max_size": [200, 500], "color": [0, 0, 255], "privacy": "private"}}], "objects": [{"name": "Toilet", "object_type": {"name": "Toilet", "effect": {"bladder": 60}}, "interaction_time": 0.3, "position": [75.0, 122.5]}, {"name": "Shower", "object_type": {"name": "Shower", "effect": {"hygiene": 60}}, "interaction_time": 0.1, "position": [225.0, 367.5]}], "doors": [{"position": [150.0, 490], "orientation": "horizontal", "room1": {"value": 2, "cut_percentage": 0.5194799230593059, "children": [], "room_type": {"name": "bathroom", "min_size": [150, 200], "max_size": [150, 250], "color": [255, 155, 20], "privacy": "private"}}, "room2": {"value": 5, "cut_percentage": 0.37376608750857393, "children": [], "room_type": {"name": "bedroom", "min_size": [200, 200], "max_size": [200, 500], "color": [0, 0, 255], "privacy": "private"}}}, {"position": [300, 83.5], "orientation": "vertical", "room1": {"value": 4, "cut_percentage": 0.5507690621695321, "children": [], "room_type": {"name": "bathroom", "min_size": [150, 200], "max_size": [150, 250], "color": [255, 155, 20], "privacy": "private"}}, "room2": {"value": 2, "cut_percentage": 0.5194799230593059, "children": [], "room_type": {"name": "bathroom", "min_size": [150, 200], "max_size": [150, 250], "color": [255, 155, 20], "privacy": "private"}}}, {"position": [300, 328.5], "orientation": "vertical", "room1": {"value": 1, "cut_percentage": 0.5485155499134747, "children": [], "room_type": {"name": "bedroom", "min_size": [200, 200], "max_size": [200, 500], "color": [0, 0, 255], "privacy": "private"}}, "room2": {"value": 2, "cut_percentage": 0.5194799230593059, "children": [], "room_type": {"name": "bathroom", "min_size": [150, 200], "max_size": [150, 250], "color": [255, 155, 20], "privacy": "private"}}}]}, {"node": {"value": 3, "cut_percentage": 0.6430151812707887, "children": [], "room_type": {"name": "bedroom", "min_size": [200, 200], "max_size": [200, 500], "color": [0, 0, 255], "privacy": "private"}}, "rect": [796, 0, 202, 800], "neighbors": [{"value": 4, "cut_percentage": 0.5507690621695321, "children": [], "room_type": {"name": "bathroom", "min_size": [150, 200], "max_size": [150, 250], "color": [255, 155, 20], "privacy": "private"}}, {"value": 1, "cut_percentage": 0.5485155499134747, "children": [], "room_type": {"name": "bedroom", "min_size": [200, 200], "max_size": [200, 500], "color": [0, 0, 255], "privacy": "private"}}], "objects": [{"name": "Bed", "object_type": {"name": "Bed", "effect": {"energy": 50}}, "interaction_time": 4.7, "position": [947.5, 600.0]}], "doors": [{"position": [796, 83.5], "orientation": "vertical", "room1": {"value": 3, "cut_percentage": 0.6430151812707887, "children": [], "room_type": {"name": "bedroom", "min_size": [200, 200], "max_size": [200, 500], "color": [0, 0, 255], "privacy": "private"}}, "room2": {"value": 4, "cut_percentage": 0.5507690621695321, "children": [], "room_type": {"name": "bathroom", "min_size": [150, 200], "max_size": [150, 250], "color": [255, 155, 20], "privacy": "private"}}}]}]], [{"node": {"value": 1, "cut_percentage": 0.5485155499134747, "children": [], "room_type": {"name": "bedroom", "min_size": [200, 200], "max_size": [200, 500], "color": [0, 0, 255], "privacy": "private"}}, "rect": [300, 167, 496, 632], "neighbors": [{"value": 2, "cut_percentage": 0.5194799230593059, "children": [], "room_type": {"name": "bathroom", "min_size": [150, 200], "max_size": [150, 250], "color": [255, 155, 20], "privacy": "private"}}, {"value": 5, "cut_percentage": 0.37376608750857393, "children": [], "room_type": {"name": "bedroom", "min_size": [200, 200], "max_size": [200, 500], "color": [0, 0, 255], "privacy": "private"}}, {"value": 4, "cut_percentage": 0.5507690621695321, "children": [], "room_type": {"name": "bathroom", "min_size": [150, 200], "max_size": [150, 250], "color": [255, 155, 20], "privacy": "private"}}, {"value": 3, "cut_percentage": 0.6430151812707887, "children": [], "room_type": {"name": "bedroom", "min_size": [200, 200], "max_size": [200, 500], "color": [0, 0, 255], "privacy": "private"}}], "objects": [{"name": "Bed", "object_type": {"name": "Bed", "effect": {"energy": 50}}, "interaction_time": 4.7, "position": [672.0, 325.0]}], "doors": [{"position": [300, 644.5], "orientation": "vertical", "room1": {"value": 5, "cut_percentage": 0.37376608750857393, "children": [], "room_type": {"name": "bedroom", "min_size": [200, 200], "max_size": [200, 500], "color": [0, 0, 255], "privacy": "private"}}, "room2": {"value": 1, "cut_percentage": 0.5485155499134747, "children": [], "room_type": {"name": "bedroom", "min_size": [200, 200], "max_size": [200, 500], "color": [0, 0, 255], "privacy": "private"}}}, {"position": [300, 328.5], "orientation": "vertical", "room1": {"value": 1, "cut_percentage": 0.5485155499134747, "children": [], "room_type": {"name": "bedroom", "min_size": [200, 200], "max_size": [200, 500], "color": [0, 0, 255], "privacy": "private"}}, "room2": {"value": 2, "cut_percentage": 0.5194799230593059, "children": [], "room_type": {"name": "bathroom", "min_size": [150, 200], "max_size": [150, 250], "color": [255, 155, 20], "privacy": "private"}}}]}, [{"node": {"value": 5, "cut_percentage": 0.37376608750857393, "children": [], "room_type": {"name": "bedroom", "min_size": [200, 200], "max_size": [200, 500], "color": [0, 0, 255], "privacy": "private"}}, "rect": [0, 490, 300, 309], "neighbors": [{"value": 2, "cut_percentage": 0.5194799230593059, "children": [], "room_type": {"name": "bathroom", "min_size": [150, 200], "max_size": [150, 250], "color": [255, 155, 20], "privacy": "private"}}, {"value": 1, "cut_percentage": 0.5485155499134747, "children": [], "room_type": {"name": "bedroom", "min_size": [200, 200], "max_size": [200, 500], "color": [0, 0, 255], "privacy": "private"}}], "objects": [{"name": "Bed", "object_type": {"name": "Bed", "effect": {"energy": 50}}, "interaction_time": 4.7, "position": [75.0, 644.5]}], "doors": [{"position": [150.0, 490], "orientation": "horizontal", "room1": {"value": 2, "cut_percentage": 0.5194799230593059, "children": [], "room_type": {"name": "bathroom", "min_size": [150, 200], "max_size": [150, 250], "color": [255, 155, 20], "privacy": "private"}}, "room2": {"value": 5, "cut_percentage": 0.37376608750857393, "children": [], "room_type": {"name": "bedroom", "min_size": [200, 200], "max_size": [200, 500], "color": [0, 0, 255], "privacy": "private"}}}, {"position": [300, 644.5], "orientation": "vertical", "room1": {"value": 5, "cut_percentage": 0.37376608750857393, "children": [], "room_type": {"name": "bedroom", "min_size": [200, 200], "max_size": [200, 500], "color": [0, 0, 255], "privacy": "private"}}, "room2": {"value": 1, "cut_percentage": 0.5485155499134747, "children": [], "room_type": {"name": "bedroom", "min_size": [200, 200], "max_size": [200, 500], "color": [0, 0, 255], "privacy": "private"}}}]}, {"node": {"value": 2, "cut_percentage": 0.5194799230593059, "children": [], "room_type": {"name": "bathroom", "min_size": [150, 200], "max_size": [150, 250], "color": [255, 155, 20], "privacy": "private"}}, "rect": [0, 0, 300, 490], "neighbors": [{"value": 5, "cut_percentage": 0.37376608750857393, "children": [], "room_type": {"name": "bedroom", "min_size": [200, 200], "max_size": [200, 500], "color": [0, 0, 255], "privacy": "private"}}, {"value": 4, "cut_percentage": 0.5507690621695321, "children": [], "room_type": {"name": "bathroom", "min_size": [150, 200], "max_size": [150, 250], "color": [255, 155, 20], "privacy": "private"}}, {"value": 1, "cut_percentage": 0.5485155499134747, "children": [], "room_type": {"name": "bedroom", "min_size": [200, 200], "max_size": [200, 500], "color": [0, 0, 255], "privacy": "private"}}], "objects": [{"name": "Toilet", "object_type": {"name": "Toilet", "effect": {"bladder": 60}}, "interaction_time": 0.3, "position": [75.0, 122.5]}, {"name": "Shower", "object_type": {"name": "Shower", "effect": {"hygiene": 60}}, "interaction_time": 0.1, "position": [225.0, 367.5]}], "doors": [{"position": [150.0, 490], "orientation": "horizontal", "room1": {"value": 2, "cut_percentage": 0.5194799230593059, "children": [], "room_type": {"name": "bathroom", "min_size": [150, 200], "max_size": [150, 250], "color": [255, 155, 20], "privacy": "private"}}, "room2": {"value": 5, "cut_percentage": 0.37376608750857393, "children": [], "room_type": {"name": "bedroom", "min_size": [200, 200], "max_size": [200, 500], "color": [0, 0, 255], "privacy": "private"}}}, {"position": [300, 83.5], "orientation": "vertical", "room1": {"value": 4, "cut_percentage": 0.5507690621695321, "children": [], "room_type": {"name": "bathroom", "min_size": [150, 200], "max_size": [150, 250], "color": [255, 155, 20], "privacy": "private"}}, "room2": {"value": 2, "cut_percentage": 0.5194799230593059, "children": [], "room_type": {"name": "bathroom", "min_size": [150, 200], "max_size": [150, 250], "color": [255, 155, 20], "privacy": "private"}}}, {"position": [300, 328.5], "orientation": "vertical", "room1": {"value": 1, "cut_percentage": 0.5485155499134747, "children": [], "room_type": {"name": "bedroom", "min_size": [200, 200], "max_size": [200, 500], "color": [0, 0, 255], "privacy": "private"}}, "room2": {"value": 2, "cut_percentage": 0.5194799230593059, "children": [], "room_type": {"name": "bathroom", "min_size": [150, 200], "max_size": [150, 250], "color": [255, 155, 20], "privacy": "private"}}}]}]], [{"node": {"value": 3, "cut_percentage": 0.6430151812707887, "children": [], "room_type": {"name": "bedroom", "min_size": [200, 200], "max_size": [200, 500], "color": [0, 0, 255], "privacy": "private"}}, "rect": [796, 0, 202, 800], "neighbors": [{"value": 4, "cut_percentage": 0.5507690621695321, "children": [], "room_type": {"name": "bathroom", "min_size": [150, 200], "max_size": [150, 250], "color": [255, 155, 20], "privacy": "private"}}, {"value": 1, "cut_percentage": 0.5485155499134747, "children": [], "room_type": {"name": "bedroom", "min_size": [200, 200], "max_size": [200, 500], "color": [0, 0, 255], "privacy": "private"}}], "objects": [{"name": "Bed", "object_type": {"name": "Bed", "effect": {"energy": 50}}, "interaction_time": 4.7, "position": [947.5, 600.0]}], "doors": [{"position": [796, 83.5], "orientation": "vertical", "room1": {"value": 3, "cut_percentage": 0.6430151812707887, "children": [], "room_type": {"name": "bedroom", "min_size": [200, 200], "max_size": [200, 500], "color": [0, 0, 255], "privacy": "private"}}, "room2": {"value": 4, "cut_percentage": 0.5507690621695321, "children": [], "room_type": {"name": "bathroom", "min_size": [150, 200], "max_size": [150, 250], "color": [255, 155, 20], "privacy": "private"}}}]}, [{"node": {"value": 4, "cut_percentage": 0.5507690621695321, "children": [], "room_type": {"name": "bathroom", "min_size": [150, 200], "max_size": [150, 250], "color": [255, 155, 20], "privacy": "private"}}, "rect": [300, 0, 496, 167], "neighbors": [{"value": 2, "cut_percentage": 0.5194799230593059, "children": [], "room_type": {"name": "bathroom", "min_size": [150, 200], "max_size": [150, 250], "color": [255, 155, 20], "privacy": "private"}}, {"value": 1, "cut_percentage": 0.5485155499134747, "children": [], "room_type": {"name": "bedroom", "min_size": [200, 200], "max_size": [200, 500], "color": [0, 0, 255], "privacy": "private"}}, {"value": 3, "cut_percentage": 0.6430151812707887, "children": [], "room_type": {"name": "bedroom", "min_size": [200, 200], "max_size": [200, 500], "color": [0, 0, 255], "privacy": "private"}}], "objects": [{"name": "Toilet", "object_type": {"name": "Toilet", "effect": {"bladder": 60}}, "interaction_time": 0.3, "position": [672.0, 125.25]}, {"name": "Shower", "object_type": {"name": "Shower", "effect": {"hygiene": 60}}, "interaction_time": 0.1, "position": [672.0, 41.75]}], "doors": [{"position": [300, 83.5], "orientation": "vertical", "room1": {"value": 4, "cut_percentage": 0.5507690621695321, "children": [], "room_type": {"name": "bathroom", "min_size": [150, 200], "max_size": [150, 250], "color": [255, 155, 20], "privacy": "private"}}, "room2": {"value": 2, "cut_percentage": 0.5194799230593059, "children": [], "room_type": {"name": "bathroom", "min_size": [150, 200], "max_size": [150, 250], "color": [255, 155, 20], "privacy": "private"}}}, {"position": [796, 83.5], "orientation": "vertical", "room1": {"value": 3, "cut_percentage": 0.6430151812707887, "children": [], "room_type": {"name": "bedroom", "min_size": [200, 200], "max_size": [200, 500], "color": [0, 0, 255], "privacy": "private"}}, "room2": {"value": 4, "cut_percentage": 0.5507690621695321, "children": [], "room_type": {"name": "bathroom", "min_size": [150, 200], "max_size": [150, 250], "color": [255, 155, 20], "privacy": "private"}}}]}]]], "fitness": 6, "agents_paths": {"Agent 1": [[["private", "bedroom"], ["private", "bathroom"]], [["private", "bathroom"], ["private", "bedroom"]], [["private", "bedroom"], ["private", "bathroom"]], [["private", "bathroom"]], [["private", "bathroom"]], [["private", "bathroom"], ["private", "bathroom"]], [["private", "bathroom"], ["private", "bedroom"]], [["private", "bedroom"], ["private", "bathroom"], ["private", "bathroom"]], [["private", "bathroom"]], [["private", "bathroom"], ["private", "bathroom"]], [["private", "bathroom"], ["private", "bathroom"]], [["private", "bathroom"], ["private", "bathroom"]], [["private", "bathroom"], ["private", "bathroom"]], [["private", "bathroom"], ["private", "bathroom"]], [["private", "bathroom"], ["private", "bathroom"]], [["private", "bathroom"], ["private", "bathroom"]], [["private", "bathroom"], ["private", "bathroom"]], [["private", "bathroom"], ["private", "bathroom"]], [["private", "bathroom"], ["private", "bedroom"]], [["private", "bedroom"], ["private", "bathroom"], ["private", "bathroom"]], [["private", "bathroom"]], [["private", "bathroom"], ["private", "bathroom"]], [["private", "bathroom"]], [["private", "bathroom"], ["private", "bedroom"]]], "Agent 2": [[["private", "bedroom"], ["private", "bathroom"]], [["private", "bathroom"], ["private", "bedroom"]], [["private", "bedroom"], ["private", "bathroom"], ["private", "bathroom"]], [["private", "bathroom"], ["private", "bathroom"]], [["private", "bathroom"], ["private", "bathroom"]], [["private", "bathroom"], ["private", "bathroom"]], [["private", "bathroom"], ["private", "bathroom"], ["private", "bedroom"]], [["private", "bedroom"], ["private", "bathroom"]], [["private", "bathroom"], ["private", "bathroom"]], [["private", "bathroom"]], [["private", "bathroom"], ["private", "bathroom"]], [["private", "bathroom"], ["private", "bathroom"]], [["private", "bathroom"], ["private", "bathroom"], ["private", "bedroom"]], [["private", "bedroom"], ["private", "bathroom"], ["private", "bathroom"]], [["private", "bathroom"], ["private", "bathroom"]], [["private", "bathroom"], ["private", "bathroom"]], [["private", "bathroom"]], [["private", "bathroom"], ["private", "bathroom"], ["private", "bedroom"]]]}, "agents_activites": {"Agent 1": [["Agent 1", " interacting with ", "Toilet", " current time in minutes ", "30", " expected interaction finish time ", "48.0", " the interaction in hours: ", "0.3"], ["Agent 1", " interacting with ", "Bed", " current time in minutes ", "60", " expected interaction finish time ", "342.0", " the interaction in hours: ", "4.7"], ["Agent 1", " interacting with ", "Shower", " current time in minutes ", "353", " expected interaction finish time ", "359.0", " the interaction in hours: ", "0.1"], ["Agent 1", " interacting with ", "Toilet", " current time in minutes ", "370", " expected interaction finish time ", "388.0", " the interaction in hours: ", "0.3"], ["Agent 1", " interacting with ", "Shower", " current time in minutes ", "394", " expected interaction finish time ", "400.0", " the interaction in hours: ", "0.1"], ["Agent 1", " interacting with ", "Toilet", " current time in minutes ", "411", " expected interaction finish time ", "429.0", " the interaction in hours: ", "0.3"], ["Agent 1", " interacting with ", "Bed", " current time in minutes ", "439", " expected interaction finish time ", "721.0", " the interaction in hours: ", "4.7"], ["Agent 1", " interacting with ", "Shower", " current time in minutes ", "747", " expected interaction finish time ", "753.0", " the interaction in hours: ", "0.1"], ["Agent 1", " interacting with ", "Shower", " current time in minutes ", "757", " expected interaction finish time ", "763.0", " the interaction in hours: ", "0.1"], ["Agent 1", " interacting with ", "Toilet", " current time in minutes ", "777", " expected interaction finish time ", "795.0", " the interaction in hours: ", "0.3"], ["Agent 1", " interacting with ", "Toilet", " current time in minutes ", "806", " expected interaction finish time ", "824.0", " the interaction in hours: ", "0.3"], ["Agent 1", " interacting with ", "Toilet", " current time in minutes ", "835", " expected interaction finish time ", "853.0", " the interaction in hours: ", "0.3"], ["Agent 1", " interacting with ", "Shower", " current time in minutes ", "863", " expected interaction finish time ", "869.0", " the interaction in hours: ", "0.1"], ["Agent 1", " interacting with ", "Shower", " current time in minutes ", "880", " expected interaction finish time ", "886.0", " the interaction in hours: ", "0.1"], ["Agent 1", " interacting with ", "Shower", " current time in minutes ", "898", " expected interaction finish time ", "904.0", " the interaction in hours: ", "0.1"], ["Agent 1", " interacting with ", "Shower", " current time in minutes ", "923", " expected interaction finish time ", "929.0", " the interaction in hours: ", "0.1"], ["Agent 1", " interacting with ", "Shower", " current time in minutes ", "941", " expected interaction finish time ", "947.0", " the interaction in hours: ", "0.1"], ["Agent 1", " interacting with ", "Toilet", " current time in minutes ", "958", " expected interaction finish time ", "976.0", " the interaction in hours: ", "0.3"], ["Agent 1", " interacting with ", "Bed", " current time in minutes ", "986", " expected interaction finish time ", "1268.0", " the interaction in hours: ", "4.7"], ["Agent 1", " interacting with ", "Toilet", " current time in minutes ", "1293", " expected interaction finish time ", "1311.0", " the interaction in hours: ", "0.3"], ["Agent 1", " interacting with ", "Shower", " current time in minutes ", "1315", " expected interaction finish time ", "1321.0", " the interaction in hours: ", "0.1"], ["Agent 1", " interacting with ", "Shower", " current time in minutes ", "1349", " expected interaction finish time ", "1355.0", " the interaction in hours: ", "0.1"], ["Agent 1", " interacting with ", "Shower", " current time in minutes ", "1359", " expected interaction finish time ", "1365.0", " the interaction in hours: ", "0.1"], ["Agent 1", " interacting with ", "Bed", " current time in minutes ", "1372", " expected interaction finish time ", "1654.0", " the interaction in hours: ", "4.7"]], "Agent 2": [["Agent 2", " interacting with ", "Toilet", " current time in minutes ", "32", " expected interaction finish time ", "50.0", " the interaction in hours: ", "0.3"], ["Agent 2", " interacting with ", "Bed", " current time in minutes ", "63", " expected interaction finish time ", "345.0", " the interaction in hours: ", "4.7"], ["Agent 2", " interacting with ", "Shower", " current time in minutes ", "370", " expected interaction finish time ", "376.0", " the interaction in hours: ", "0.1"], ["Agent 2", " interacting with ", "Toilet", " current time in minutes ", "391", " expected interaction finish time ", "409.0", " the interaction in hours: ", "0.3"], ["Agent 2", " interacting with ", "Shower", " current time in minutes ", "362", " expected interaction finish time ", "368.0", " the interaction in hours: ", "0.1"], ["Agent 2", " interacting with ", "Bed", " current time in minutes ", "444", " expected interaction finish time ", "726.0", " the interaction in hours: ", "4.7"], ["Agent 2", " interacting with ", "Shower", " current time in minutes ", "740", " expected interaction finish time ", "746.0", " the interaction in hours: ", "0.1"], ["Agent 2", " interacting with ", "Toilet", " current time in minutes ", "757", " expected interaction finish time ", "775.0", " the interaction in hours: ", "0.3"], ["Agent 2", " interacting with ", "Shower", " current time in minutes ", "721", " expected interaction finish time ", "727.0", " the interaction in hours: ", "0.1"], ["Agent 2", " interacting with ", "Shower", " current time in minutes ", "798", " expected interaction finish time ", "804.0", " the interaction in hours: ", "0.1"], ["Agent 2", " interacting with ", "Toilet", " current time in minutes ", "814", " expected interaction finish time ", "832.0", " the interaction in hours: ", "0.3"], ["Agent 2", " interacting with ", "Bed", " current time in minutes ", "790", " expected interaction finish time ", "1072.0", " the interaction in hours: ", "4.7"], ["Agent 2", " interacting with ", "Toilet", " current time in minutes ", "1029", " expected interaction finish time ", "1047.0", " the interaction in hours: ", "0.3"], ["Agent 2", " interacting with ", "Toilet", " current time in minutes ", "1105", " expected interaction finish time ", "1123.0", " the interaction in hours: ", "0.3"], ["Agent 2", " interacting with ", "Shower", " current time in minutes ", "1135", " expected interaction finish time ", "1141.0", " the interaction in hours: ", "0.1"], ["Agent 2", " interacting with ", "Toilet", " current time in minutes ", "1161", " expected interaction finish time ", "1179.0", " the interaction in hours: ", "0.3"], ["Agent 2", " interacting with ", "Bed", " current time in minutes ", "1197", " expected interaction finish time ", "1479.0", " the interaction in hours: ", "4.7"]]}, "neighbouring_rooms": {"bathroom": ["bathroom", "bedroom", "bedroom"], "bedroom": ["bathroom", "bedroom"]}, "mutated": false, "crossover": false, "parent1": null, "parent2": null, "mutation_probability": null, "agents_have_bedrooms": 0}