{"num_rooms": 5, "room_types": [{"name": "bedroom", "min_size": [200, 200], "max_size": [200, 500], "color": [0, 0, 255], "privacy": "private"}, {"name": "kitchen", "min_size": [200, 350], "max_size": [300, 500], "color": [255, 0, 0], "privacy": "common"}, {"name": "bedroom", "min_size": [200, 200], "max_size": [200, 500], "color": [0, 0, 255], "privacy": "private"}, {"name": "bathroom", "min_size": [150, 200], "max_size": [150, 250], "color": [255, 155, 20], "privacy": "private"}, {"name": "bedroom", "min_size": [200, 200], "max_size": [200, 500], "color": [0, 0, 255], "privacy": "private"}], "slicing_tree_root": {"value": "V", "cut_percentage": 0.2896415985936344, "children": [{"value": 1, "cut_percentage": 0.5125031118211831, "children": [], "room_type": {"name": "bedroom", "min_size": [200, 200], "max_size": [200, 500], "color": [0, 0, 255], "privacy": "private"}}, {"value": "H", "cut_percentage": 0.611571884299394, "children": [{"value": "H", "cut_percentage": 0.50872918366098, "children": [{"value": 3, "cut_percentage": 0.5257659898189596, "children": [], "room_type": {"name": "bedroom", "min_size": [200, 200], "max_size": [200, 500], "color": [0, 0, 255], "privacy": "private"}}, {"value": 5, "cut_percentage": 0.49269040806425657, "children": [], "room_type": {"name": "bedroom", "min_size": [200, 200], "max_size": [200, 500], "color": [0, 0, 255], "privacy": "private"}}], "room_type": null}, {"value": "V", "cut_percentage": 0.5405021406946368, "children": [{"value": 2, "cut_percentage": 0.4355764966075982, "children": [], "room_type": {"name": "bathroom", "min_size": [150, 200], "max_size": [150, 250], "color": [255, 155, 20], "privacy": "private"}}, {"value": 4, "cut_percentage": 0.6353655069621529, "children": [], "room_type": {"name": "bedroom", "min_size": [200, 200], "max_size": [200, 500], "color": [0, 0, 255], "privacy": "private"}}], "room_type": null}], "room_type": null}], "room_type": null}, "rooms": [{"node": {"value": 1, "cut_percentage": 0.5125031118211831, "children": [], "room_type": {"name": "bedroom", "min_size": [200, 200], "max_size": [200, 500], "color": [0, 0, 255], "privacy": "private"}}, "rect": [0, 0, 289, 800], "neighbors": [{"value": 3, "cut_percentage": 0.5257659898189596, "children": [], "room_type": {"name": "bedroom", "min_size": [200, 200], "max_size": [200, 500], "color": [0, 0, 255], "privacy": "private"}}, {"value": 5, "cut_percentage": 0.49269040806425657, "children": [], "room_type": {"name": "bedroom", "min_size": [200, 200], "max_size": [200, 500], "color": [0, 0, 255], "privacy": "private"}}, {"value": 2, "cut_percentage": 0.4355764966075982, "children": [], "room_type": {"name": "bathroom", "min_size": [150, 200], "max_size": [150, 250], "color": [255, 155, 20], "privacy": "private"}}], "objects": [{"name": "Bed", "object_type": {"name": "Bed", "effect": {"energy": 50}}, "interaction_time": 4.7, "position": [216.75, 200.0]}], "doors": [{"position": [289, 124.0], "orientation": "vertical", "room1": {"value": 1, "cut_percentage": 0.5125031118211831, "children": [], "room_type": {"name": "bedroom", "min_size": [200, 200], "max_size": [200, 500], "color": [0, 0, 255], "privacy": "private"}}, "room2": {"value": 3, "cut_percentage": 0.5257659898189596, "children": [], "room_type": {"name": "bedroom", "min_size": [200, 200], "max_size": [200, 500], "color": [0, 0, 255], "privacy": "private"}}}, {"position": [289, 368.0], "orientation": "vertical", "room1": {"value": 5, "cut_percentage": 0.49269040806425657, "children": [], "room_type": {"name": "bedroom", "min_size": [200, 200], "max_size": [200, 500], "color": [0, 0, 255], "privacy": "private"}}, "room2": {"value": 1, "cut_percentage": 0.5125031118211831, "children": [], "room_type": {"name": "bedroom", "min_size": [200, 200], "max_size": [200, 500], "color": [0, 0, 255], "privacy": "private"}}}, {"position": [289, 644.0], "orientation": "vertical", "room1": {"value": 2, "cut_percentage": 0.4355764966075982, "children": [], "room_type": {"name": "bathroom", "min_size": [150, 200], "max_size": [150, 250], "color": [255, 155, 20], "privacy": "private"}}, "room2": {"value": 1, "cut_percentage": 0.5125031118211831, "children": [], "room_type": {"name": "bedroom", "min_size": [200, 200], "max_size": [200, 500], "color": [0, 0, 255], "privacy": "private"}}}]}, {"node": {"value": 3, "cut_percentage": 0.5257659898189596, "children": [], "room_type": {"name": "bedroom", "min_size": [200, 200], "max_size": [200, 500], "color": [0, 0, 255], "privacy": "private"}}, "rect": [289, 0, 710, 248], "neighbors": [{"value": 1, "cut_percentage": 0.5125031118211831, "children": [], "room_type": {"name": "bedroom", "min_size": [200, 200], "max_size": [200, 500], "color": [0, 0, 255], "privacy": "private"}}, {"value": 5, "cut_percentage": 0.49269040806425657, "children": [], "room_type": {"name": "bedroom", "min_size": [200, 200], "max_size": [200, 500], "color": [0, 0, 255], "privacy": "private"}}], "objects": [{"name": "Bed", "object_type": {"name": "Bed", "effect": {"energy": 50}}, "interaction_time": 4.7, "position": [821.5, 62.0]}], "doors": [{"position": [289, 124.0], "orientation": "vertical", "room1": {"value": 1, "cut_percentage": 0.5125031118211831, "children": [], "room_type": {"name": "bedroom", "min_size": [200, 200], "max_size": [200, 500], "color": [0, 0, 255], "privacy": "private"}}, "room2": {"value": 3, "cut_percentage": 0.5257659898189596, "children": [], "room_type": {"name": "bedroom", "min_size": [200, 200], "max_size": [200, 500], "color": [0, 0, 255], "privacy": "private"}}}, {"position": [644.0, 248], "orientation": "horizontal", "room1": {"value": 3, "cut_percentage": 0.5257659898189596, "children": [], "room_type": {"name": "bedroom", "min_size": [200, 200], "max_size": [200, 500], "color": [0, 0, 255], "privacy": "private"}}, "room2": {"value": 5, "cut_percentage": 0.49269040806425657, "children": [], "room_type": {"name": "bedroom", "min_size": [200, 200], "max_size": [200, 500], "color": [0, 0, 255], "privacy": "private"}}}]}, {"node": {"value": 5, "cut_percentage": 0.49269040806425657, "children": [], "room_type": {"name": "bedroom", "min_size": [200, 200], "max_size": [200, 500], "color": [0, 0, 255], "privacy": "private"}}, "rect": [289, 248, 710, 240], "neighbors": [{"value": 1, "cut_percentage": 0.5125031118211831, "children": [], "room_type": {"name": "bedroom", "min_size": [200, 200], "max_size": [200, 500], "color": [0, 0, 255], "privacy": "private"}}, {"value": 3, "cut_percentage": 0.5257659898189596, "children": [], "room_type": {"name": "bedroom", "min_size": [200, 200], "max_size": [200, 500], "color": [0, 0, 255], "privacy": "private"}}, {"value": 2, "cut_percentage": 0.4355764966075982, "children": [], "room_type": {"name": "bathroom", "min_size": [150, 200], "max_size": [150, 250], "color": [255, 155, 20], "privacy": "private"}}, {"value": 4, "cut_percentage": 0.6353655069621529, "children": [], "room_type": {"name": "bedroom", "min_size": [200, 200], "max_size": [200, 500], "color": [0, 0, 255], "privacy": "private"}}], "objects": [{"name": "Bed", "object_type": {"name": "Bed", "effect": {"energy": 50}}, "interaction_time": 4.7, "position": [821.5, 428.0]}], "doors": [{"position": [644.0, 248], "orientation": "horizontal", "room1": {"value": 3, "cut_percentage": 0.5257659898189596, "children": [], "room_type": {"name": "bedroom", "min_size": [200, 200], "max_size": [200, 500], "color": [0, 0, 255], "privacy": "private"}}, "room2": {"value": 5, "cut_percentage": 0.49269040806425657, "children": [], "room_type": {"name": "bedroom", "min_size": [200, 200], "max_size": [200, 500], "color": [0, 0, 255], "privacy": "private"}}}, {"position": [289, 368.0], "orientation": "vertical", "room1": {"value": 5, "cut_percentage": 0.49269040806425657, "children": [], "room_type": {"name": "bedroom", "min_size": [200, 200], "max_size": [200, 500], "color": [0, 0, 255], "privacy": "private"}}, "room2": {"value": 1, "cut_percentage": 0.5125031118211831, "children": [], "room_type": {"name": "bedroom", "min_size": [200, 200], "max_size": [200, 500], "color": [0, 0, 255], "privacy": "private"}}}, {"position": [835.0, 489], "orientation": "horizontal", "room1": {"value": 4, "cut_percentage": 0.6353655069621529, "children": [], "room_type": {"name": "bedroom", "min_size": [200, 200], "max_size": [200, 500], "color": [0, 0, 255], "privacy": "private"}}, "room2": {"value": 5, "cut_percentage": 0.49269040806425657, "children": [], "room_type": {"name": "bedroom", "min_size": [200, 200], "max_size": [200, 500], "color": [0, 0, 255], "privacy": "private"}}}]}, {"node": {"value": 2, "cut_percentage": 0.4355764966075982, "children": [], "room_type": {"name": "bathroom", "min_size": [150, 200], "max_size": [150, 250], "color": [255, 155, 20], "privacy": "private"}}, "rect": [289, 489, 383, 310], "neighbors": [{"value": 1, "cut_percentage": 0.5125031118211831, "children": [], "room_type": {"name": "bedroom", "min_size": [200, 200], "max_size": [200, 500], "color": [0, 0, 255], "privacy": "private"}}, {"value": 5, "cut_percentage": 0.49269040806425657, "children": [], "room_type": {"name": "bedroom", "min_size": [200, 200], "max_size": [200, 500], "color": [0, 0, 255], "privacy": "private"}}, {"value": 4, "cut_percentage": 0.6353655069621529, "children": [], "room_type": {"name": "bedroom", "min_size": [200, 200], "max_size": [200, 500], "color": [0, 0, 255], "privacy": "private"}}], "objects": [{"name": "Toilet", "object_type": {"name": "Toilet", "effect": {"bladder": 60}}, "interaction_time": 0.3, "position": [384.75, 566.5]}, {"name": "Shower", "object_type": {"name": "Shower", "effect": {"hygiene": 60}}, "interaction_time": 0.1, "position": [384.75, 721.5]}], "doors": [{"position": [289, 644.0], "orientation": "vertical", "room1": {"value": 2, "cut_percentage": 0.4355764966075982, "children": [], "room_type": {"name": "bathroom", "min_size": [150, 200], "max_size": [150, 250], "color": [255, 155, 20], "privacy": "private"}}, "room2": {"value": 1, "cut_percentage": 0.5125031118211831, "children": [], "room_type": {"name": "bedroom", "min_size": [200, 200], "max_size": [200, 500], "color": [0, 0, 255], "privacy": "private"}}}]}, {"node": {"value": 4, "cut_percentage": 0.6353655069621529, "children": [], "room_type": {"name": "bedroom", "min_size": [200, 200], "max_size": [200, 500], "color": [0, 0, 255], "privacy": "private"}}, "rect": [672, 489, 326, 310], "neighbors": [{"value": 5, "cut_percentage": 0.49269040806425657, "children": [], "room_type": {"name": "bedroom", "min_size": [200, 200], "max_size": [200, 500], "color": [0, 0, 255], "privacy": "private"}}, {"value": 2, "cut_percentage": 0.4355764966075982, "children": [], "room_type": {"name": "bathroom", "min_size": [150, 200], "max_size": [150, 250], "color": [255, 155, 20], "privacy": "private"}}], "objects": [{"name": "Bed", "object_type": {"name": "Bed", "effect": {"energy": 50}}, "interaction_time": 4.7, "position": [753.5, 644.0]}], "doors": [{"position": [835.0, 489], "orientation": "horizontal", "room1": {"value": 4, "cut_percentage": 0.6353655069621529, "children": [], "room_type": {"name": "bedroom", "min_size": [200, 200], "max_size": [200, 500], "color": [0, 0, 255], "privacy": "private"}}, "room2": {"value": 5, "cut_percentage": 0.49269040806425657, "children": [], "room_type": {"name": "bedroom", "min_size": [200, 200], "max_size": [200, 500], "color": [0, 0, 255], "privacy": "private"}}}]}], "doors_list": [{"position": [289, 124.0], "orientation": "vertical", "room1": {"value": 1, "cut_percentage": 0.5125031118211831, "children": [], "room_type": {"name": "bedroom", "min_size": [200, 200], "max_size": [200, 500], "color": [0, 0, 255], "privacy": "private"}}, "room2": {"value": 3, "cut_percentage": 0.5257659898189596, "children": [], "room_type": {"name": "bedroom", "min_size": [200, 200], "max_size": [200, 500], "color": [0, 0, 255], "privacy": "private"}}}, {"position": [644.0, 248], "orientation": "horizontal", "room1": {"value": 3, "cut_percentage": 0.5257659898189596, "children": [], "room_type": {"name": "bedroom", "min_size": [200, 200], "max_size": [200, 500], "color": [0, 0, 255], "privacy": "private"}}, "room2": {"value": 5, "cut_percentage": 0.49269040806425657, "children": [], "room_type": {"name": "bedroom", "min_size": [200, 200], "max_size": [200, 500], "color": [0, 0, 255], "privacy": "private"}}}, {"position": [289, 368.0], "orientation": "vertical", "room1": {"value": 5, "cut_percentage": 0.49269040806425657, "children": [], "room_type": {"name": "bedroom", "min_size": [200, 200], "max_size": [200, 500], "color": [0, 0, 255], "privacy": "private"}}, "room2": {"value": 1, "cut_percentage": 0.5125031118211831, "children": [], "room_type": {"name": "bedroom", "min_size": [200, 200], "max_size": [200, 500], "color": [0, 0, 255], "privacy": "private"}}}, {"position": [289, 644.0], "orientation": "vertical", "room1": {"value": 2, "cut_percentage": 0.4355764966075982, "children": [], "room_type": {"name": "bathroom", "min_size": [150, 200], "max_size": [150, 250], "color": [255, 155, 20], "privacy": "private"}}, "room2": {"value": 1, "cut_percentage": 0.5125031118211831, "children": [], "room_type": {"name": "bedroom", "min_size": [200, 200], "max_size": [200, 500], "color": [0, 0, 255], "privacy": "private"}}}, {"position": [835.0, 489], "orientation": "horizontal", "room1": {"value": 4, "cut_percentage": 0.6353655069621529, "children": [], "room_type": {"name": "bedroom", "min_size": [200, 200], "max_size": [200, 500], "color": [0, 0, 255], "privacy": "private"}}, "room2": {"value": 5, "cut_percentage": 0.49269040806425657, "children": [], "room_type": {"name": "bedroom", "min_size": [200, 200], "max_size": [200, 500], "color": [0, 0, 255], "privacy": "private"}}}], "graph": [[{"node": {"value": 1, "cut_percentage": 0.5125031118211831, "children": [], "room_type": {"name": "bedroom", "min_size": [200, 200], "max_size": [200, 500], "color": [0, 0, 255], "privacy": "private"}}, "rect": [0, 0, 289, 800], "neighbors": [{"value": 3, "cut_percentage": 0.5257659898189596, "children": [], "room_type": {"name": "bedroom", "min_size": [200, 200], "max_size": [200, 500], "color": [0, 0, 255], "privacy": "private"}}, {"value": 5, "cut_percentage": 0.49269040806425657, "children": [], "room_type": {"name": "bedroom", "min_size": [200, 200], "max_size": [200, 500], "color": [0, 0, 255], "privacy": "private"}}, {"value": 2, "cut_percentage": 0.4355764966075982, "children": [], "room_type": {"name": "bathroom", "min_size": [150, 200], "max_size": [150, 250], "color": [255, 155, 20], "privacy": "private"}}], "objects": [{"name": "Bed", "object_type": {"name": "Bed", "effect": {"energy": 50}}, "interaction_time": 4.7, "position": [216.75, 200.0]}], "doors": [{"position": [289, 124.0], "orientation": "vertical", "room1": {"value": 1, "cut_percentage": 0.5125031118211831, "children": [], "room_type": {"name": "bedroom", "min_size": [200, 200], "max_size": [200, 500], "color": [0, 0, 255], "privacy": "private"}}, "room2": {"value": 3, "cut_percentage": 0.5257659898189596, "children": [], "room_type": {"name": "bedroom", "min_size": [200, 200], "max_size": [200, 500], "color": [0, 0, 255], "privacy": "private"}}}, {"position": [289, 368.0], "orientation": "vertical", "room1": {"value": 5, "cut_percentage": 0.49269040806425657, "children": [], "room_type": {"name": "bedroom", "min_size": [200, 200], "max_size": [200, 500], "color": [0, 0, 255], "privacy": "private"}}, "room2": {"value": 1, "cut_percentage": 0.5125031118211831, "children": [], "room_type": {"name": "bedroom", "min_size": [200, 200], "max_size": [200, 500], "color": [0, 0, 255], "privacy": "private"}}}, {"position": [289, 644.0], "orientation": "vertical", "room1": {"value": 2, "cut_percentage": 0.4355764966075982, "children": [], "room_type": {"name": "bathroom", "min_size": [150, 200], "max_size": [150, 250], "color": [255, 155, 20], "privacy": "private"}}, "room2": {"value": 1, "cut_percentage": 0.5125031118211831, "children": [], "room_type": {"name": "bedroom", "min_size": [200, 200], "max_size": [200, 500], "color": [0, 0, 255], "privacy": "private"}}}]}, [{"node": {"value": 3, "cut_percentage": 0.5257659898189596, "children": [], "room_type": {"name": "bedroom", "min_size": [200, 200], "max_size": [200, 500], "color": [0, 0, 255], "privacy": "private"}}, "rect": [289, 0, 710, 248], "neighbors": [{"value": 1, "cut_percentage": 0.5125031118211831, "children": [], "room_type": {"name": "bedroom", "min_size": [200, 200], "max_size": [200, 500], "color": [0, 0, 255], "privacy": "private"}}, {"value": 5, "cut_percentage": 0.49269040806425657, "children": [], "room_type": {"name": "bedroom", "min_size": [200, 200], "max_size": [200, 500], "color": [0, 0, 255], "privacy": "private"}}], "objects": [{"name": "Bed", "object_type": {"name": "Bed", "effect": {"energy": 50}}, "interaction_time": 4.7, "position": [821.5, 62.0]}], "doors": [{"position": [289, 124.0], "orientation": "vertical", "room1": {"value": 1, "cut_percentage": 0.5125031118211831, "children": [], "room_type": {"name": "bedroom", "min_size": [200, 200], "max_size": [200, 500], "color": [0, 0, 255], "privacy": "private"}}, "room2": {"value": 3, "cut_percentage": 0.5257659898189596, "children": [], "room_type": {"name": "bedroom", "min_size": [200, 200], "max_size": [200, 500], "color": [0, 0, 255], "privacy": "private"}}}, {"position": [644.0, 248], "orientation": "horizontal", "room1": {"value": 3, "cut_percentage": 0.5257659898189596, "children": [], "room_type": {"name": "bedroom", "min_size": [200, 200], "max_size": [200, 500], "color": [0, 0, 255], "privacy": "private"}}, "room2": {"value": 5, "cut_percentage": 0.49269040806425657, "children": [], "room_type": {"name": "bedroom", "min_size": [200, 200], "max_size": [200, 500], "color": [0, 0, 255], "privacy": "private"}}}]}, {"node": {"value": 5, "cut_percentage": 0.49269040806425657, "children": [], "room_type": {"name": "bedroom", "min_size": [200, 200], "max_size": [200, 500], "color": [0, 0, 255], "privacy": "private"}}, "rect": [289, 248, 710, 240], "neighbors": [{"value": 1, "cut_percentage": 0.5125031118211831, "children": [], "room_type": {"name": "bedroom", "min_size": [200, 200], "max_size": [200, 500], "color": [0, 0, 255], "privacy": "private"}}, {"value": 3, "cut_percentage": 0.5257659898189596, "children": [], "room_type": {"name": "bedroom", "min_size": [200, 200], "max_size": [200, 500], "color": [0, 0, 255], "privacy": "private"}}, {"value": 2, "cut_percentage": 0.4355764966075982, "children": [], "room_type": {"name": "bathroom", "min_size": [150, 200], "max_size": [150, 250], "color": [255, 155, 20], "privacy": "private"}}, {"value": 4, "cut_percentage": 0.6353655069621529, "children": [], "room_type": {"name": "bedroom", "min_size": [200, 200], "max_size": [200, 500], "color": [0, 0, 255], "privacy": "private"}}], "objects": [{"name": "Bed", "object_type": {"name": "Bed", "effect": {"energy": 50}}, "interaction_time": 4.7, "position": [821.5, 428.0]}], "doors": [{"position": [644.0, 248], "orientation": "horizontal", "room1": {"value": 3, "cut_percentage": 0.5257659898189596, "children": [], "room_type": {"name": "bedroom", "min_size": [200, 200], "max_size": [200, 500], "color": [0, 0, 255], "privacy": "private"}}, "room2": {"value": 5, "cut_percentage": 0.49269040806425657, "children": [], "room_type": {"name": "bedroom", "min_size": [200, 200], "max_size": [200, 500], "color": [0, 0, 255], "privacy": "private"}}}, {"position": [289, 368.0], "orientation": "vertical", "room1": {"value": 5, "cut_percentage": 0.49269040806425657, "children": [], "room_type": {"name": "bedroom", "min_size": [200, 200], "max_size": [200, 500], "color": [0, 0, 255], "privacy": "private"}}, "room2": {"value": 1, "cut_percentage": 0.5125031118211831, "children": [], "room_type": {"name": "bedroom", "min_size": [200, 200], "max_size": [200, 500], "color": [0, 0, 255], "privacy": "private"}}}, {"position": [835.0, 489], "orientation": "horizontal", "room1": {"value": 4, "cut_percentage": 0.6353655069621529, "children": [], "room_type": {"name": "bedroom", "min_size": [200, 200], "max_size": [200, 500], "color": [0, 0, 255], "privacy": "private"}}, "room2": {"value": 5, "cut_percentage": 0.49269040806425657, "children": [], "room_type": {"name": "bedroom", "min_size": [200, 200], "max_size": [200, 500], "color": [0, 0, 255], "privacy": "private"}}}]}, {"node": {"value": 2, "cut_percentage": 0.4355764966075982, "children": [], "room_type": {"name": "bathroom", "min_size": [150, 200], "max_size": [150, 250], "color": [255, 155, 20], "privacy": "private"}}, "rect": [289, 489, 383, 310], "neighbors": [{"value": 1, "cut_percentage": 0.5125031118211831, "children": [], "room_type": {"name": "bedroom", "min_size": [200, 200], "max_size": [200, 500], "color": [0, 0, 255], "privacy": "private"}}, {"value": 5, "cut_percentage": 0.49269040806425657, "children": [], "room_type": {"name": "bedroom", "min_size": [200, 200], "max_size": [200, 500], "color": [0, 0, 255], "privacy": "private"}}, {"value": 4, "cut_percentage": 0.6353655069621529, "children": [], "room_type": {"name": "bedroom", "min_size": [200, 200], "max_size": [200, 500], "color": [0, 0, 255], "privacy": "private"}}], "objects": [{"name": "Toilet", "object_type": {"name": "Toilet", "effect": {"bladder": 60}}, "interaction_time": 0.3, "position": [384.75, 566.5]}, {"name": "Shower", "object_type": {"name": "Shower", "effect": {"hygiene": 60}}, "interaction_time": 0.1, "position": [384.75, 721.5]}], "doors": [{"position": [289, 644.0], "orientation": "vertical", "room1": {"value": 2, "cut_percentage": 0.4355764966075982, "children": [], "room_type": {"name": "bathroom", "min_size": [150, 200], "max_size": [150, 250], "color": [255, 155, 20], "privacy": "private"}}, "room2": {"value": 1, "cut_percentage": 0.5125031118211831, "children": [], "room_type": {"name": "bedroom", "min_size": [200, 200], "max_size": [200, 500], "color": [0, 0, 255], "privacy": "private"}}}]}]], [{"node": {"value": 3, "cut_percentage": 0.5257659898189596, "children": [], "room_type": {"name": "bedroom", "min_size": [200, 200], "max_size": [200, 500], "color": [0, 0, 255], "privacy": "private"}}, "rect": [289, 0, 710, 248], "neighbors": [{"value": 1, "cut_percentage": 0.5125031118211831, "children": [], "room_type": {"name": "bedroom", "min_size": [200, 200], "max_size": [200, 500], "color": [0, 0, 255], "privacy": "private"}}, {"value": 5, "cut_percentage": 0.49269040806425657, "children": [], "room_type": {"name": "bedroom", "min_size": [200, 200], "max_size": [200, 500], "color": [0, 0, 255], "privacy": "private"}}], "objects": [{"name": "Bed", "object_type": {"name": "Bed", "effect": {"energy": 50}}, "interaction_time": 4.7, "position": [821.5, 62.0]}], "doors": [{"position": [289, 124.0], "orientation": "vertical", "room1": {"value": 1, "cut_percentage": 0.5125031118211831, "children": [], "room_type": {"name": "bedroom", "min_size": [200, 200], "max_size": [200, 500], "color": [0, 0, 255], "privacy": "private"}}, "room2": {"value": 3, "cut_percentage": 0.5257659898189596, "children": [], "room_type": {"name": "bedroom", "min_size": [200, 200], "max_size": [200, 500], "color": [0, 0, 255], "privacy": "private"}}}, {"position": [644.0, 248], "orientation": "horizontal", "room1": {"value": 3, "cut_percentage": 0.5257659898189596, "children": [], "room_type": {"name": "bedroom", "min_size": [200, 200], "max_size": [200, 500], "color": [0, 0, 255], "privacy": "private"}}, "room2": {"value": 5, "cut_percentage": 0.49269040806425657, "children": [], "room_type": {"name": "bedroom", "min_size": [200, 200], "max_size": [200, 500], "color": [0, 0, 255], "privacy": "private"}}}]}, [{"node": {"value": 1, "cut_percentage": 0.5125031118211831, "children": [], "room_type": {"name": "bedroom", "min_size": [200, 200], "max_size": [200, 500], "color": [0, 0, 255], "privacy": "private"}}, "rect": [0, 0, 289, 800], "neighbors": [{"value": 3, "cut_percentage": 0.5257659898189596, "children": [], "room_type": {"name": "bedroom", "min_size": [200, 200], "max_size": [200, 500], "color": [0, 0, 255], "privacy": "private"}}, {"value": 5, "cut_percentage": 0.49269040806425657, "children": [], "room_type": {"name": "bedroom", "min_size": [200, 200], "max_size": [200, 500], "color": [0, 0, 255], "privacy": "private"}}, {"value": 2, "cut_percentage": 0.4355764966075982, "children": [], "room_type": {"name": "bathroom", "min_size": [150, 200], "max_size": [150, 250], "color": [255, 155, 20], "privacy": "private"}}], "objects": [{"name": "Bed", "object_type": {"name": "Bed", "effect": {"energy": 50}}, "interaction_time": 4.7, "position": [216.75, 200.0]}], "doors": [{"position": [289, 124.0], "orientation": "vertical", "room1": {"value": 1, "cut_percentage": 0.5125031118211831, "children": [], "room_type": {"name": "bedroom", "min_size": [200, 200], "max_size": [200, 500], "color": [0, 0, 255], "privacy": "private"}}, "room2": {"value": 3, "cut_percentage": 0.5257659898189596, "children": [], "room_type": {"name": "bedroom", "min_size": [200, 200], "max_size": [200, 500], "color": [0, 0, 255], "privacy": "private"}}}, {"position": [289, 368.0], "orientation": "vertical", "room1": {"value": 5, "cut_percentage": 0.49269040806425657, "children": [], "room_type": {"name": "bedroom", "min_size": [200, 200], "max_size": [200, 500], "color": [0, 0, 255], "privacy": "private"}}, "room2": {"value": 1, "cut_percentage": 0.5125031118211831, "children": [], "room_type": {"name": "bedroom", "min_size": [200, 200], "max_size": [200, 500], "color": [0, 0, 255], "privacy": "private"}}}, {"position": [289, 644.0], "orientation": "vertical", "room1": {"value": 2, "cut_percentage": 0.4355764966075982, "children": [], "room_type": {"name": "bathroom", "min_size": [150, 200], "max_size": [150, 250], "color": [255, 155, 20], "privacy": "private"}}, "room2": {"value": 1, "cut_percentage": 0.5125031118211831, "children": [], "room_type": {"name": "bedroom", "min_size": [200, 200], "max_size": [200, 500], "color": [0, 0, 255], "privacy": "private"}}}]}, {"node": {"value": 5, "cut_percentage": 0.49269040806425657, "children": [], "room_type": {"name": "bedroom", "min_size": [200, 200], "max_size": [200, 500], "color": [0, 0, 255], "privacy": "private"}}, "rect": [289, 248, 710, 240], "neighbors": [{"value": 1, "cut_percentage": 0.5125031118211831, "children": [], "room_type": {"name": "bedroom", "min_size": [200, 200], "max_size": [200, 500], "color": [0, 0, 255], "privacy": "private"}}, {"value": 3, "cut_percentage": 0.5257659898189596, "children": [], "room_type": {"name": "bedroom", "min_size": [200, 200], "max_size": [200, 500], "color": [0, 0, 255], "privacy": "private"}}, {"value": 2, "cut_percentage": 0.4355764966075982, "children": [], "room_type": {"name": "bathroom", "min_size": [150, 200], "max_size": [150, 250], "color": [255, 155, 20], "privacy": "private"}}, {"value": 4, "cut_percentage": 0.6353655069621529, "children": [], "room_type": {"name": "bedroom", "min_size": [200, 200], "max_size": [200, 500], "color": [0, 0, 255], "privacy": "private"}}], "objects": [{"name": "Bed", "object_type": {"name": "Bed", "effect": {"energy": 50}}, "interaction_time": 4.7, "position": [821.5, 428.0]}], "doors": [{"position": [644.0, 248], "orientation": "horizontal", "room1": {"value": 3, "cut_percentage": 0.5257659898189596, "children": [], "room_type": {"name": "bedroom", "min_size": [200, 200], "max_size": [200, 500], "color": [0, 0, 255], "privacy": "private"}}, "room2": {"value": 5, "cut_percentage": 0.49269040806425657, "children": [], "room_type": {"name": "bedroom", "min_size": [200, 200], "max_size": [200, 500], "color": [0, 0, 255], "privacy": "private"}}}, {"position": [289, 368.0], "orientation": "vertical", "room1": {"value": 5, "cut_percentage": 0.49269040806425657, "children": [], "room_type": {"name": "bedroom", "min_size": [200, 200], "max_size": [200, 500], "color": [0, 0, 255], "privacy": "private"}}, "room2": {"value": 1, "cut_percentage": 0.5125031118211831, "children": [], "room_type": {"name": "bedroom", "min_size": [200, 200], "max_size": [200, 500], "color": [0, 0, 255], "privacy": "private"}}}, {"position": [835.0, 489], "orientation": "horizontal", "room1": {"value": 4, "cut_percentage": 0.6353655069621529, "children": [], "room_type": {"name": "bedroom", "min_size": [200, 200], "max_size": [200, 500], "color": [0, 0, 255], "privacy": "private"}}, "room2": {"value": 5, "cut_percentage": 0.49269040806425657, "children": [], "room_type": {"name": "bedroom", "min_size": [200, 200], "max_size": [200, 500], "color": [0, 0, 255], "privacy": "private"}}}]}]], [{"node": {"value": 5, "cut_percentage": 0.49269040806425657, "children": [], "room_type": {"name": "bedroom", "min_size": [200, 200], "max_size": [200, 500], "color": [0, 0, 255], "privacy": "private"}}, "rect": [289, 248, 710, 240], "neighbors": [{"value": 1, "cut_percentage": 0.5125031118211831, "children": [], "room_type": {"name": "bedroom", "min_size": [200, 200], "max_size": [200, 500], "color": [0, 0, 255], "privacy": "private"}}, {"value": 3, "cut_percentage": 0.5257659898189596, "children": [], "room_type": {"name": "bedroom", "min_size": [200, 200], "max_size": [200, 500], "color": [0, 0, 255], "privacy": "private"}}, {"value": 2, "cut_percentage": 0.4355764966075982, "children": [], "room_type": {"name": "bathroom", "min_size": [150, 200], "max_size": [150, 250], "color": [255, 155, 20], "privacy": "private"}}, {"value": 4, "cut_percentage": 0.6353655069621529, "children": [], "room_type": {"name": "bedroom", "min_size": [200, 200], "max_size": [200, 500], "color": [0, 0, 255], "privacy": "private"}}], "objects": [{"name": "Bed", "object_type": {"name": "Bed", "effect": {"energy": 50}}, "interaction_time": 4.7, "position": [821.5, 428.0]}], "doors": [{"position": [644.0, 248], "orientation": "horizontal", "room1": {"value": 3, "cut_percentage": 0.5257659898189596, "children": [], "room_type": {"name": "bedroom", "min_size": [200, 200], "max_size": [200, 500], "color": [0, 0, 255], "privacy": "private"}}, "room2": {"value": 5, "cut_percentage": 0.49269040806425657, "children": [], "room_type": {"name": "bedroom", "min_size": [200, 200], "max_size": [200, 500], "color": [0, 0, 255], "privacy": "private"}}}, {"position": [289, 368.0], "orientation": "vertical", "room1": {"value": 5, "cut_percentage": 0.49269040806425657, "children": [], "room_type": {"name": "bedroom", "min_size": [200, 200], "max_size": [200, 500], "color": [0, 0, 255], "privacy": "private"}}, "room2": {"value": 1, "cut_percentage": 0.5125031118211831, "children": [], "room_type": {"name": "bedroom", "min_size": [200, 200], "max_size": [200, 500], "color": [0, 0, 255], "privacy": "private"}}}, {"position": [835.0, 489], "orientation": "horizontal", "room1": {"value": 4, "cut_percentage": 0.6353655069621529, "children": [], "room_type": {"name": "bedroom", "min_size": [200, 200], "max_size": [200, 500], "color": [0, 0, 255], "privacy": "private"}}, "room2": {"value": 5, "cut_percentage": 0.49269040806425657, "children": [], "room_type": {"name": "bedroom", "min_size": [200, 200], "max_size": [200, 500], "color": [0, 0, 255], "privacy": "private"}}}]}, [{"node": {"value": 3, "cut_percentage": 0.5257659898189596, "children": [], "room_type": {"name": "bedroom", "min_size": [200, 200], "max_size": [200, 500], "color": [0, 0, 255], "privacy": "private"}}, "rect": [289, 0, 710, 248], "neighbors": [{"value": 1, "cut_percentage": 0.5125031118211831, "children": [], "room_type": {"name": "bedroom", "min_size": [200, 200], "max_size": [200, 500], "color": [0, 0, 255], "privacy": "private"}}, {"value": 5, "cut_percentage": 0.49269040806425657, "children": [], "room_type": {"name": "bedroom", "min_size": [200, 200], "max_size": [200, 500], "color": [0, 0, 255], "privacy": "private"}}], "objects": [{"name": "Bed", "object_type": {"name": "Bed", "effect": {"energy": 50}}, "interaction_time": 4.7, "position": [821.5, 62.0]}], "doors": [{"position": [289, 124.0], "orientation": "vertical", "room1": {"value": 1, "cut_percentage": 0.5125031118211831, "children": [], "room_type": {"name": "bedroom", "min_size": [200, 200], "max_size": [200, 500], "color": [0, 0, 255], "privacy": "private"}}, "room2": {"value": 3, "cut_percentage": 0.5257659898189596, "children": [], "room_type": {"name": "bedroom", "min_size": [200, 200], "max_size": [200, 500], "color": [0, 0, 255], "privacy": "private"}}}, {"position": [644.0, 248], "orientation": "horizontal", "room1": {"value": 3, "cut_percentage": 0.5257659898189596, "children": [], "room_type": {"name": "bedroom", "min_size": [200, 200], "max_size": [200, 500], "color": [0, 0, 255], "privacy": "private"}}, "room2": {"value": 5, "cut_percentage": 0.49269040806425657, "children": [], "room_type": {"name": "bedroom", "min_size": [200, 200], "max_size": [200, 500], "color": [0, 0, 255], "privacy": "private"}}}]}, {"node": {"value": 1, "cut_percentage": 0.5125031118211831, "children": [], "room_type": {"name": "bedroom", "min_size": [200, 200], "max_size": [200, 500], "color": [0, 0, 255], "privacy": "private"}}, "rect": [0, 0, 289, 800], "neighbors": [{"value": 3, "cut_percentage": 0.5257659898189596, "children": [], "room_type": {"name": "bedroom", "min_size": [200, 200], "max_size": [200, 500], "color": [0, 0, 255], "privacy": "private"}}, {"value": 5, "cut_percentage": 0.49269040806425657, "children": [], "room_type": {"name": "bedroom", "min_size": [200, 200], "max_size": [200, 500], "color": [0, 0, 255], "privacy": "private"}}, {"value": 2, "cut_percentage": 0.4355764966075982, "children": [], "room_type": {"name": "bathroom", "min_size": [150, 200], "max_size": [150, 250], "color": [255, 155, 20], "privacy": "private"}}], "objects": [{"name": "Bed", "object_type": {"name": "Bed", "effect": {"energy": 50}}, "interaction_time": 4.7, "position": [216.75, 200.0]}], "doors": [{"position": [289, 124.0], "orientation": "vertical", "room1": {"value": 1, "cut_percentage": 0.5125031118211831, "children": [], "room_type": {"name": "bedroom", "min_size": [200, 200], "max_size": [200, 500], "color": [0, 0, 255], "privacy": "private"}}, "room2": {"value": 3, "cut_percentage": 0.5257659898189596, "children": [], "room_type": {"name": "bedroom", "min_size": [200, 200], "max_size": [200, 500], "color": [0, 0, 255], "privacy": "private"}}}, {"position": [289, 368.0], "orientation": "vertical", "room1": {"value": 5, "cut_percentage": 0.49269040806425657, "children": [], "room_type": {"name": "bedroom", "min_size": [200, 200], "max_size": [200, 500], "color": [0, 0, 255], "privacy": "private"}}, "room2": {"value": 1, "cut_percentage": 0.5125031118211831, "children": [], "room_type": {"name": "bedroom", "min_size": [200, 200], "max_size": [200, 500], "color": [0, 0, 255], "privacy": "private"}}}, {"position": [289, 644.0], "orientation": "vertical", "room1": {"value": 2, "cut_percentage": 0.4355764966075982, "children": [], "room_type": {"name": "bathroom", "min_size": [150, 200], "max_size": [150, 250], "color": [255, 155, 20], "privacy": "private"}}, "room2": {"value": 1, "cut_percentage": 0.5125031118211831, "children": [], "room_type": {"name": "bedroom", "min_size": [200, 200], "max_size": [200, 500], "color": [0, 0, 255], "privacy": "private"}}}]}, {"node": {"value": 4, "cut_percentage": 0.6353655069621529, "children": [], "room_type": {"name": "bedroom", "min_size": [200, 200], "max_size": [200, 500], "color": [0, 0, 255], "privacy": "private"}}, "rect": [672, 489, 326, 310], "neighbors": [{"value": 5, "cut_percentage": 0.49269040806425657, "children": [], "room_type": {"name": "bedroom", "min_size": [200, 200], "max_size": [200, 500], "color": [0, 0, 255], "privacy": "private"}}, {"value": 2, "cut_percentage": 0.4355764966075982, "children": [], "room_type": {"name": "bathroom", "min_size": [150, 200], "max_size": [150, 250], "color": [255, 155, 20], "privacy": "private"}}], "objects": [{"name": "Bed", "object_type": {"name": "Bed", "effect": {"energy": 50}}, "interaction_time": 4.7, "position": [753.5, 644.0]}], "doors": [{"position": [835.0, 489], "orientation": "horizontal", "room1": {"value": 4, "cut_percentage": 0.6353655069621529, "children": [], "room_type": {"name": "bedroom", "min_size": [200, 200], "max_size": [200, 500], "color": [0, 0, 255], "privacy": "private"}}, "room2": {"value": 5, "cut_percentage": 0.49269040806425657, "children": [], "room_type": {"name": "bedroom", "min_size": [200, 200], "max_size": [200, 500], "color": [0, 0, 255], "privacy": "private"}}}]}]], [{"node": {"value": 2, "cut_percentage": 0.4355764966075982, "children": [], "room_type": {"name": "bathroom", "min_size": [150, 200], "max_size": [150, 250], "color": [255, 155, 20], "privacy": "private"}}, "rect": [289, 489, 383, 310], "neighbors": [{"value": 1, "cut_percentage": 0.5125031118211831, "children": [], "room_type": {"name": "bedroom", "min_size": [200, 200], "max_size": [200, 500], "color": [0, 0, 255], "privacy": "private"}}, {"value": 5, "cut_percentage": 0.49269040806425657, "children": [], "room_type": {"name": "bedroom", "min_size": [200, 200], "max_size": [200, 500], "color": [0, 0, 255], "privacy": "private"}}, {"value": 4, "cut_percentage": 0.6353655069621529, "children": [], "room_type": {"name": "bedroom", "min_size": [200, 200], "max_size": [200, 500], "color": [0, 0, 255], "privacy": "private"}}], "objects": [{"name": "Toilet", "object_type": {"name": "Toilet", "effect": {"bladder": 60}}, "interaction_time": 0.3, "position": [384.75, 566.5]}, {"name": "Shower", "object_type": {"name": "Shower", "effect": {"hygiene": 60}}, "interaction_time": 0.1, "position": [384.75, 721.5]}], "doors": [{"position": [289, 644.0], "orientation": "vertical", "room1": {"value": 2, "cut_percentage": 0.4355764966075982, "children": [], "room_type": {"name": "bathroom", "min_size": [150, 200], "max_size": [150, 250], "color": [255, 155, 20], "privacy": "private"}}, "room2": {"value": 1, "cut_percentage": 0.5125031118211831, "children": [], "room_type": {"name": "bedroom", "min_size": [200, 200], "max_size": [200, 500], "color": [0, 0, 255], "privacy": "private"}}}]}, [{"node": {"value": 1, "cut_percentage": 0.5125031118211831, "children": [], "room_type": {"name": "bedroom", "min_size": [200, 200], "max_size": [200, 500], "color": [0, 0, 255], "privacy": "private"}}, "rect": [0, 0, 289, 800], "neighbors": [{"value": 3, "cut_percentage": 0.5257659898189596, "children": [], "room_type": {"name": "bedroom", "min_size": [200, 200], "max_size": [200, 500], "color": [0, 0, 255], "privacy": "private"}}, {"value": 5, "cut_percentage": 0.49269040806425657, "children": [], "room_type": {"name": "bedroom", "min_size": [200, 200], "max_size": [200, 500], "color": [0, 0, 255], "privacy": "private"}}, {"value": 2, "cut_percentage": 0.4355764966075982, "children": [], "room_type": {"name": "bathroom", "min_size": [150, 200], "max_size": [150, 250], "color": [255, 155, 20], "privacy": "private"}}], "objects": [{"name": "Bed", "object_type": {"name": "Bed", "effect": {"energy": 50}}, "interaction_time": 4.7, "position": [216.75, 200.0]}], "doors": [{"position": [289, 124.0], "orientation": "vertical", "room1": {"value": 1, "cut_percentage": 0.5125031118211831, "children": [], "room_type": {"name": "bedroom", "min_size": [200, 200], "max_size": [200, 500], "color": [0, 0, 255], "privacy": "private"}}, "room2": {"value": 3, "cut_percentage": 0.5257659898189596, "children": [], "room_type": {"name": "bedroom", "min_size": [200, 200], "max_size": [200, 500], "color": [0, 0, 255], "privacy": "private"}}}, {"position": [289, 368.0], "orientation": "vertical", "room1": {"value": 5, "cut_percentage": 0.49269040806425657, "children": [], "room_type": {"name": "bedroom", "min_size": [200, 200], "max_size": [200, 500], "color": [0, 0, 255], "privacy": "private"}}, "room2": {"value": 1, "cut_percentage": 0.5125031118211831, "children": [], "room_type": {"name": "bedroom", "min_size": [200, 200], "max_size": [200, 500], "color": [0, 0, 255], "privacy": "private"}}}, {"position": [289, 644.0], "orientation": "vertical", "room1": {"value": 2, "cut_percentage": 0.4355764966075982, "children": [], "room_type": {"name": "bathroom", "min_size": [150, 200], "max_size": [150, 250], "color": [255, 155, 20], "privacy": "private"}}, "room2": {"value": 1, "cut_percentage": 0.5125031118211831, "children": [], "room_type": {"name": "bedroom", "min_size": [200, 200], "max_size": [200, 500], "color": [0, 0, 255], "privacy": "private"}}}]}]], [{"node": {"value": 4, "cut_percentage": 0.6353655069621529, "children": [], "room_type": {"name": "bedroom", "min_size": [200, 200], "max_size": [200, 500], "color": [0, 0, 255], "privacy": "private"}}, "rect": [672, 489, 326, 310], "neighbors": [{"value": 5, "cut_percentage": 0.49269040806425657, "children": [], "room_type": {"name": "bedroom", "min_size": [200, 200], "max_size": [200, 500], "color": [0, 0, 255], "privacy": "private"}}, {"value": 2, "cut_percentage": 0.4355764966075982, "children": [], "room_type": {"name": "bathroom", "min_size": [150, 200], "max_size": [150, 250], "color": [255, 155, 20], "privacy": "private"}}], "objects": [{"name": "Bed", "object_type": {"name": "Bed", "effect": {"energy": 50}}, "interaction_time": 4.7, "position": [753.5, 644.0]}], "doors": [{"position": [835.0, 489], "orientation": "horizontal", "room1": {"value": 4, "cut_percentage": 0.6353655069621529, "children": [], "room_type": {"name": "bedroom", "min_size": [200, 200], "max_size": [200, 500], "color": [0, 0, 255], "privacy": "private"}}, "room2": {"value": 5, "cut_percentage": 0.49269040806425657, "children": [], "room_type": {"name": "bedroom", "min_size": [200, 200], "max_size": [200, 500], "color": [0, 0, 255], "privacy": "private"}}}]}, [{"node": {"value": 5, "cut_percentage": 0.49269040806425657, "children": [], "room_type": {"name": "bedroom", "min_size": [200, 200], "max_size": [200, 500], "color": [0, 0, 255], "privacy": "private"}}, "rect": [289, 248, 710, 240], "neighbors": [{"value": 1, "cut_percentage": 0.5125031118211831, "children": [], "room_type": {"name": "bedroom", "min_size": [200, 200], "max_size": [200, 500], "color": [0, 0, 255], "privacy": "private"}}, {"value": 3, "cut_percentage": 0.5257659898189596, "children": [], "room_type": {"name": "bedroom", "min_size": [200, 200], "max_size": [200, 500], "color": [0, 0, 255], "privacy": "private"}}, {"value": 2, "cut_percentage": 0.4355764966075982, "children": [], "room_type": {"name": "bathroom", "min_size": [150, 200], "max_size": [150, 250], "color": [255, 155, 20], "privacy": "private"}}, {"value": 4, "cut_percentage": 0.6353655069621529, "children": [], "room_type": {"name": "bedroom", "min_size": [200, 200], "max_size": [200, 500], "color": [0, 0, 255], "privacy": "private"}}], "objects": [{"name": "Bed", "object_type": {"name": "Bed", "effect": {"energy": 50}}, "interaction_time": 4.7, "position": [821.5, 428.0]}], "doors": [{"position": [644.0, 248], "orientation": "horizontal", "room1": {"value": 3, "cut_percentage": 0.5257659898189596, "children": [], "room_type": {"name": "bedroom", "min_size": [200, 200], "max_size": [200, 500], "color": [0, 0, 255], "privacy": "private"}}, "room2": {"value": 5, "cut_percentage": 0.49269040806425657, "children": [], "room_type": {"name": "bedroom", "min_size": [200, 200], "max_size": [200, 500], "color": [0, 0, 255], "privacy": "private"}}}, {"position": [289, 368.0], "orientation": "vertical", "room1": {"value": 5, "cut_percentage": 0.49269040806425657, "children": [], "room_type": {"name": "bedroom", "min_size": [200, 200], "max_size": [200, 500], "color": [0, 0, 255], "privacy": "private"}}, "room2": {"value": 1, "cut_percentage": 0.5125031118211831, "children": [], "room_type": {"name": "bedroom", "min_size": [200, 200], "max_size": [200, 500], "color": [0, 0, 255], "privacy": "private"}}}, {"position": [835.0, 489], "orientation": "horizontal", "room1": {"value": 4, "cut_percentage": 0.6353655069621529, "children": [], "room_type": {"name": "bedroom", "min_size": [200, 200], "max_size": [200, 500], "color": [0, 0, 255], "privacy": "private"}}, "room2": {"value": 5, "cut_percentage": 0.49269040806425657, "children": [], "room_type": {"name": "bedroom", "min_size": [200, 200], "max_size": [200, 500], "color": [0, 0, 255], "privacy": "private"}}}]}]]], "fitness": 0, "agents_paths": {"Agent 1": [[["private", "bedroom"], ["private", "bathroom"]], [["private", "bathroom"], ["private", "bedroom"], ["private", "bedroom"]], [["private", "bedroom"], ["private", "bedroom"], ["private", "bathroom"]], [["private", "bathroom"]], [["private", "bathroom"]], [["private", "bathroom"]], [["private", "bathroom"], ["private", "bedroom"], ["private", "bedroom"], ["private", "bedroom"]], [["private", "bedroom"], ["private", "bedroom"], ["private", "bedroom"], ["private", "bathroom"]], [["private", "bathroom"]], [["private", "bathroom"]], [["private", "bathroom"]], [["private", "bathroom"], ["private", "bedroom"]], [["private", "bedroom"], ["private", "bathroom"]], [["private", "bathroom"]], [["private", "bathroom"]], [["private", "bathroom"], ["private", "bedroom"], ["private", "bedroom"]]], "Agent 2": [[["private", "bedroom"], ["private", "bedroom"]], [["private", "bedroom"], ["private", "bathroom"]], [["private", "bathroom"]], [["private", "bathroom"]], [["private", "bathroom"]], [["private", "bathroom"], ["private", "bedroom"]], [["private", "bedroom"], ["private", "bathroom"]], [["private", "bathroom"]], [["private", "bathroom"]], [["private", "bathroom"], ["private", "bedroom"], ["private", "bedroom"], ["private", "bedroom"]], [["private", "bedroom"], ["private", "bedroom"], ["private", "bedroom"], ["private", "bathroom"]], [["private", "bathroom"]], [["private", "bathroom"]], [["private", "bathroom"]], [["private", "bathroom"], ["private", "bedroom"]], [["private", "bedroom"], ["private", "bathroom"]], [["private", "bathroom"], ["private", "bedroom"], ["private", "bedroom"], ["private", "bedroom"]]]}, "agents_activites": {"Agent 1": [["Agent 1", " interacting with ", "Toilet", " current time in minutes ", "53", " expected interaction finish time ", "71.0", " the interaction in hours: ", "0.3"], ["Agent 1", " interacting with ", "Bed", " current time in minutes ", "89", " expected interaction finish time ", "371.0", " the interaction in hours: ", "4.7"], ["Agent 1", " interacting with ", "Shower", " current time in minutes ", "389", " expected interaction finish time ", "395.0", " the interaction in hours: ", "0.1"], ["Agent 1", " interacting with ", "Toilet", " current time in minutes ", "401", " expected interaction finish time ", "419.0", " the interaction in hours: ", "0.3"], ["Agent 1", " interacting with ", "Shower", " current time in minutes ", "432", " expected interaction finish time ", "438.0", " the interaction in hours: ", "0.1"], ["Agent 1", " interacting with ", "Toilet", " current time in minutes ", "444", " expected interaction finish time ", "462.0", " the interaction in hours: ", "0.3"], ["Agent 1", " interacting with ", "Bed", " current time in minutes ", "478", " expected interaction finish time ", "760.0", " the interaction in hours: ", "4.7"], ["Agent 1", " interacting with ", "Shower", " current time in minutes ", "776", " expected interaction finish time ", "782.0", " the interaction in hours: ", "0.1"], ["Agent 1", " interacting with ", "Toilet", " current time in minutes ", "795", " expected interaction finish time ", "813.0", " the interaction in hours: ", "0.3"], ["Agent 1", " interacting with ", "Toilet", " current time in minutes ", "816", " expected interaction finish time ", "834.0", " the interaction in hours: ", "0.3"], ["Agent 1", " interacting with ", "Shower", " current time in minutes ", "781", " expected interaction finish time ", "787.0", " the interaction in hours: ", "0.1"], ["Agent 1", " interacting with ", "Bed", " current time in minutes ", "857", " expected interaction finish time ", "1139.0", " the interaction in hours: ", "4.7"], ["Agent 1", " interacting with ", "Toilet", " current time in minutes ", "1165", " expected interaction finish time ", "1183.0", " the interaction in hours: ", "0.3"], ["Agent 1", " interacting with ", "Shower", " current time in minutes ", "1189", " expected interaction finish time ", "1195.0", " the interaction in hours: ", "0.1"], ["Agent 1", " interacting with ", "Toilet", " current time in minutes ", "1143", " expected interaction finish time ", "1161.0", " the interaction in hours: ", "0.3"], ["Agent 1", " interacting with ", "Bed", " current time in minutes ", "1230", " expected interaction finish time ", "1512.0", " the interaction in hours: ", "4.7"]], "Agent 2": [["Agent 2", " interacting with ", "Bed", " current time in minutes ", "53", " expected interaction finish time ", "335.0", " the interaction in hours: ", "4.7"], ["Agent 2", " interacting with ", "Shower", " current time in minutes ", "346", " expected interaction finish time ", "352.0", " the interaction in hours: ", "0.1"], ["Agent 2", " interacting with ", "Toilet", " current time in minutes ", "357", " expected interaction finish time ", "375.0", " the interaction in hours: ", "0.3"], ["Agent 2", " interacting with ", "Shower", " current time in minutes ", "381", " expected interaction finish time ", "387.0", " the interaction in hours: ", "0.1"], ["Agent 2", " interacting with ", "Shower", " current time in minutes ", "396", " expected interaction finish time ", "402.0", " the interaction in hours: ", "0.1"], ["Agent 2", " interacting with ", "Bed", " current time in minutes ", "414", " expected interaction finish time ", "696.0", " the interaction in hours: ", "4.7"], ["Agent 2", " interacting with ", "Shower", " current time in minutes ", "706", " expected interaction finish time ", "712.0", " the interaction in hours: ", "0.1"], ["Agent 2", " interacting with ", "Toilet", " current time in minutes ", "717", " expected interaction finish time ", "735.0", " the interaction in hours: ", "0.3"], ["Agent 2", " interacting with ", "Shower", " current time in minutes ", "740", " expected interaction finish time ", "746.0", " the interaction in hours: ", "0.1"], ["Agent 2", " interacting with ", "Bed", " current time in minutes ", "761", " expected interaction finish time ", "1043.0", " the interaction in hours: ", "4.7"], ["Agent 2", " interacting with ", "Shower", " current time in minutes ", "1061", " expected interaction finish time ", "1067.0", " the interaction in hours: ", "0.1"], ["Agent 2", " interacting with ", "Toilet", " current time in minutes ", "1072", " expected interaction finish time ", "1090.0", " the interaction in hours: ", "0.3"], ["Agent 2", " interacting with ", "Shower", " current time in minutes ", "1099", " expected interaction finish time ", "1105.0", " the interaction in hours: ", "0.1"], ["Agent 2", " interacting with ", "Toilet", " current time in minutes ", "1109", " expected interaction finish time ", "1127.0", " the interaction in hours: ", "0.3"], ["Agent 2", " interacting with ", "Shower", " current time in minutes ", "1090", " expected interaction finish time ", "1096.0", " the interaction in hours: ", "0.1"], ["Agent 2", " interacting with ", "Bed", " current time in minutes ", "1173", " expected interaction finish time ", "1455.0", " the interaction in hours: ", "4.7"]]}, "neighbouring_rooms": {"bedroom": ["bedroom", "bathroom"], "bathroom": ["bedroom", "bedroom", "bedroom"]}, "mutated": false, "crossover": false, "parent1": null, "parent2": null, "mutation_probability": null, "agents_have_bedrooms": 0}