{"num_rooms": 5, "room_types": [{"name": "living_room", "min_size": [300, 400], "max_size": [300, 700], "color": [0, 255, 0], "privacy": "common"}, {"name": "kitchen", "min_size": [200, 350], "max_size": [300, 500], "color": [255, 0, 0], "privacy": "common"}, {"name": "kitchen", "min_size": [200, 350], "max_size": [300, 500], "color": [255, 0, 0], "privacy": "common"}, {"name": "bathroom", "min_size": [150, 200], "max_size": [150, 250], "color": [255, 155, 20], "privacy": "private"}, {"name": "bedroom", "min_size": [200, 200], "max_size": [200, 500], "color": [0, 0, 255], "privacy": "private"}], "slicing_tree_root": {"value": "H", "cut_percentage": 0.26904558873368684, "children": [{"value": 1, "cut_percentage": 0.5171707308741075, "children": [], "room_type": {"name": "kitchen", "min_size": [200, 350], "max_size": [300, 500], "color": [255, 0, 0], "privacy": "common"}}, {"value": "V", "cut_percentage": 0.3746707212852418, "children": [{"value": 2, "cut_percentage": 0.44151581454401606, "children": [], "room_type": {"name": "kitchen", "min_size": [200, 350], "max_size": [300, 500], "color": [255, 0, 0], "privacy": "common"}}, {"value": "H", "cut_percentage": 0.411976385623775, "children": [{"value": "V", "cut_percentage": 0.5904538561780863, "children": [{"value": 3, "cut_percentage": 0.3848290616474309, "children": [], "room_type": {"name": "bedroom", "min_size": [200, 200], "max_size": [200, 500], "color": [0, 0, 255], "privacy": "private"}}, {"value": 4, "cut_percentage": 0.42290739737050553, "children": [], "room_type": {"name": "bedroom", "min_size": [200, 200], "max_size": [200, 500], "color": [0, 0, 255], "privacy": "private"}}], "room_type": null}, {"value": 5, "cut_percentage": 0.5540689493724438, "children": [], "room_type": {"name": "kitchen", "min_size": [200, 350], "max_size": [300, 500], "color": [255, 0, 0], "privacy": "common"}}], "room_type": null}], "room_type": null}], "room_type": null}, "rooms": [{"node": {"value": 1, "cut_percentage": 0.5171707308741075, "children": [], "room_type": {"name": "kitchen", "min_size": [200, 350], "max_size": [300, 500], "color": [255, 0, 0], "privacy": "common"}}, "rect": [0, 0, 1000, 215], "neighbors": [{"value": 2, "cut_percentage": 0.44151581454401606, "children": [], "room_type": {"name": "kitchen", "min_size": [200, 350], "max_size": [300, 500], "color": [255, 0, 0], "privacy": "common"}}, {"value": 3, "cut_percentage": 0.3848290616474309, "children": [], "room_type": {"name": "bedroom", "min_size": [200, 200], "max_size": [200, 500], "color": [0, 0, 255], "privacy": "private"}}, {"value": 4, "cut_percentage": 0.42290739737050553, "children": [], "room_type": {"name": "bedroom", "min_size": [200, 200], "max_size": [200, 500], "color": [0, 0, 255], "privacy": "private"}}], "objects": [{"name": "Fridge", "object_type": {"name": "Fridge", "effect": {"hunger": 50}}, "interaction_time": 0.5, "position": [750.0, 53.75]}, {"name": "Sink", "object_type": {"name": "Sink", "effect": {"thirst": 50}}, "interaction_time": 0.1, "position": [750.0, 107.5]}], "doors": [{"position": [187.0, 215], "orientation": "horizontal", "room1": {"value": 1, "cut_percentage": 0.5171707308741075, "children": [], "room_type": {"name": "kitchen", "min_size": [200, 350], "max_size": [300, 500], "color": [255, 0, 0], "privacy": "common"}}, "room2": {"value": 2, "cut_percentage": 0.44151581454401606, "children": [], "room_type": {"name": "kitchen", "min_size": [200, 350], "max_size": [300, 500], "color": [255, 0, 0], "privacy": "common"}}}, {"position": [558.5, 215], "orientation": "horizontal", "room1": {"value": 3, "cut_percentage": 0.3848290616474309, "children": [], "room_type": {"name": "bedroom", "min_size": [200, 200], "max_size": [200, 500], "color": [0, 0, 255], "privacy": "private"}}, "room2": {"value": 1, "cut_percentage": 0.5171707308741075, "children": [], "room_type": {"name": "kitchen", "min_size": [200, 350], "max_size": [300, 500], "color": [255, 0, 0], "privacy": "common"}}}, {"position": [870.5, 215], "orientation": "horizontal", "room1": {"value": 4, "cut_percentage": 0.42290739737050553, "children": [], "room_type": {"name": "bedroom", "min_size": [200, 200], "max_size": [200, 500], "color": [0, 0, 255], "privacy": "private"}}, "room2": {"value": 1, "cut_percentage": 0.5171707308741075, "children": [], "room_type": {"name": "kitchen", "min_size": [200, 350], "max_size": [300, 500], "color": [255, 0, 0], "privacy": "common"}}}]}, {"node": {"value": 2, "cut_percentage": 0.44151581454401606, "children": [], "room_type": {"name": "kitchen", "min_size": [200, 350], "max_size": [300, 500], "color": [255, 0, 0], "privacy": "common"}}, "rect": [0, 215, 374, 584], "neighbors": [{"value": 1, "cut_percentage": 0.5171707308741075, "children": [], "room_type": {"name": "kitchen", "min_size": [200, 350], "max_size": [300, 500], "color": [255, 0, 0], "privacy": "common"}}, {"value": 3, "cut_percentage": 0.3848290616474309, "children": [], "room_type": {"name": "bedroom", "min_size": [200, 200], "max_size": [200, 500], "color": [0, 0, 255], "privacy": "private"}}, {"value": 5, "cut_percentage": 0.5540689493724438, "children": [], "room_type": {"name": "kitchen", "min_size": [200, 350], "max_size": [300, 500], "color": [255, 0, 0], "privacy": "common"}}], "objects": [{"name": "Fridge", "object_type": {"name": "Fridge", "effect": {"hunger": 50}}, "interaction_time": 0.5, "position": [280.5, 507.0]}, {"name": "Sink", "object_type": {"name": "Sink", "effect": {"thirst": 50}}, "interaction_time": 0.1, "position": [93.5, 361.0]}], "doors": [{"position": [187.0, 215], "orientation": "horizontal", "room1": {"value": 1, "cut_percentage": 0.5171707308741075, "children": [], "room_type": {"name": "kitchen", "min_size": [200, 350], "max_size": [300, 500], "color": [255, 0, 0], "privacy": "common"}}, "room2": {"value": 2, "cut_percentage": 0.44151581454401606, "children": [], "room_type": {"name": "kitchen", "min_size": [200, 350], "max_size": [300, 500], "color": [255, 0, 0], "privacy": "common"}}}, {"position": [374, 335.0], "orientation": "vertical", "room1": {"value": 2, "cut_percentage": 0.44151581454401606, "children": [], "room_type": {"name": "kitchen", "min_size": [200, 350], "max_size": [300, 500], "color": [255, 0, 0], "privacy": "common"}}, "room2": {"value": 3, "cut_percentage": 0.3848290616474309, "children": [], "room_type": {"name": "bedroom", "min_size": [200, 200], "max_size": [200, 500], "color": [0, 0, 255], "privacy": "private"}}}, {"position": [374, 626.5], "orientation": "vertical", "room1": {"value": 5, "cut_percentage": 0.5540689493724438, "children": [], "room_type": {"name": "kitchen", "min_size": [200, 350], "max_size": [300, 500], "color": [255, 0, 0], "privacy": "common"}}, "room2": {"value": 2, "cut_percentage": 0.44151581454401606, "children": [], "room_type": {"name": "kitchen", "min_size": [200, 350], "max_size": [300, 500], "color": [255, 0, 0], "privacy": "common"}}}]}, {"node": {"value": 3, "cut_percentage": 0.3848290616474309, "children": [], "room_type": {"name": "bedroom", "min_size": [200, 200], "max_size": [200, 500], "color": [0, 0, 255], "privacy": "private"}}, "rect": [374, 215, 369, 240], "neighbors": [{"value": 1, "cut_percentage": 0.5171707308741075, "children": [], "room_type": {"name": "kitchen", "min_size": [200, 350], "max_size": [300, 500], "color": [255, 0, 0], "privacy": "common"}}, {"value": 2, "cut_percentage": 0.44151581454401606, "children": [], "room_type": {"name": "kitchen", "min_size": [200, 350], "max_size": [300, 500], "color": [255, 0, 0], "privacy": "common"}}, {"value": 4, "cut_percentage": 0.42290739737050553, "children": [], "room_type": {"name": "bedroom", "min_size": [200, 200], "max_size": [200, 500], "color": [0, 0, 255], "privacy": "private"}}, {"value": 5, "cut_percentage": 0.5540689493724438, "children": [], "room_type": {"name": "kitchen", "min_size": [200, 350], "max_size": [300, 500], "color": [255, 0, 0], "privacy": "common"}}], "objects": [{"name": "Bed", "object_type": {"name": "Bed", "effect": {"energy": 50}}, "interaction_time": 5.9, "position": [466.25, 275.0]}], "doors": [{"position": [374, 335.0], "orientation": "vertical", "room1": {"value": 2, "cut_percentage": 0.44151581454401606, "children": [], "room_type": {"name": "kitchen", "min_size": [200, 350], "max_size": [300, 500], "color": [255, 0, 0], "privacy": "common"}}, "room2": {"value": 3, "cut_percentage": 0.3848290616474309, "children": [], "room_type": {"name": "bedroom", "min_size": [200, 200], "max_size": [200, 500], "color": [0, 0, 255], "privacy": "private"}}}, {"position": [558.5, 215], "orientation": "horizontal", "room1": {"value": 3, "cut_percentage": 0.3848290616474309, "children": [], "room_type": {"name": "bedroom", "min_size": [200, 200], "max_size": [200, 500], "color": [0, 0, 255], "privacy": "private"}}, "room2": {"value": 1, "cut_percentage": 0.5171707308741075, "children": [], "room_type": {"name": "kitchen", "min_size": [200, 350], "max_size": [300, 500], "color": [255, 0, 0], "privacy": "common"}}}]}, {"node": {"value": 4, "cut_percentage": 0.42290739737050553, "children": [], "room_type": {"name": "bedroom", "min_size": [200, 200], "max_size": [200, 500], "color": [0, 0, 255], "privacy": "private"}}, "rect": [743, 215, 255, 240], "neighbors": [{"value": 1, "cut_percentage": 0.5171707308741075, "children": [], "room_type": {"name": "kitchen", "min_size": [200, 350], "max_size": [300, 500], "color": [255, 0, 0], "privacy": "common"}}, {"value": 3, "cut_percentage": 0.3848290616474309, "children": [], "room_type": {"name": "bedroom", "min_size": [200, 200], "max_size": [200, 500], "color": [0, 0, 255], "privacy": "private"}}, {"value": 5, "cut_percentage": 0.5540689493724438, "children": [], "room_type": {"name": "kitchen", "min_size": [200, 350], "max_size": [300, 500], "color": [255, 0, 0], "privacy": "common"}}], "objects": [{"name": "Bed", "object_type": {"name": "Bed", "effect": {"energy": 50}}, "interaction_time": 5.9, "position": [934.25, 275.0]}], "doors": [{"position": [870.5, 215], "orientation": "horizontal", "room1": {"value": 4, "cut_percentage": 0.42290739737050553, "children": [], "room_type": {"name": "bedroom", "min_size": [200, 200], "max_size": [200, 500], "color": [0, 0, 255], "privacy": "private"}}, "room2": {"value": 1, "cut_percentage": 0.5171707308741075, "children": [], "room_type": {"name": "kitchen", "min_size": [200, 350], "max_size": [300, 500], "color": [255, 0, 0], "privacy": "common"}}}]}, {"node": {"value": 5, "cut_percentage": 0.5540689493724438, "children": [], "room_type": {"name": "kitchen", "min_size": [200, 350], "max_size": [300, 500], "color": [255, 0, 0], "privacy": "common"}}, "rect": [374, 455, 625, 343], "neighbors": [{"value": 2, "cut_percentage": 0.44151581454401606, "children": [], "room_type": {"name": "kitchen", "min_size": [200, 350], "max_size": [300, 500], "color": [255, 0, 0], "privacy": "common"}}, {"value": 3, "cut_percentage": 0.3848290616474309, "children": [], "room_type": {"name": "bedroom", "min_size": [200, 200], "max_size": [200, 500], "color": [0, 0, 255], "privacy": "private"}}, {"value": 4, "cut_percentage": 0.42290739737050553, "children": [], "room_type": {"name": "bedroom", "min_size": [200, 200], "max_size": [200, 500], "color": [0, 0, 255], "privacy": "private"}}], "objects": [{"name": "Fridge", "object_type": {"name": "Fridge", "effect": {"hunger": 50}}, "interaction_time": 0.5, "position": [530.25, 712.25]}, {"name": "Sink", "object_type": {"name": "Sink", "effect": {"thirst": 50}}, "interaction_time": 0.1, "position": [530.25, 540.75]}], "doors": [{"position": [374, 626.5], "orientation": "vertical", "room1": {"value": 5, "cut_percentage": 0.5540689493724438, "children": [], "room_type": {"name": "kitchen", "min_size": [200, 350], "max_size": [300, 500], "color": [255, 0, 0], "privacy": "common"}}, "room2": {"value": 2, "cut_percentage": 0.44151581454401606, "children": [], "room_type": {"name": "kitchen", "min_size": [200, 350], "max_size": [300, 500], "color": [255, 0, 0], "privacy": "common"}}}]}], "doors_list": [{"position": [187.0, 215], "orientation": "horizontal", "room1": {"value": 1, "cut_percentage": 0.5171707308741075, "children": [], "room_type": {"name": "kitchen", "min_size": [200, 350], "max_size": [300, 500], "color": [255, 0, 0], "privacy": "common"}}, "room2": {"value": 2, "cut_percentage": 0.44151581454401606, "children": [], "room_type": {"name": "kitchen", "min_size": [200, 350], "max_size": [300, 500], "color": [255, 0, 0], "privacy": "common"}}}, {"position": [374, 335.0], "orientation": "vertical", "room1": {"value": 2, "cut_percentage": 0.44151581454401606, "children": [], "room_type": {"name": "kitchen", "min_size": [200, 350], "max_size": [300, 500], "color": [255, 0, 0], "privacy": "common"}}, "room2": {"value": 3, "cut_percentage": 0.3848290616474309, "children": [], "room_type": {"name": "bedroom", "min_size": [200, 200], "max_size": [200, 500], "color": [0, 0, 255], "privacy": "private"}}}, {"position": [558.5, 215], "orientation": "horizontal", "room1": {"value": 3, "cut_percentage": 0.3848290616474309, "children": [], "room_type": {"name": "bedroom", "min_size": [200, 200], "max_size": [200, 500], "color": [0, 0, 255], "privacy": "private"}}, "room2": {"value": 1, "cut_percentage": 0.5171707308741075, "children": [], "room_type": {"name": "kitchen", "min_size": [200, 350], "max_size": [300, 500], "color": [255, 0, 0], "privacy": "common"}}}, {"position": [870.5, 215], "orientation": "horizontal", "room1": {"value": 4, "cut_percentage": 0.42290739737050553, "children": [], "room_type": {"name": "bedroom", "min_size": [200, 200], "max_size": [200, 500], "color": [0, 0, 255], "privacy": "private"}}, "room2": {"value": 1, "cut_percentage": 0.5171707308741075, "children": [], "room_type": {"name": "kitchen", "min_size": [200, 350], "max_size": [300, 500], "color": [255, 0, 0], "privacy": "common"}}}, {"position": [374, 626.5], "orientation": "vertical", "room1": {"value": 5, "cut_percentage": 0.5540689493724438, "children": [], "room_type": {"name": "kitchen", "min_size": [200, 350], "max_size": [300, 500], "color": [255, 0, 0], "privacy": "common"}}, "room2": {"value": 2, "cut_percentage": 0.44151581454401606, "children": [], "room_type": {"name": "kitchen", "min_size": [200, 350], "max_size": [300, 500], "color": [255, 0, 0], "privacy": "common"}}}], "graph": [[{"node": {"value": 1, "cut_percentage": 0.5171707308741075, "children": [], "room_type": {"name": "kitchen", "min_size": [200, 350], "max_size": [300, 500], "color": [255, 0, 0], "privacy": "common"}}, "rect": [0, 0, 1000, 215], "neighbors": [{"value": 2, "cut_percentage": 0.44151581454401606, "children": [], "room_type": {"name": "kitchen", "min_size": [200, 350], "max_size": [300, 500], "color": [255, 0, 0], "privacy": "common"}}, {"value": 3, "cut_percentage": 0.3848290616474309, "children": [], "room_type": {"name": "bedroom", "min_size": [200, 200], "max_size": [200, 500], "color": [0, 0, 255], "privacy": "private"}}, {"value": 4, "cut_percentage": 0.42290739737050553, "children": [], "room_type": {"name": "bedroom", "min_size": [200, 200], "max_size": [200, 500], "color": [0, 0, 255], "privacy": "private"}}], "objects": [{"name": "Fridge", "object_type": {"name": "Fridge", "effect": {"hunger": 50}}, "interaction_time": 0.5, "position": [750.0, 53.75]}, {"name": "Sink", "object_type": {"name": "Sink", "effect": {"thirst": 50}}, "interaction_time": 0.1, "position": [750.0, 107.5]}], "doors": [{"position": [187.0, 215], "orientation": "horizontal", "room1": {"value": 1, "cut_percentage": 0.5171707308741075, "children": [], "room_type": {"name": "kitchen", "min_size": [200, 350], "max_size": [300, 500], "color": [255, 0, 0], "privacy": "common"}}, "room2": {"value": 2, "cut_percentage": 0.44151581454401606, "children": [], "room_type": {"name": "kitchen", "min_size": [200, 350], "max_size": [300, 500], "color": [255, 0, 0], "privacy": "common"}}}, {"position": [558.5, 215], "orientation": "horizontal", "room1": {"value": 3, "cut_percentage": 0.3848290616474309, "children": [], "room_type": {"name": "bedroom", "min_size": [200, 200], "max_size": [200, 500], "color": [0, 0, 255], "privacy": "private"}}, "room2": {"value": 1, "cut_percentage": 0.5171707308741075, "children": [], "room_type": {"name": "kitchen", "min_size": [200, 350], "max_size": [300, 500], "color": [255, 0, 0], "privacy": "common"}}}, {"position": [870.5, 215], "orientation": "horizontal", "room1": {"value": 4, "cut_percentage": 0.42290739737050553, "children": [], "room_type": {"name": "bedroom", "min_size": [200, 200], "max_size": [200, 500], "color": [0, 0, 255], "privacy": "private"}}, "room2": {"value": 1, "cut_percentage": 0.5171707308741075, "children": [], "room_type": {"name": "kitchen", "min_size": [200, 350], "max_size": [300, 500], "color": [255, 0, 0], "privacy": "common"}}}]}, [{"node": {"value": 2, "cut_percentage": 0.44151581454401606, "children": [], "room_type": {"name": "kitchen", "min_size": [200, 350], "max_size": [300, 500], "color": [255, 0, 0], "privacy": "common"}}, "rect": [0, 215, 374, 584], "neighbors": [{"value": 1, "cut_percentage": 0.5171707308741075, "children": [], "room_type": {"name": "kitchen", "min_size": [200, 350], "max_size": [300, 500], "color": [255, 0, 0], "privacy": "common"}}, {"value": 3, "cut_percentage": 0.3848290616474309, "children": [], "room_type": {"name": "bedroom", "min_size": [200, 200], "max_size": [200, 500], "color": [0, 0, 255], "privacy": "private"}}, {"value": 5, "cut_percentage": 0.5540689493724438, "children": [], "room_type": {"name": "kitchen", "min_size": [200, 350], "max_size": [300, 500], "color": [255, 0, 0], "privacy": "common"}}], "objects": [{"name": "Fridge", "object_type": {"name": "Fridge", "effect": {"hunger": 50}}, "interaction_time": 0.5, "position": [280.5, 507.0]}, {"name": "Sink", "object_type": {"name": "Sink", "effect": {"thirst": 50}}, "interaction_time": 0.1, "position": [93.5, 361.0]}], "doors": [{"position": [187.0, 215], "orientation": "horizontal", "room1": {"value": 1, "cut_percentage": 0.5171707308741075, "children": [], "room_type": {"name": "kitchen", "min_size": [200, 350], "max_size": [300, 500], "color": [255, 0, 0], "privacy": "common"}}, "room2": {"value": 2, "cut_percentage": 0.44151581454401606, "children": [], "room_type": {"name": "kitchen", "min_size": [200, 350], "max_size": [300, 500], "color": [255, 0, 0], "privacy": "common"}}}, {"position": [374, 335.0], "orientation": "vertical", "room1": {"value": 2, "cut_percentage": 0.44151581454401606, "children": [], "room_type": {"name": "kitchen", "min_size": [200, 350], "max_size": [300, 500], "color": [255, 0, 0], "privacy": "common"}}, "room2": {"value": 3, "cut_percentage": 0.3848290616474309, "children": [], "room_type": {"name": "bedroom", "min_size": [200, 200], "max_size": [200, 500], "color": [0, 0, 255], "privacy": "private"}}}, {"position": [374, 626.5], "orientation": "vertical", "room1": {"value": 5, "cut_percentage": 0.5540689493724438, "children": [], "room_type": {"name": "kitchen", "min_size": [200, 350], "max_size": [300, 500], "color": [255, 0, 0], "privacy": "common"}}, "room2": {"value": 2, "cut_percentage": 0.44151581454401606, "children": [], "room_type": {"name": "kitchen", "min_size": [200, 350], "max_size": [300, 500], "color": [255, 0, 0], "privacy": "common"}}}]}, {"node": {"value": 3, "cut_percentage": 0.3848290616474309, "children": [], "room_type": {"name": "bedroom", "min_size": [200, 200], "max_size": [200, 500], "color": [0, 0, 255], "privacy": "private"}}, "rect": [374, 215, 369, 240], "neighbors": [{"value": 1, "cut_percentage": 0.5171707308741075, "children": [], "room_type": {"name": "kitchen", "min_size": [200, 350], "max_size": [300, 500], "color": [255, 0, 0], "privacy": "common"}}, {"value": 2, "cut_percentage": 0.44151581454401606, "children": [], "room_type": {"name": "kitchen", "min_size": [200, 350], "max_size": [300, 500], "color": [255, 0, 0], "privacy": "common"}}, {"value": 4, "cut_percentage": 0.42290739737050553, "children": [], "room_type": {"name": "bedroom", "min_size": [200, 200], "max_size": [200, 500], "color": [0, 0, 255], "privacy": "private"}}, {"value": 5, "cut_percentage": 0.5540689493724438, "children": [], "room_type": {"name": "kitchen", "min_size": [200, 350], "max_size": [300, 500], "color": [255, 0, 0], "privacy": "common"}}], "objects": [{"name": "Bed", "object_type": {"name": "Bed", "effect": {"energy": 50}}, "interaction_time": 5.9, "position": [466.25, 275.0]}], "doors": [{"position": [374, 335.0], "orientation": "vertical", "room1": {"value": 2, "cut_percentage": 0.44151581454401606, "children": [], "room_type": {"name": "kitchen", "min_size": [200, 350], "max_size": [300, 500], "color": [255, 0, 0], "privacy": "common"}}, "room2": {"value": 3, "cut_percentage": 0.3848290616474309, "children": [], "room_type": {"name": "bedroom", "min_size": [200, 200], "max_size": [200, 500], "color": [0, 0, 255], "privacy": "private"}}}, {"position": [558.5, 215], "orientation": "horizontal", "room1": {"value": 3, "cut_percentage": 0.3848290616474309, "children": [], "room_type": {"name": "bedroom", "min_size": [200, 200], "max_size": [200, 500], "color": [0, 0, 255], "privacy": "private"}}, "room2": {"value": 1, "cut_percentage": 0.5171707308741075, "children": [], "room_type": {"name": "kitchen", "min_size": [200, 350], "max_size": [300, 500], "color": [255, 0, 0], "privacy": "common"}}}]}, {"node": {"value": 4, "cut_percentage": 0.42290739737050553, "children": [], "room_type": {"name": "bedroom", "min_size": [200, 200], "max_size": [200, 500], "color": [0, 0, 255], "privacy": "private"}}, "rect": [743, 215, 255, 240], "neighbors": [{"value": 1, "cut_percentage": 0.5171707308741075, "children": [], "room_type": {"name": "kitchen", "min_size": [200, 350], "max_size": [300, 500], "color": [255, 0, 0], "privacy": "common"}}, {"value": 3, "cut_percentage": 0.3848290616474309, "children": [], "room_type": {"name": "bedroom", "min_size": [200, 200], "max_size": [200, 500], "color": [0, 0, 255], "privacy": "private"}}, {"value": 5, "cut_percentage": 0.5540689493724438, "children": [], "room_type": {"name": "kitchen", "min_size": [200, 350], "max_size": [300, 500], "color": [255, 0, 0], "privacy": "common"}}], "objects": [{"name": "Bed", "object_type": {"name": "Bed", "effect": {"energy": 50}}, "interaction_time": 5.9, "position": [934.25, 275.0]}], "doors": [{"position": [870.5, 215], "orientation": "horizontal", "room1": {"value": 4, "cut_percentage": 0.42290739737050553, "children": [], "room_type": {"name": "bedroom", "min_size": [200, 200], "max_size": [200, 500], "color": [0, 0, 255], "privacy": "private"}}, "room2": {"value": 1, "cut_percentage": 0.5171707308741075, "children": [], "room_type": {"name": "kitchen", "min_size": [200, 350], "max_size": [300, 500], "color": [255, 0, 0], "privacy": "common"}}}]}]], [{"node": {"value": 2, "cut_percentage": 0.44151581454401606, "children": [], "room_type": {"name": "kitchen", "min_size": [200, 350], "max_size": [300, 500], "color": [255, 0, 0], "privacy": "common"}}, "rect": [0, 215, 374, 584], "neighbors": [{"value": 1, "cut_percentage": 0.5171707308741075, "children": [], "room_type": {"name": "kitchen", "min_size": [200, 350], "max_size": [300, 500], "color": [255, 0, 0], "privacy": "common"}}, {"value": 3, "cut_percentage": 0.3848290616474309, "children": [], "room_type": {"name": "bedroom", "min_size": [200, 200], "max_size": [200, 500], "color": [0, 0, 255], "privacy": "private"}}, {"value": 5, "cut_percentage": 0.5540689493724438, "children": [], "room_type": {"name": "kitchen", "min_size": [200, 350], "max_size": [300, 500], "color": [255, 0, 0], "privacy": "common"}}], "objects": [{"name": "Fridge", "object_type": {"name": "Fridge", "effect": {"hunger": 50}}, "interaction_time": 0.5, "position": [280.5, 507.0]}, {"name": "Sink", "object_type": {"name": "Sink", "effect": {"thirst": 50}}, "interaction_time": 0.1, "position": [93.5, 361.0]}], "doors": [{"position": [187.0, 215], "orientation": "horizontal", "room1": {"value": 1, "cut_percentage": 0.5171707308741075, "children": [], "room_type": {"name": "kitchen", "min_size": [200, 350], "max_size": [300, 500], "color": [255, 0, 0], "privacy": "common"}}, "room2": {"value": 2, "cut_percentage": 0.44151581454401606, "children": [], "room_type": {"name": "kitchen", "min_size": [200, 350], "max_size": [300, 500], "color": [255, 0, 0], "privacy": "common"}}}, {"position": [374, 335.0], "orientation": "vertical", "room1": {"value": 2, "cut_percentage": 0.44151581454401606, "children": [], "room_type": {"name": "kitchen", "min_size": [200, 350], "max_size": [300, 500], "color": [255, 0, 0], "privacy": "common"}}, "room2": {"value": 3, "cut_percentage": 0.3848290616474309, "children": [], "room_type": {"name": "bedroom", "min_size": [200, 200], "max_size": [200, 500], "color": [0, 0, 255], "privacy": "private"}}}, {"position": [374, 626.5], "orientation": "vertical", "room1": {"value": 5, "cut_percentage": 0.5540689493724438, "children": [], "room_type": {"name": "kitchen", "min_size": [200, 350], "max_size": [300, 500], "color": [255, 0, 0], "privacy": "common"}}, "room2": {"value": 2, "cut_percentage": 0.44151581454401606, "children": [], "room_type": {"name": "kitchen", "min_size": [200, 350], "max_size": [300, 500], "color": [255, 0, 0], "privacy": "common"}}}]}, [{"node": {"value": 1, "cut_percentage": 0.5171707308741075, "children": [], "room_type": {"name": "kitchen", "min_size": [200, 350], "max_size": [300, 500], "color": [255, 0, 0], "privacy": "common"}}, "rect": [0, 0, 1000, 215], "neighbors": [{"value": 2, "cut_percentage": 0.44151581454401606, "children": [], "room_type": {"name": "kitchen", "min_size": [200, 350], "max_size": [300, 500], "color": [255, 0, 0], "privacy": "common"}}, {"value": 3, "cut_percentage": 0.3848290616474309, "children": [], "room_type": {"name": "bedroom", "min_size": [200, 200], "max_size": [200, 500], "color": [0, 0, 255], "privacy": "private"}}, {"value": 4, "cut_percentage": 0.42290739737050553, "children": [], "room_type": {"name": "bedroom", "min_size": [200, 200], "max_size": [200, 500], "color": [0, 0, 255], "privacy": "private"}}], "objects": [{"name": "Fridge", "object_type": {"name": "Fridge", "effect": {"hunger": 50}}, "interaction_time": 0.5, "position": [750.0, 53.75]}, {"name": "Sink", "object_type": {"name": "Sink", "effect": {"thirst": 50}}, "interaction_time": 0.1, "position": [750.0, 107.5]}], "doors": [{"position": [187.0, 215], "orientation": "horizontal", "room1": {"value": 1, "cut_percentage": 0.5171707308741075, "children": [], "room_type": {"name": "kitchen", "min_size": [200, 350], "max_size": [300, 500], "color": [255, 0, 0], "privacy": "common"}}, "room2": {"value": 2, "cut_percentage": 0.44151581454401606, "children": [], "room_type": {"name": "kitchen", "min_size": [200, 350], "max_size": [300, 500], "color": [255, 0, 0], "privacy": "common"}}}, {"position": [558.5, 215], "orientation": "horizontal", "room1": {"value": 3, "cut_percentage": 0.3848290616474309, "children": [], "room_type": {"name": "bedroom", "min_size": [200, 200], "max_size": [200, 500], "color": [0, 0, 255], "privacy": "private"}}, "room2": {"value": 1, "cut_percentage": 0.5171707308741075, "children": [], "room_type": {"name": "kitchen", "min_size": [200, 350], "max_size": [300, 500], "color": [255, 0, 0], "privacy": "common"}}}, {"position": [870.5, 215], "orientation": "horizontal", "room1": {"value": 4, "cut_percentage": 0.42290739737050553, "children": [], "room_type": {"name": "bedroom", "min_size": [200, 200], "max_size": [200, 500], "color": [0, 0, 255], "privacy": "private"}}, "room2": {"value": 1, "cut_percentage": 0.5171707308741075, "children": [], "room_type": {"name": "kitchen", "min_size": [200, 350], "max_size": [300, 500], "color": [255, 0, 0], "privacy": "common"}}}]}, {"node": {"value": 3, "cut_percentage": 0.3848290616474309, "children": [], "room_type": {"name": "bedroom", "min_size": [200, 200], "max_size": [200, 500], "color": [0, 0, 255], "privacy": "private"}}, "rect": [374, 215, 369, 240], "neighbors": [{"value": 1, "cut_percentage": 0.5171707308741075, "children": [], "room_type": {"name": "kitchen", "min_size": [200, 350], "max_size": [300, 500], "color": [255, 0, 0], "privacy": "common"}}, {"value": 2, "cut_percentage": 0.44151581454401606, "children": [], "room_type": {"name": "kitchen", "min_size": [200, 350], "max_size": [300, 500], "color": [255, 0, 0], "privacy": "common"}}, {"value": 4, "cut_percentage": 0.42290739737050553, "children": [], "room_type": {"name": "bedroom", "min_size": [200, 200], "max_size": [200, 500], "color": [0, 0, 255], "privacy": "private"}}, {"value": 5, "cut_percentage": 0.5540689493724438, "children": [], "room_type": {"name": "kitchen", "min_size": [200, 350], "max_size": [300, 500], "color": [255, 0, 0], "privacy": "common"}}], "objects": [{"name": "Bed", "object_type": {"name": "Bed", "effect": {"energy": 50}}, "interaction_time": 5.9, "position": [466.25, 275.0]}], "doors": [{"position": [374, 335.0], "orientation": "vertical", "room1": {"value": 2, "cut_percentage": 0.44151581454401606, "children": [], "room_type": {"name": "kitchen", "min_size": [200, 350], "max_size": [300, 500], "color": [255, 0, 0], "privacy": "common"}}, "room2": {"value": 3, "cut_percentage": 0.3848290616474309, "children": [], "room_type": {"name": "bedroom", "min_size": [200, 200], "max_size": [200, 500], "color": [0, 0, 255], "privacy": "private"}}}, {"position": [558.5, 215], "orientation": "horizontal", "room1": {"value": 3, "cut_percentage": 0.3848290616474309, "children": [], "room_type": {"name": "bedroom", "min_size": [200, 200], "max_size": [200, 500], "color": [0, 0, 255], "privacy": "private"}}, "room2": {"value": 1, "cut_percentage": 0.5171707308741075, "children": [], "room_type": {"name": "kitchen", "min_size": [200, 350], "max_size": [300, 500], "color": [255, 0, 0], "privacy": "common"}}}]}, {"node": {"value": 5, "cut_percentage": 0.5540689493724438, "children": [], "room_type": {"name": "kitchen", "min_size": [200, 350], "max_size": [300, 500], "color": [255, 0, 0], "privacy": "common"}}, "rect": [374, 455, 625, 343], "neighbors": [{"value": 2, "cut_percentage": 0.44151581454401606, "children": [], "room_type": {"name": "kitchen", "min_size": [200, 350], "max_size": [300, 500], "color": [255, 0, 0], "privacy": "common"}}, {"value": 3, "cut_percentage": 0.3848290616474309, "children": [], "room_type": {"name": "bedroom", "min_size": [200, 200], "max_size": [200, 500], "color": [0, 0, 255], "privacy": "private"}}, {"value": 4, "cut_percentage": 0.42290739737050553, "children": [], "room_type": {"name": "bedroom", "min_size": [200, 200], "max_size": [200, 500], "color": [0, 0, 255], "privacy": "private"}}], "objects": [{"name": "Fridge", "object_type": {"name": "Fridge", "effect": {"hunger": 50}}, "interaction_time": 0.5, "position": [530.25, 712.25]}, {"name": "Sink", "object_type": {"name": "Sink", "effect": {"thirst": 50}}, "interaction_time": 0.1, "position": [530.25, 540.75]}], "doors": [{"position": [374, 626.5], "orientation": "vertical", "room1": {"value": 5, "cut_percentage": 0.5540689493724438, "children": [], "room_type": {"name": "kitchen", "min_size": [200, 350], "max_size": [300, 500], "color": [255, 0, 0], "privacy": "common"}}, "room2": {"value": 2, "cut_percentage": 0.44151581454401606, "children": [], "room_type": {"name": "kitchen", "min_size": [200, 350], "max_size": [300, 500], "color": [255, 0, 0], "privacy": "common"}}}]}]], [{"node": {"value": 3, "cut_percentage": 0.3848290616474309, "children": [], "room_type": {"name": "bedroom", "min_size": [200, 200], "max_size": [200, 500], "color": [0, 0, 255], "privacy": "private"}}, "rect": [374, 215, 369, 240], "neighbors": [{"value": 1, "cut_percentage": 0.5171707308741075, "children": [], "room_type": {"name": "kitchen", "min_size": [200, 350], "max_size": [300, 500], "color": [255, 0, 0], "privacy": "common"}}, {"value": 2, "cut_percentage": 0.44151581454401606, "children": [], "room_type": {"name": "kitchen", "min_size": [200, 350], "max_size": [300, 500], "color": [255, 0, 0], "privacy": "common"}}, {"value": 4, "cut_percentage": 0.42290739737050553, "children": [], "room_type": {"name": "bedroom", "min_size": [200, 200], "max_size": [200, 500], "color": [0, 0, 255], "privacy": "private"}}, {"value": 5, "cut_percentage": 0.5540689493724438, "children": [], "room_type": {"name": "kitchen", "min_size": [200, 350], "max_size": [300, 500], "color": [255, 0, 0], "privacy": "common"}}], "objects": [{"name": "Bed", "object_type": {"name": "Bed", "effect": {"energy": 50}}, "interaction_time": 5.9, "position": [466.25, 275.0]}], "doors": [{"position": [374, 335.0], "orientation": "vertical", "room1": {"value": 2, "cut_percentage": 0.44151581454401606, "children": [], "room_type": {"name": "kitchen", "min_size": [200, 350], "max_size": [300, 500], "color": [255, 0, 0], "privacy": "common"}}, "room2": {"value": 3, "cut_percentage": 0.3848290616474309, "children": [], "room_type": {"name": "bedroom", "min_size": [200, 200], "max_size": [200, 500], "color": [0, 0, 255], "privacy": "private"}}}, {"position": [558.5, 215], "orientation": "horizontal", "room1": {"value": 3, "cut_percentage": 0.3848290616474309, "children": [], "room_type": {"name": "bedroom", "min_size": [200, 200], "max_size": [200, 500], "color": [0, 0, 255], "privacy": "private"}}, "room2": {"value": 1, "cut_percentage": 0.5171707308741075, "children": [], "room_type": {"name": "kitchen", "min_size": [200, 350], "max_size": [300, 500], "color": [255, 0, 0], "privacy": "common"}}}]}, [{"node": {"value": 2, "cut_percentage": 0.44151581454401606, "children": [], "room_type": {"name": "kitchen", "min_size": [200, 350], "max_size": [300, 500], "color": [255, 0, 0], "privacy": "common"}}, "rect": [0, 215, 374, 584], "neighbors": [{"value": 1, "cut_percentage": 0.5171707308741075, "children": [], "room_type": {"name": "kitchen", "min_size": [200, 350], "max_size": [300, 500], "color": [255, 0, 0], "privacy": "common"}}, {"value": 3, "cut_percentage": 0.3848290616474309, "children": [], "room_type": {"name": "bedroom", "min_size": [200, 200], "max_size": [200, 500], "color": [0, 0, 255], "privacy": "private"}}, {"value": 5, "cut_percentage": 0.5540689493724438, "children": [], "room_type": {"name": "kitchen", "min_size": [200, 350], "max_size": [300, 500], "color": [255, 0, 0], "privacy": "common"}}], "objects": [{"name": "Fridge", "object_type": {"name": "Fridge", "effect": {"hunger": 50}}, "interaction_time": 0.5, "position": [280.5, 507.0]}, {"name": "Sink", "object_type": {"name": "Sink", "effect": {"thirst": 50}}, "interaction_time": 0.1, "position": [93.5, 361.0]}], "doors": [{"position": [187.0, 215], "orientation": "horizontal", "room1": {"value": 1, "cut_percentage": 0.5171707308741075, "children": [], "room_type": {"name": "kitchen", "min_size": [200, 350], "max_size": [300, 500], "color": [255, 0, 0], "privacy": "common"}}, "room2": {"value": 2, "cut_percentage": 0.44151581454401606, "children": [], "room_type": {"name": "kitchen", "min_size": [200, 350], "max_size": [300, 500], "color": [255, 0, 0], "privacy": "common"}}}, {"position": [374, 335.0], "orientation": "vertical", "room1": {"value": 2, "cut_percentage": 0.44151581454401606, "children": [], "room_type": {"name": "kitchen", "min_size": [200, 350], "max_size": [300, 500], "color": [255, 0, 0], "privacy": "common"}}, "room2": {"value": 3, "cut_percentage": 0.3848290616474309, "children": [], "room_type": {"name": "bedroom", "min_size": [200, 200], "max_size": [200, 500], "color": [0, 0, 255], "privacy": "private"}}}, {"position": [374, 626.5], "orientation": "vertical", "room1": {"value": 5, "cut_percentage": 0.5540689493724438, "children": [], "room_type": {"name": "kitchen", "min_size": [200, 350], "max_size": [300, 500], "color": [255, 0, 0], "privacy": "common"}}, "room2": {"value": 2, "cut_percentage": 0.44151581454401606, "children": [], "room_type": {"name": "kitchen", "min_size": [200, 350], "max_size": [300, 500], "color": [255, 0, 0], "privacy": "common"}}}]}, {"node": {"value": 1, "cut_percentage": 0.5171707308741075, "children": [], "room_type": {"name": "kitchen", "min_size": [200, 350], "max_size": [300, 500], "color": [255, 0, 0], "privacy": "common"}}, "rect": [0, 0, 1000, 215], "neighbors": [{"value": 2, "cut_percentage": 0.44151581454401606, "children": [], "room_type": {"name": "kitchen", "min_size": [200, 350], "max_size": [300, 500], "color": [255, 0, 0], "privacy": "common"}}, {"value": 3, "cut_percentage": 0.3848290616474309, "children": [], "room_type": {"name": "bedroom", "min_size": [200, 200], "max_size": [200, 500], "color": [0, 0, 255], "privacy": "private"}}, {"value": 4, "cut_percentage": 0.42290739737050553, "children": [], "room_type": {"name": "bedroom", "min_size": [200, 200], "max_size": [200, 500], "color": [0, 0, 255], "privacy": "private"}}], "objects": [{"name": "Fridge", "object_type": {"name": "Fridge", "effect": {"hunger": 50}}, "interaction_time": 0.5, "position": [750.0, 53.75]}, {"name": "Sink", "object_type": {"name": "Sink", "effect": {"thirst": 50}}, "interaction_time": 0.1, "position": [750.0, 107.5]}], "doors": [{"position": [187.0, 215], "orientation": "horizontal", "room1": {"value": 1, "cut_percentage": 0.5171707308741075, "children": [], "room_type": {"name": "kitchen", "min_size": [200, 350], "max_size": [300, 500], "color": [255, 0, 0], "privacy": "common"}}, "room2": {"value": 2, "cut_percentage": 0.44151581454401606, "children": [], "room_type": {"name": "kitchen", "min_size": [200, 350], "max_size": [300, 500], "color": [255, 0, 0], "privacy": "common"}}}, {"position": [558.5, 215], "orientation": "horizontal", "room1": {"value": 3, "cut_percentage": 0.3848290616474309, "children": [], "room_type": {"name": "bedroom", "min_size": [200, 200], "max_size": [200, 500], "color": [0, 0, 255], "privacy": "private"}}, "room2": {"value": 1, "cut_percentage": 0.5171707308741075, "children": [], "room_type": {"name": "kitchen", "min_size": [200, 350], "max_size": [300, 500], "color": [255, 0, 0], "privacy": "common"}}}, {"position": [870.5, 215], "orientation": "horizontal", "room1": {"value": 4, "cut_percentage": 0.42290739737050553, "children": [], "room_type": {"name": "bedroom", "min_size": [200, 200], "max_size": [200, 500], "color": [0, 0, 255], "privacy": "private"}}, "room2": {"value": 1, "cut_percentage": 0.5171707308741075, "children": [], "room_type": {"name": "kitchen", "min_size": [200, 350], "max_size": [300, 500], "color": [255, 0, 0], "privacy": "common"}}}]}]], [{"node": {"value": 4, "cut_percentage": 0.42290739737050553, "children": [], "room_type": {"name": "bedroom", "min_size": [200, 200], "max_size": [200, 500], "color": [0, 0, 255], "privacy": "private"}}, "rect": [743, 215, 255, 240], "neighbors": [{"value": 1, "cut_percentage": 0.5171707308741075, "children": [], "room_type": {"name": "kitchen", "min_size": [200, 350], "max_size": [300, 500], "color": [255, 0, 0], "privacy": "common"}}, {"value": 3, "cut_percentage": 0.3848290616474309, "children": [], "room_type": {"name": "bedroom", "min_size": [200, 200], "max_size": [200, 500], "color": [0, 0, 255], "privacy": "private"}}, {"value": 5, "cut_percentage": 0.5540689493724438, "children": [], "room_type": {"name": "kitchen", "min_size": [200, 350], "max_size": [300, 500], "color": [255, 0, 0], "privacy": "common"}}], "objects": [{"name": "Bed", "object_type": {"name": "Bed", "effect": {"energy": 50}}, "interaction_time": 5.9, "position": [934.25, 275.0]}], "doors": [{"position": [870.5, 215], "orientation": "horizontal", "room1": {"value": 4, "cut_percentage": 0.42290739737050553, "children": [], "room_type": {"name": "bedroom", "min_size": [200, 200], "max_size": [200, 500], "color": [0, 0, 255], "privacy": "private"}}, "room2": {"value": 1, "cut_percentage": 0.5171707308741075, "children": [], "room_type": {"name": "kitchen", "min_size": [200, 350], "max_size": [300, 500], "color": [255, 0, 0], "privacy": "common"}}}]}, [{"node": {"value": 1, "cut_percentage": 0.5171707308741075, "children": [], "room_type": {"name": "kitchen", "min_size": [200, 350], "max_size": [300, 500], "color": [255, 0, 0], "privacy": "common"}}, "rect": [0, 0, 1000, 215], "neighbors": [{"value": 2, "cut_percentage": 0.44151581454401606, "children": [], "room_type": {"name": "kitchen", "min_size": [200, 350], "max_size": [300, 500], "color": [255, 0, 0], "privacy": "common"}}, {"value": 3, "cut_percentage": 0.3848290616474309, "children": [], "room_type": {"name": "bedroom", "min_size": [200, 200], "max_size": [200, 500], "color": [0, 0, 255], "privacy": "private"}}, {"value": 4, "cut_percentage": 0.42290739737050553, "children": [], "room_type": {"name": "bedroom", "min_size": [200, 200], "max_size": [200, 500], "color": [0, 0, 255], "privacy": "private"}}], "objects": [{"name": "Fridge", "object_type": {"name": "Fridge", "effect": {"hunger": 50}}, "interaction_time": 0.5, "position": [750.0, 53.75]}, {"name": "Sink", "object_type": {"name": "Sink", "effect": {"thirst": 50}}, "interaction_time": 0.1, "position": [750.0, 107.5]}], "doors": [{"position": [187.0, 215], "orientation": "horizontal", "room1": {"value": 1, "cut_percentage": 0.5171707308741075, "children": [], "room_type": {"name": "kitchen", "min_size": [200, 350], "max_size": [300, 500], "color": [255, 0, 0], "privacy": "common"}}, "room2": {"value": 2, "cut_percentage": 0.44151581454401606, "children": [], "room_type": {"name": "kitchen", "min_size": [200, 350], "max_size": [300, 500], "color": [255, 0, 0], "privacy": "common"}}}, {"position": [558.5, 215], "orientation": "horizontal", "room1": {"value": 3, "cut_percentage": 0.3848290616474309, "children": [], "room_type": {"name": "bedroom", "min_size": [200, 200], "max_size": [200, 500], "color": [0, 0, 255], "privacy": "private"}}, "room2": {"value": 1, "cut_percentage": 0.5171707308741075, "children": [], "room_type": {"name": "kitchen", "min_size": [200, 350], "max_size": [300, 500], "color": [255, 0, 0], "privacy": "common"}}}, {"position": [870.5, 215], "orientation": "horizontal", "room1": {"value": 4, "cut_percentage": 0.42290739737050553, "children": [], "room_type": {"name": "bedroom", "min_size": [200, 200], "max_size": [200, 500], "color": [0, 0, 255], "privacy": "private"}}, "room2": {"value": 1, "cut_percentage": 0.5171707308741075, "children": [], "room_type": {"name": "kitchen", "min_size": [200, 350], "max_size": [300, 500], "color": [255, 0, 0], "privacy": "common"}}}]}]], [{"node": {"value": 5, "cut_percentage": 0.5540689493724438, "children": [], "room_type": {"name": "kitchen", "min_size": [200, 350], "max_size": [300, 500], "color": [255, 0, 0], "privacy": "common"}}, "rect": [374, 455, 625, 343], "neighbors": [{"value": 2, "cut_percentage": 0.44151581454401606, "children": [], "room_type": {"name": "kitchen", "min_size": [200, 350], "max_size": [300, 500], "color": [255, 0, 0], "privacy": "common"}}, {"value": 3, "cut_percentage": 0.3848290616474309, "children": [], "room_type": {"name": "bedroom", "min_size": [200, 200], "max_size": [200, 500], "color": [0, 0, 255], "privacy": "private"}}, {"value": 4, "cut_percentage": 0.42290739737050553, "children": [], "room_type": {"name": "bedroom", "min_size": [200, 200], "max_size": [200, 500], "color": [0, 0, 255], "privacy": "private"}}], "objects": [{"name": "Fridge", "object_type": {"name": "Fridge", "effect": {"hunger": 50}}, "interaction_time": 0.5, "position": [530.25, 712.25]}, {"name": "Sink", "object_type": {"name": "Sink", "effect": {"thirst": 50}}, "interaction_time": 0.1, "position": [530.25, 540.75]}], "doors": [{"position": [374, 626.5], "orientation": "vertical", "room1": {"value": 5, "cut_percentage": 0.5540689493724438, "children": [], "room_type": {"name": "kitchen", "min_size": [200, 350], "max_size": [300, 500], "color": [255, 0, 0], "privacy": "common"}}, "room2": {"value": 2, "cut_percentage": 0.44151581454401606, "children": [], "room_type": {"name": "kitchen", "min_size": [200, 350], "max_size": [300, 500], "color": [255, 0, 0], "privacy": "common"}}}]}, [{"node": {"value": 2, "cut_percentage": 0.44151581454401606, "children": [], "room_type": {"name": "kitchen", "min_size": [200, 350], "max_size": [300, 500], "color": [255, 0, 0], "privacy": "common"}}, "rect": [0, 215, 374, 584], "neighbors": [{"value": 1, "cut_percentage": 0.5171707308741075, "children": [], "room_type": {"name": "kitchen", "min_size": [200, 350], "max_size": [300, 500], "color": [255, 0, 0], "privacy": "common"}}, {"value": 3, "cut_percentage": 0.3848290616474309, "children": [], "room_type": {"name": "bedroom", "min_size": [200, 200], "max_size": [200, 500], "color": [0, 0, 255], "privacy": "private"}}, {"value": 5, "cut_percentage": 0.5540689493724438, "children": [], "room_type": {"name": "kitchen", "min_size": [200, 350], "max_size": [300, 500], "color": [255, 0, 0], "privacy": "common"}}], "objects": [{"name": "Fridge", "object_type": {"name": "Fridge", "effect": {"hunger": 50}}, "interaction_time": 0.5, "position": [280.5, 507.0]}, {"name": "Sink", "object_type": {"name": "Sink", "effect": {"thirst": 50}}, "interaction_time": 0.1, "position": [93.5, 361.0]}], "doors": [{"position": [187.0, 215], "orientation": "horizontal", "room1": {"value": 1, "cut_percentage": 0.5171707308741075, "children": [], "room_type": {"name": "kitchen", "min_size": [200, 350], "max_size": [300, 500], "color": [255, 0, 0], "privacy": "common"}}, "room2": {"value": 2, "cut_percentage": 0.44151581454401606, "children": [], "room_type": {"name": "kitchen", "min_size": [200, 350], "max_size": [300, 500], "color": [255, 0, 0], "privacy": "common"}}}, {"position": [374, 335.0], "orientation": "vertical", "room1": {"value": 2, "cut_percentage": 0.44151581454401606, "children": [], "room_type": {"name": "kitchen", "min_size": [200, 350], "max_size": [300, 500], "color": [255, 0, 0], "privacy": "common"}}, "room2": {"value": 3, "cut_percentage": 0.3848290616474309, "children": [], "room_type": {"name": "bedroom", "min_size": [200, 200], "max_size": [200, 500], "color": [0, 0, 255], "privacy": "private"}}}, {"position": [374, 626.5], "orientation": "vertical", "room1": {"value": 5, "cut_percentage": 0.5540689493724438, "children": [], "room_type": {"name": "kitchen", "min_size": [200, 350], "max_size": [300, 500], "color": [255, 0, 0], "privacy": "common"}}, "room2": {"value": 2, "cut_percentage": 0.44151581454401606, "children": [], "room_type": {"name": "kitchen", "min_size": [200, 350], "max_size": [300, 500], "color": [255, 0, 0], "privacy": "common"}}}]}]]], "fitness": 18, "agents_paths": {"Agent 1": [[["private", "bedroom"], ["common", "kitchen"], ["common", "kitchen"]], [["common", "kitchen"]], [["common", "kitchen"], ["common", "kitchen"], ["private", "bedroom"]], [["private", "bedroom"], ["common", "kitchen"], ["private", "bedroom"]], [["private", "bedroom"], ["common", "kitchen"]], [["common", "kitchen"], ["common", "kitchen"]], [["common", "kitchen"], ["common", "kitchen"]], [["common", "kitchen"], ["common", "kitchen"]], [["common", "kitchen"]], [["common", "kitchen"], ["common", "kitchen"], ["common", "kitchen"]], [["common", "kitchen"], ["common", "kitchen"]], [["common", "kitchen"], ["private", "bedroom"]], [["private", "bedroom"], ["common", "kitchen"], ["private", "bedroom"]], [["private", "bedroom"], ["common", "kitchen"], ["common", "kitchen"]], [["common", "kitchen"]], [["common", "kitchen"], ["common", "kitchen"]], [["common", "kitchen"], ["common", "kitchen"], ["common", "kitchen"]], [["common", "kitchen"], ["common", "kitchen"], ["private", "bedroom"]], [["private", "bedroom"], ["common", "kitchen"]], [["common", "kitchen"], ["common", "kitchen"], ["common", "kitchen"]], [["common", "kitchen"], ["common", "kitchen"], ["common", "kitchen"]], [["common", "kitchen"], ["private", "bedroom"]], [["private", "bedroom"], ["common", "kitchen"], ["common", "kitchen"]], [["common", "kitchen"], ["common", "kitchen"]]], "Agent 2": [[["private", "bedroom"], ["common", "kitchen"]], [["common", "kitchen"], ["private", "bedroom"]], [["private", "bedroom"], ["common", "kitchen"]], [["common", "kitchen"], ["common", "kitchen"], ["common", "kitchen"]], [["common", "kitchen"]], [["common", "kitchen"], ["common", "kitchen"], ["private", "bedroom"]], [["private", "bedroom"], ["common", "kitchen"]], [["common", "kitchen"]], [["common", "kitchen"], ["common", "kitchen"], ["private", "bedroom"]], [["private", "bedroom"], ["common", "kitchen"], ["common", "kitchen"]], [["common", "kitchen"], ["common", "kitchen"]], [["common", "kitchen"]], [["common", "kitchen"], ["common", "kitchen"], ["private", "bedroom"]], [["private", "bedroom"], ["common", "kitchen"], ["private", "bedroom"]]]}, "agents_activites": {"Agent 1": [["Agent 1", " interacting with ", "Sink", " current time in minutes ", "24", " expected interaction finish time ", "30.0", " the interaction in hours: ", "0.1"], ["Agent 1", " interacting with ", "Fridge", " current time in minutes ", "36", " expected interaction finish time ", "66.0", " the interaction in hours: ", "0.5"], ["Agent 1", " interacting with ", "Bed", " current time in minutes ", "88", " expected interaction finish time ", "442.0", " the interaction in hours: ", "5.9"], ["Agent 1", " interacting with ", "Sink", " current time in minutes ", "449", " expected interaction finish time ", "455.0", " the interaction in hours: ", "0.1"], ["Agent 1", " interacting with ", "Fridge", " current time in minutes ", "471", " expected interaction finish time ", "501.0", " the interaction in hours: ", "0.5"], ["Agent 1", " interacting with ", "Sink", " current time in minutes ", "514", " expected interaction finish time ", "520.0", " the interaction in hours: ", "0.1"], ["Agent 1", " interacting with ", "Sink", " current time in minutes ", "522", " expected interaction finish time ", "528.0", " the interaction in hours: ", "0.1"], ["Agent 1", " interacting with ", "Sink", " current time in minutes ", "545", " expected interaction finish time ", "551.0", " the interaction in hours: ", "0.1"], ["Agent 1", " interacting with ", "Fridge", " current time in minutes ", "557", " expected interaction finish time ", "587.0", " the interaction in hours: ", "0.5"], ["Agent 1", " interacting with ", "Bed", " current time in minutes ", "541", " expected interaction finish time ", "895.0", " the interaction in hours: ", "5.9"], ["Agent 1", " interacting with ", "Fridge", " current time in minutes ", "849", " expected interaction finish time ", "879.0", " the interaction in hours: ", "0.5"], ["Agent 1", " interacting with ", "Fridge", " current time in minutes ", "913", " expected interaction finish time ", "943.0", " the interaction in hours: ", "0.5"], ["Agent 1", " interacting with ", "Sink", " current time in minutes ", "955", " expected interaction finish time ", "961.0", " the interaction in hours: ", "0.1"], ["Agent 1", " interacting with ", "Sink", " current time in minutes ", "986", " expected interaction finish time ", "992.0", " the interaction in hours: ", "0.1"], ["Agent 1", " interacting with ", "Bed", " current time in minutes ", "1001", " expected interaction finish time ", "1355.0", " the interaction in hours: ", "5.9"], ["Agent 1", " interacting with ", "Sink", " current time in minutes ", "1361", " expected interaction finish time ", "1367.0", " the interaction in hours: ", "0.1"], ["Agent 1", " interacting with ", "Fridge", " current time in minutes ", "1321", " expected interaction finish time ", "1351.0", " the interaction in hours: ", "0.5"], ["Agent 1", " interacting with ", "Sink", " current time in minutes ", "1408", " expected interaction finish time ", "1414.0", " the interaction in hours: ", "0.1"], ["Agent 1", " interacting with ", "Sink", " current time in minutes ", "1430", " expected interaction finish time ", "1436.0", " the interaction in hours: ", "0.1"]], "Agent 2": [["Agent 2", " interacting with ", "Sink", " current time in minutes ", "18", " expected interaction finish time ", "24.0", " the interaction in hours: ", "0.1"], ["Agent 2", " interacting with ", "Bed", " current time in minutes ", "31", " expected interaction finish time ", "385.0", " the interaction in hours: ", "5.9"], ["Agent 2", " interacting with ", "Fridge", " current time in minutes ", "392", " expected interaction finish time ", "422.0", " the interaction in hours: ", "0.5"], ["Agent 2", " interacting with ", "Sink", " current time in minutes ", "438", " expected interaction finish time ", "444.0", " the interaction in hours: ", "0.1"], ["Agent 2", " interacting with ", "Fridge", " current time in minutes ", "449", " expected interaction finish time ", "479.0", " the interaction in hours: ", "0.5"], ["Agent 2", " interacting with ", "Bed", " current time in minutes ", "495", " expected interaction finish time ", "849.0", " the interaction in hours: ", "5.9"], ["Agent 2", " interacting with ", "Fridge", " current time in minutes ", "855", " expected interaction finish time ", "885.0", " the interaction in hours: ", "0.5"], ["Agent 2", " interacting with ", "Sink", " current time in minutes ", "890", " expected interaction finish time ", "896.0", " the interaction in hours: ", "0.1"], ["Agent 2", " interacting with ", "Bed", " current time in minutes ", "849", " expected interaction finish time ", "1203.0", " the interaction in hours: ", "5.9"], ["Agent 2", " interacting with ", "Sink", " current time in minutes ", "1225", " expected interaction finish time ", "1231.0", " the interaction in hours: ", "0.1"], ["Agent 2", " interacting with ", "Fridge", " current time in minutes ", "1239", " expected interaction finish time ", "1269.0", " the interaction in hours: ", "0.5"], ["Agent 2", " interacting with ", "Sink", " current time in minutes ", "1278", " expected interaction finish time ", "1284.0", " the interaction in hours: ", "0.1"], ["Agent 2", " interacting with ", "Bed", " current time in minutes ", "1301", " expected interaction finish time ", "1655.0", " the interaction in hours: ", "5.9"]]}, "neighbouring_rooms": {"kitchen": ["kitchen", "bedroom", "bedroom"], "bedroom": ["kitchen", "bedroom", "kitchen"]}, "mutated": false, "crossover": false, "parent1": null, "parent2": null, "mutation_probability": null, "agents_have_bedrooms": 0}