{"num_rooms": 5, "room_types": [{"name": "bathroom", "min_size": [150, 200], "max_size": [150, 250], "color": [255, 155, 20], "privacy": "private"}, {"name": "kitchen", "min_size": [200, 350], "max_size": [300, 500], "color": [255, 0, 0], "privacy": "common"}, {"name": "bedroom", "min_size": [200, 200], "max_size": [200, 500], "color": [0, 0, 255], "privacy": "private"}, {"name": "bedroom", "min_size": [200, 200], "max_size": [200, 500], "color": [0, 0, 255], "privacy": "private"}, {"name": "bedroom", "min_size": [200, 200], "max_size": [200, 500], "color": [0, 0, 255], "privacy": "private"}], "slicing_tree_root": {"value": "V", "cut_percentage": 0.29549163436001175, "children": [{"value": "H", "cut_percentage": 0.49605571090275713, "children": [{"value": 1, "cut_percentage": 0.4709281149158185, "children": [], "room_type": {"name": "bedroom", "min_size": [200, 200], "max_size": [200, 500], "color": [0, 0, 255], "privacy": "private"}}, {"value": 4, "cut_percentage": 0.46659923539210946, "children": [], "room_type": {"name": "bedroom", "min_size": [200, 200], "max_size": [200, 500], "color": [0, 0, 255], "privacy": "private"}}], "room_type": null}, {"value": "V", "cut_percentage": 0.6337611889785038, "children": [{"value": 3, "cut_percentage": 0.6375006477181153, "children": [], "room_type": {"name": "bathroom", "min_size": [150, 200], "max_size": [150, 250], "color": [255, 155, 20], "privacy": "private"}}, {"value": "H", "cut_percentage": 0.5808407264531963, "children": [{"value": 5, "cut_percentage": 0.45316670998671743, "children": [], "room_type": {"name": "bedroom", "min_size": [200, 200], "max_size": [200, 500], "color": [0, 0, 255], "privacy": "private"}}, {"value": 2, "cut_percentage": 0.4551228027482337, "children": [], "room_type": {"name": "bedroom", "min_size": [200, 200], "max_size": [200, 500], "color": [0, 0, 255], "privacy": "private"}}], "room_type": null}], "room_type": null}], "room_type": null}, "rooms": [{"node": {"value": 1, "cut_percentage": 0.4709281149158185, "children": [], "room_type": {"name": "bedroom", "min_size": [200, 200], "max_size": [200, 500], "color": [0, 0, 255], "privacy": "private"}}, "rect": [0, 0, 295, 396], "neighbors": [{"value": 4, "cut_percentage": 0.46659923539210946, "children": [], "room_type": {"name": "bedroom", "min_size": [200, 200], "max_size": [200, 500], "color": [0, 0, 255], "privacy": "private"}}, {"value": 3, "cut_percentage": 0.6375006477181153, "children": [], "room_type": {"name": "bathroom", "min_size": [150, 200], "max_size": [150, 250], "color": [255, 155, 20], "privacy": "private"}}], "objects": [{"name": "Bed", "object_type": {"name": "Bed", "effect": {"energy": 50}}, "interaction_time": 4.1, "position": [221.25, 99.0]}], "doors": [{"position": [147.5, 396], "orientation": "horizontal", "room1": {"value": 1, "cut_percentage": 0.4709281149158185, "children": [], "room_type": {"name": "bedroom", "min_size": [200, 200], "max_size": [200, 500], "color": [0, 0, 255], "privacy": "private"}}, "room2": {"value": 4, "cut_percentage": 0.46659923539210946, "children": [], "room_type": {"name": "bedroom", "min_size": [200, 200], "max_size": [200, 500], "color": [0, 0, 255], "privacy": "private"}}}, {"position": [295, 198.0], "orientation": "vertical", "room1": {"value": 3, "cut_percentage": 0.6375006477181153, "children": [], "room_type": {"name": "bathroom", "min_size": [150, 200], "max_size": [150, 250], "color": [255, 155, 20], "privacy": "private"}}, "room2": {"value": 1, "cut_percentage": 0.4709281149158185, "children": [], "room_type": {"name": "bedroom", "min_size": [200, 200], "max_size": [200, 500], "color": [0, 0, 255], "privacy": "private"}}}]}, {"node": {"value": 4, "cut_percentage": 0.46659923539210946, "children": [], "room_type": {"name": "bedroom", "min_size": [200, 200], "max_size": [200, 500], "color": [0, 0, 255], "privacy": "private"}}, "rect": [0, 396, 295, 403], "neighbors": [{"value": 1, "cut_percentage": 0.4709281149158185, "children": [], "room_type": {"name": "bedroom", "min_size": [200, 200], "max_size": [200, 500], "color": [0, 0, 255], "privacy": "private"}}, {"value": 3, "cut_percentage": 0.6375006477181153, "children": [], "room_type": {"name": "bathroom", "min_size": [150, 200], "max_size": [150, 250], "color": [255, 155, 20], "privacy": "private"}}], "objects": [{"name": "Bed", "object_type": {"name": "Bed", "effect": {"energy": 50}}, "interaction_time": 4.1, "position": [73.75, 698.25]}], "doors": [{"position": [147.5, 396], "orientation": "horizontal", "room1": {"value": 1, "cut_percentage": 0.4709281149158185, "children": [], "room_type": {"name": "bedroom", "min_size": [200, 200], "max_size": [200, 500], "color": [0, 0, 255], "privacy": "private"}}, "room2": {"value": 4, "cut_percentage": 0.46659923539210946, "children": [], "room_type": {"name": "bedroom", "min_size": [200, 200], "max_size": [200, 500], "color": [0, 0, 255], "privacy": "private"}}}, {"position": [295, 597.5], "orientation": "vertical", "room1": {"value": 4, "cut_percentage": 0.46659923539210946, "children": [], "room_type": {"name": "bedroom", "min_size": [200, 200], "max_size": [200, 500], "color": [0, 0, 255], "privacy": "private"}}, "room2": {"value": 3, "cut_percentage": 0.6375006477181153, "children": [], "room_type": {"name": "bathroom", "min_size": [150, 200], "max_size": [150, 250], "color": [255, 155, 20], "privacy": "private"}}}]}, {"node": {"value": 3, "cut_percentage": 0.6375006477181153, "children": [], "room_type": {"name": "bathroom", "min_size": [150, 200], "max_size": [150, 250], "color": [255, 155, 20], "privacy": "private"}}, "rect": [295, 0, 446, 800], "neighbors": [{"value": 1, "cut_percentage": 0.4709281149158185, "children": [], "room_type": {"name": "bedroom", "min_size": [200, 200], "max_size": [200, 500], "color": [0, 0, 255], "privacy": "private"}}, {"value": 4, "cut_percentage": 0.46659923539210946, "children": [], "room_type": {"name": "bedroom", "min_size": [200, 200], "max_size": [200, 500], "color": [0, 0, 255], "privacy": "private"}}, {"value": 5, "cut_percentage": 0.45316670998671743, "children": [], "room_type": {"name": "bedroom", "min_size": [200, 200], "max_size": [200, 500], "color": [0, 0, 255], "privacy": "private"}}, {"value": 2, "cut_percentage": 0.4551228027482337, "children": [], "room_type": {"name": "bedroom", "min_size": [200, 200], "max_size": [200, 500], "color": [0, 0, 255], "privacy": "private"}}], "objects": [{"name": "Toilet", "object_type": {"name": "Toilet", "effect": {"bladder": 60}}, "interaction_time": 0.4, "position": [629.5, 400.0]}, {"name": "Shower", "object_type": {"name": "Shower", "effect": {"hygiene": 60}}, "interaction_time": 0.4, "position": [629.5, 400.0]}], "doors": [{"position": [295, 597.5], "orientation": "vertical", "room1": {"value": 4, "cut_percentage": 0.46659923539210946, "children": [], "room_type": {"name": "bedroom", "min_size": [200, 200], "max_size": [200, 500], "color": [0, 0, 255], "privacy": "private"}}, "room2": {"value": 3, "cut_percentage": 0.6375006477181153, "children": [], "room_type": {"name": "bathroom", "min_size": [150, 200], "max_size": [150, 250], "color": [255, 155, 20], "privacy": "private"}}}, {"position": [295, 198.0], "orientation": "vertical", "room1": {"value": 3, "cut_percentage": 0.6375006477181153, "children": [], "room_type": {"name": "bathroom", "min_size": [150, 200], "max_size": [150, 250], "color": [255, 155, 20], "privacy": "private"}}, "room2": {"value": 1, "cut_percentage": 0.4709281149158185, "children": [], "room_type": {"name": "bedroom", "min_size": [200, 200], "max_size": [200, 500], "color": [0, 0, 255], "privacy": "private"}}}, {"position": [741, 232.0], "orientation": "vertical", "room1": {"value": 5, "cut_percentage": 0.45316670998671743, "children": [], "room_type": {"name": "bedroom", "min_size": [200, 200], "max_size": [200, 500], "color": [0, 0, 255], "privacy": "private"}}, "room2": {"value": 3, "cut_percentage": 0.6375006477181153, "children": [], "room_type": {"name": "bathroom", "min_size": [150, 200], "max_size": [150, 250], "color": [255, 155, 20], "privacy": "private"}}}, {"position": [741, 631.5], "orientation": "vertical", "room1": {"value": 2, "cut_percentage": 0.4551228027482337, "children": [], "room_type": {"name": "bedroom", "min_size": [200, 200], "max_size": [200, 500], "color": [0, 0, 255], "privacy": "private"}}, "room2": {"value": 3, "cut_percentage": 0.6375006477181153, "children": [], "room_type": {"name": "bathroom", "min_size": [150, 200], "max_size": [150, 250], "color": [255, 155, 20], "privacy": "private"}}}]}, {"node": {"value": 5, "cut_percentage": 0.45316670998671743, "children": [], "room_type": {"name": "bedroom", "min_size": [200, 200], "max_size": [200, 500], "color": [0, 0, 255], "privacy": "private"}}, "rect": [741, 0, 257, 464], "neighbors": [{"value": 3, "cut_percentage": 0.6375006477181153, "children": [], "room_type": {"name": "bathroom", "min_size": [150, 200], "max_size": [150, 250], "color": [255, 155, 20], "privacy": "private"}}, {"value": 2, "cut_percentage": 0.4551228027482337, "children": [], "room_type": {"name": "bedroom", "min_size": [200, 200], "max_size": [200, 500], "color": [0, 0, 255], "privacy": "private"}}], "objects": [{"name": "Bed", "object_type": {"name": "Bed", "effect": {"energy": 50}}, "interaction_time": 4.1, "position": [933.75, 348.0]}], "doors": [{"position": [741, 232.0], "orientation": "vertical", "room1": {"value": 5, "cut_percentage": 0.45316670998671743, "children": [], "room_type": {"name": "bedroom", "min_size": [200, 200], "max_size": [200, 500], "color": [0, 0, 255], "privacy": "private"}}, "room2": {"value": 3, "cut_percentage": 0.6375006477181153, "children": [], "room_type": {"name": "bathroom", "min_size": [150, 200], "max_size": [150, 250], "color": [255, 155, 20], "privacy": "private"}}}]}, {"node": {"value": 2, "cut_percentage": 0.4551228027482337, "children": [], "room_type": {"name": "bedroom", "min_size": [200, 200], "max_size": [200, 500], "color": [0, 0, 255], "privacy": "private"}}, "rect": [741, 464, 257, 335], "neighbors": [{"value": 3, "cut_percentage": 0.6375006477181153, "children": [], "room_type": {"name": "bathroom", "min_size": [150, 200], "max_size": [150, 250], "color": [255, 155, 20], "privacy": "private"}}, {"value": 5, "cut_percentage": 0.45316670998671743, "children": [], "room_type": {"name": "bedroom", "min_size": [200, 200], "max_size": [200, 500], "color": [0, 0, 255], "privacy": "private"}}], "objects": [{"name": "Bed", "object_type": {"name": "Bed", "effect": {"energy": 50}}, "interaction_time": 4.1, "position": [805.25, 715.25]}], "doors": [{"position": [741, 631.5], "orientation": "vertical", "room1": {"value": 2, "cut_percentage": 0.4551228027482337, "children": [], "room_type": {"name": "bedroom", "min_size": [200, 200], "max_size": [200, 500], "color": [0, 0, 255], "privacy": "private"}}, "room2": {"value": 3, "cut_percentage": 0.6375006477181153, "children": [], "room_type": {"name": "bathroom", "min_size": [150, 200], "max_size": [150, 250], "color": [255, 155, 20], "privacy": "private"}}}]}], "doors_list": [{"position": [147.5, 396], "orientation": "horizontal", "room1": {"value": 1, "cut_percentage": 0.4709281149158185, "children": [], "room_type": {"name": "bedroom", "min_size": [200, 200], "max_size": [200, 500], "color": [0, 0, 255], "privacy": "private"}}, "room2": {"value": 4, "cut_percentage": 0.46659923539210946, "children": [], "room_type": {"name": "bedroom", "min_size": [200, 200], "max_size": [200, 500], "color": [0, 0, 255], "privacy": "private"}}}, {"position": [295, 597.5], "orientation": "vertical", "room1": {"value": 4, "cut_percentage": 0.46659923539210946, "children": [], "room_type": {"name": "bedroom", "min_size": [200, 200], "max_size": [200, 500], "color": [0, 0, 255], "privacy": "private"}}, "room2": {"value": 3, "cut_percentage": 0.6375006477181153, "children": [], "room_type": {"name": "bathroom", "min_size": [150, 200], "max_size": [150, 250], "color": [255, 155, 20], "privacy": "private"}}}, {"position": [295, 198.0], "orientation": "vertical", "room1": {"value": 3, "cut_percentage": 0.6375006477181153, "children": [], "room_type": {"name": "bathroom", "min_size": [150, 200], "max_size": [150, 250], "color": [255, 155, 20], "privacy": "private"}}, "room2": {"value": 1, "cut_percentage": 0.4709281149158185, "children": [], "room_type": {"name": "bedroom", "min_size": [200, 200], "max_size": [200, 500], "color": [0, 0, 255], "privacy": "private"}}}, {"position": [741, 232.0], "orientation": "vertical", "room1": {"value": 5, "cut_percentage": 0.45316670998671743, "children": [], "room_type": {"name": "bedroom", "min_size": [200, 200], "max_size": [200, 500], "color": [0, 0, 255], "privacy": "private"}}, "room2": {"value": 3, "cut_percentage": 0.6375006477181153, "children": [], "room_type": {"name": "bathroom", "min_size": [150, 200], "max_size": [150, 250], "color": [255, 155, 20], "privacy": "private"}}}, {"position": [741, 631.5], "orientation": "vertical", "room1": {"value": 2, "cut_percentage": 0.4551228027482337, "children": [], "room_type": {"name": "bedroom", "min_size": [200, 200], "max_size": [200, 500], "color": [0, 0, 255], "privacy": "private"}}, "room2": {"value": 3, "cut_percentage": 0.6375006477181153, "children": [], "room_type": {"name": "bathroom", "min_size": [150, 200], "max_size": [150, 250], "color": [255, 155, 20], "privacy": "private"}}}], "graph": [[{"node": {"value": 1, "cut_percentage": 0.4709281149158185, "children": [], "room_type": {"name": "bedroom", "min_size": [200, 200], "max_size": [200, 500], "color": [0, 0, 255], "privacy": "private"}}, "rect": [0, 0, 295, 396], "neighbors": [{"value": 4, "cut_percentage": 0.46659923539210946, "children": [], "room_type": {"name": "bedroom", "min_size": [200, 200], "max_size": [200, 500], "color": [0, 0, 255], "privacy": "private"}}, {"value": 3, "cut_percentage": 0.6375006477181153, "children": [], "room_type": {"name": "bathroom", "min_size": [150, 200], "max_size": [150, 250], "color": [255, 155, 20], "privacy": "private"}}], "objects": [{"name": "Bed", "object_type": {"name": "Bed", "effect": {"energy": 50}}, "interaction_time": 4.1, "position": [221.25, 99.0]}], "doors": [{"position": [147.5, 396], "orientation": "horizontal", "room1": {"value": 1, "cut_percentage": 0.4709281149158185, "children": [], "room_type": {"name": "bedroom", "min_size": [200, 200], "max_size": [200, 500], "color": [0, 0, 255], "privacy": "private"}}, "room2": {"value": 4, "cut_percentage": 0.46659923539210946, "children": [], "room_type": {"name": "bedroom", "min_size": [200, 200], "max_size": [200, 500], "color": [0, 0, 255], "privacy": "private"}}}, {"position": [295, 198.0], "orientation": "vertical", "room1": {"value": 3, "cut_percentage": 0.6375006477181153, "children": [], "room_type": {"name": "bathroom", "min_size": [150, 200], "max_size": [150, 250], "color": [255, 155, 20], "privacy": "private"}}, "room2": {"value": 1, "cut_percentage": 0.4709281149158185, "children": [], "room_type": {"name": "bedroom", "min_size": [200, 200], "max_size": [200, 500], "color": [0, 0, 255], "privacy": "private"}}}]}, [{"node": {"value": 4, "cut_percentage": 0.46659923539210946, "children": [], "room_type": {"name": "bedroom", "min_size": [200, 200], "max_size": [200, 500], "color": [0, 0, 255], "privacy": "private"}}, "rect": [0, 396, 295, 403], "neighbors": [{"value": 1, "cut_percentage": 0.4709281149158185, "children": [], "room_type": {"name": "bedroom", "min_size": [200, 200], "max_size": [200, 500], "color": [0, 0, 255], "privacy": "private"}}, {"value": 3, "cut_percentage": 0.6375006477181153, "children": [], "room_type": {"name": "bathroom", "min_size": [150, 200], "max_size": [150, 250], "color": [255, 155, 20], "privacy": "private"}}], "objects": [{"name": "Bed", "object_type": {"name": "Bed", "effect": {"energy": 50}}, "interaction_time": 4.1, "position": [73.75, 698.25]}], "doors": [{"position": [147.5, 396], "orientation": "horizontal", "room1": {"value": 1, "cut_percentage": 0.4709281149158185, "children": [], "room_type": {"name": "bedroom", "min_size": [200, 200], "max_size": [200, 500], "color": [0, 0, 255], "privacy": "private"}}, "room2": {"value": 4, "cut_percentage": 0.46659923539210946, "children": [], "room_type": {"name": "bedroom", "min_size": [200, 200], "max_size": [200, 500], "color": [0, 0, 255], "privacy": "private"}}}, {"position": [295, 597.5], "orientation": "vertical", "room1": {"value": 4, "cut_percentage": 0.46659923539210946, "children": [], "room_type": {"name": "bedroom", "min_size": [200, 200], "max_size": [200, 500], "color": [0, 0, 255], "privacy": "private"}}, "room2": {"value": 3, "cut_percentage": 0.6375006477181153, "children": [], "room_type": {"name": "bathroom", "min_size": [150, 200], "max_size": [150, 250], "color": [255, 155, 20], "privacy": "private"}}}]}, {"node": {"value": 3, "cut_percentage": 0.6375006477181153, "children": [], "room_type": {"name": "bathroom", "min_size": [150, 200], "max_size": [150, 250], "color": [255, 155, 20], "privacy": "private"}}, "rect": [295, 0, 446, 800], "neighbors": [{"value": 1, "cut_percentage": 0.4709281149158185, "children": [], "room_type": {"name": "bedroom", "min_size": [200, 200], "max_size": [200, 500], "color": [0, 0, 255], "privacy": "private"}}, {"value": 4, "cut_percentage": 0.46659923539210946, "children": [], "room_type": {"name": "bedroom", "min_size": [200, 200], "max_size": [200, 500], "color": [0, 0, 255], "privacy": "private"}}, {"value": 5, "cut_percentage": 0.45316670998671743, "children": [], "room_type": {"name": "bedroom", "min_size": [200, 200], "max_size": [200, 500], "color": [0, 0, 255], "privacy": "private"}}, {"value": 2, "cut_percentage": 0.4551228027482337, "children": [], "room_type": {"name": "bedroom", "min_size": [200, 200], "max_size": [200, 500], "color": [0, 0, 255], "privacy": "private"}}], "objects": [{"name": "Toilet", "object_type": {"name": "Toilet", "effect": {"bladder": 60}}, "interaction_time": 0.4, "position": [629.5, 400.0]}, {"name": "Shower", "object_type": {"name": "Shower", "effect": {"hygiene": 60}}, "interaction_time": 0.4, "position": [629.5, 400.0]}], "doors": [{"position": [295, 597.5], "orientation": "vertical", "room1": {"value": 4, "cut_percentage": 0.46659923539210946, "children": [], "room_type": {"name": "bedroom", "min_size": [200, 200], "max_size": [200, 500], "color": [0, 0, 255], "privacy": "private"}}, "room2": {"value": 3, "cut_percentage": 0.6375006477181153, "children": [], "room_type": {"name": "bathroom", "min_size": [150, 200], "max_size": [150, 250], "color": [255, 155, 20], "privacy": "private"}}}, {"position": [295, 198.0], "orientation": "vertical", "room1": {"value": 3, "cut_percentage": 0.6375006477181153, "children": [], "room_type": {"name": "bathroom", "min_size": [150, 200], "max_size": [150, 250], "color": [255, 155, 20], "privacy": "private"}}, "room2": {"value": 1, "cut_percentage": 0.4709281149158185, "children": [], "room_type": {"name": "bedroom", "min_size": [200, 200], "max_size": [200, 500], "color": [0, 0, 255], "privacy": "private"}}}, {"position": [741, 232.0], "orientation": "vertical", "room1": {"value": 5, "cut_percentage": 0.45316670998671743, "children": [], "room_type": {"name": "bedroom", "min_size": [200, 200], "max_size": [200, 500], "color": [0, 0, 255], "privacy": "private"}}, "room2": {"value": 3, "cut_percentage": 0.6375006477181153, "children": [], "room_type": {"name": "bathroom", "min_size": [150, 200], "max_size": [150, 250], "color": [255, 155, 20], "privacy": "private"}}}, {"position": [741, 631.5], "orientation": "vertical", "room1": {"value": 2, "cut_percentage": 0.4551228027482337, "children": [], "room_type": {"name": "bedroom", "min_size": [200, 200], "max_size": [200, 500], "color": [0, 0, 255], "privacy": "private"}}, "room2": {"value": 3, "cut_percentage": 0.6375006477181153, "children": [], "room_type": {"name": "bathroom", "min_size": [150, 200], "max_size": [150, 250], "color": [255, 155, 20], "privacy": "private"}}}]}]], [{"node": {"value": 4, "cut_percentage": 0.46659923539210946, "children": [], "room_type": {"name": "bedroom", "min_size": [200, 200], "max_size": [200, 500], "color": [0, 0, 255], "privacy": "private"}}, "rect": [0, 396, 295, 403], "neighbors": [{"value": 1, "cut_percentage": 0.4709281149158185, "children": [], "room_type": {"name": "bedroom", "min_size": [200, 200], "max_size": [200, 500], "color": [0, 0, 255], "privacy": "private"}}, {"value": 3, "cut_percentage": 0.6375006477181153, "children": [], "room_type": {"name": "bathroom", "min_size": [150, 200], "max_size": [150, 250], "color": [255, 155, 20], "privacy": "private"}}], "objects": [{"name": "Bed", "object_type": {"name": "Bed", "effect": {"energy": 50}}, "interaction_time": 4.1, "position": [73.75, 698.25]}], "doors": [{"position": [147.5, 396], "orientation": "horizontal", "room1": {"value": 1, "cut_percentage": 0.4709281149158185, "children": [], "room_type": {"name": "bedroom", "min_size": [200, 200], "max_size": [200, 500], "color": [0, 0, 255], "privacy": "private"}}, "room2": {"value": 4, "cut_percentage": 0.46659923539210946, "children": [], "room_type": {"name": "bedroom", "min_size": [200, 200], "max_size": [200, 500], "color": [0, 0, 255], "privacy": "private"}}}, {"position": [295, 597.5], "orientation": "vertical", "room1": {"value": 4, "cut_percentage": 0.46659923539210946, "children": [], "room_type": {"name": "bedroom", "min_size": [200, 200], "max_size": [200, 500], "color": [0, 0, 255], "privacy": "private"}}, "room2": {"value": 3, "cut_percentage": 0.6375006477181153, "children": [], "room_type": {"name": "bathroom", "min_size": [150, 200], "max_size": [150, 250], "color": [255, 155, 20], "privacy": "private"}}}]}, [{"node": {"value": 1, "cut_percentage": 0.4709281149158185, "children": [], "room_type": {"name": "bedroom", "min_size": [200, 200], "max_size": [200, 500], "color": [0, 0, 255], "privacy": "private"}}, "rect": [0, 0, 295, 396], "neighbors": [{"value": 4, "cut_percentage": 0.46659923539210946, "children": [], "room_type": {"name": "bedroom", "min_size": [200, 200], "max_size": [200, 500], "color": [0, 0, 255], "privacy": "private"}}, {"value": 3, "cut_percentage": 0.6375006477181153, "children": [], "room_type": {"name": "bathroom", "min_size": [150, 200], "max_size": [150, 250], "color": [255, 155, 20], "privacy": "private"}}], "objects": [{"name": "Bed", "object_type": {"name": "Bed", "effect": {"energy": 50}}, "interaction_time": 4.1, "position": [221.25, 99.0]}], "doors": [{"position": [147.5, 396], "orientation": "horizontal", "room1": {"value": 1, "cut_percentage": 0.4709281149158185, "children": [], "room_type": {"name": "bedroom", "min_size": [200, 200], "max_size": [200, 500], "color": [0, 0, 255], "privacy": "private"}}, "room2": {"value": 4, "cut_percentage": 0.46659923539210946, "children": [], "room_type": {"name": "bedroom", "min_size": [200, 200], "max_size": [200, 500], "color": [0, 0, 255], "privacy": "private"}}}, {"position": [295, 198.0], "orientation": "vertical", "room1": {"value": 3, "cut_percentage": 0.6375006477181153, "children": [], "room_type": {"name": "bathroom", "min_size": [150, 200], "max_size": [150, 250], "color": [255, 155, 20], "privacy": "private"}}, "room2": {"value": 1, "cut_percentage": 0.4709281149158185, "children": [], "room_type": {"name": "bedroom", "min_size": [200, 200], "max_size": [200, 500], "color": [0, 0, 255], "privacy": "private"}}}]}, {"node": {"value": 3, "cut_percentage": 0.6375006477181153, "children": [], "room_type": {"name": "bathroom", "min_size": [150, 200], "max_size": [150, 250], "color": [255, 155, 20], "privacy": "private"}}, "rect": [295, 0, 446, 800], "neighbors": [{"value": 1, "cut_percentage": 0.4709281149158185, "children": [], "room_type": {"name": "bedroom", "min_size": [200, 200], "max_size": [200, 500], "color": [0, 0, 255], "privacy": "private"}}, {"value": 4, "cut_percentage": 0.46659923539210946, "children": [], "room_type": {"name": "bedroom", "min_size": [200, 200], "max_size": [200, 500], "color": [0, 0, 255], "privacy": "private"}}, {"value": 5, "cut_percentage": 0.45316670998671743, "children": [], "room_type": {"name": "bedroom", "min_size": [200, 200], "max_size": [200, 500], "color": [0, 0, 255], "privacy": "private"}}, {"value": 2, "cut_percentage": 0.4551228027482337, "children": [], "room_type": {"name": "bedroom", "min_size": [200, 200], "max_size": [200, 500], "color": [0, 0, 255], "privacy": "private"}}], "objects": [{"name": "Toilet", "object_type": {"name": "Toilet", "effect": {"bladder": 60}}, "interaction_time": 0.4, "position": [629.5, 400.0]}, {"name": "Shower", "object_type": {"name": "Shower", "effect": {"hygiene": 60}}, "interaction_time": 0.4, "position": [629.5, 400.0]}], "doors": [{"position": [295, 597.5], "orientation": "vertical", "room1": {"value": 4, "cut_percentage": 0.46659923539210946, "children": [], "room_type": {"name": "bedroom", "min_size": [200, 200], "max_size": [200, 500], "color": [0, 0, 255], "privacy": "private"}}, "room2": {"value": 3, "cut_percentage": 0.6375006477181153, "children": [], "room_type": {"name": "bathroom", "min_size": [150, 200], "max_size": [150, 250], "color": [255, 155, 20], "privacy": "private"}}}, {"position": [295, 198.0], "orientation": "vertical", "room1": {"value": 3, "cut_percentage": 0.6375006477181153, "children": [], "room_type": {"name": "bathroom", "min_size": [150, 200], "max_size": [150, 250], "color": [255, 155, 20], "privacy": "private"}}, "room2": {"value": 1, "cut_percentage": 0.4709281149158185, "children": [], "room_type": {"name": "bedroom", "min_size": [200, 200], "max_size": [200, 500], "color": [0, 0, 255], "privacy": "private"}}}, {"position": [741, 232.0], "orientation": "vertical", "room1": {"value": 5, "cut_percentage": 0.45316670998671743, "children": [], "room_type": {"name": "bedroom", "min_size": [200, 200], "max_size": [200, 500], "color": [0, 0, 255], "privacy": "private"}}, "room2": {"value": 3, "cut_percentage": 0.6375006477181153, "children": [], "room_type": {"name": "bathroom", "min_size": [150, 200], "max_size": [150, 250], "color": [255, 155, 20], "privacy": "private"}}}, {"position": [741, 631.5], "orientation": "vertical", "room1": {"value": 2, "cut_percentage": 0.4551228027482337, "children": [], "room_type": {"name": "bedroom", "min_size": [200, 200], "max_size": [200, 500], "color": [0, 0, 255], "privacy": "private"}}, "room2": {"value": 3, "cut_percentage": 0.6375006477181153, "children": [], "room_type": {"name": "bathroom", "min_size": [150, 200], "max_size": [150, 250], "color": [255, 155, 20], "privacy": "private"}}}]}]], [{"node": {"value": 3, "cut_percentage": 0.6375006477181153, "children": [], "room_type": {"name": "bathroom", "min_size": [150, 200], "max_size": [150, 250], "color": [255, 155, 20], "privacy": "private"}}, "rect": [295, 0, 446, 800], "neighbors": [{"value": 1, "cut_percentage": 0.4709281149158185, "children": [], "room_type": {"name": "bedroom", "min_size": [200, 200], "max_size": [200, 500], "color": [0, 0, 255], "privacy": "private"}}, {"value": 4, "cut_percentage": 0.46659923539210946, "children": [], "room_type": {"name": "bedroom", "min_size": [200, 200], "max_size": [200, 500], "color": [0, 0, 255], "privacy": "private"}}, {"value": 5, "cut_percentage": 0.45316670998671743, "children": [], "room_type": {"name": "bedroom", "min_size": [200, 200], "max_size": [200, 500], "color": [0, 0, 255], "privacy": "private"}}, {"value": 2, "cut_percentage": 0.4551228027482337, "children": [], "room_type": {"name": "bedroom", "min_size": [200, 200], "max_size": [200, 500], "color": [0, 0, 255], "privacy": "private"}}], "objects": [{"name": "Toilet", "object_type": {"name": "Toilet", "effect": {"bladder": 60}}, "interaction_time": 0.4, "position": [629.5, 400.0]}, {"name": "Shower", "object_type": {"name": "Shower", "effect": {"hygiene": 60}}, "interaction_time": 0.4, "position": [629.5, 400.0]}], "doors": [{"position": [295, 597.5], "orientation": "vertical", "room1": {"value": 4, "cut_percentage": 0.46659923539210946, "children": [], "room_type": {"name": "bedroom", "min_size": [200, 200], "max_size": [200, 500], "color": [0, 0, 255], "privacy": "private"}}, "room2": {"value": 3, "cut_percentage": 0.6375006477181153, "children": [], "room_type": {"name": "bathroom", "min_size": [150, 200], "max_size": [150, 250], "color": [255, 155, 20], "privacy": "private"}}}, {"position": [295, 198.0], "orientation": "vertical", "room1": {"value": 3, "cut_percentage": 0.6375006477181153, "children": [], "room_type": {"name": "bathroom", "min_size": [150, 200], "max_size": [150, 250], "color": [255, 155, 20], "privacy": "private"}}, "room2": {"value": 1, "cut_percentage": 0.4709281149158185, "children": [], "room_type": {"name": "bedroom", "min_size": [200, 200], "max_size": [200, 500], "color": [0, 0, 255], "privacy": "private"}}}, {"position": [741, 232.0], "orientation": "vertical", "room1": {"value": 5, "cut_percentage": 0.45316670998671743, "children": [], "room_type": {"name": "bedroom", "min_size": [200, 200], "max_size": [200, 500], "color": [0, 0, 255], "privacy": "private"}}, "room2": {"value": 3, "cut_percentage": 0.6375006477181153, "children": [], "room_type": {"name": "bathroom", "min_size": [150, 200], "max_size": [150, 250], "color": [255, 155, 20], "privacy": "private"}}}, {"position": [741, 631.5], "orientation": "vertical", "room1": {"value": 2, "cut_percentage": 0.4551228027482337, "children": [], "room_type": {"name": "bedroom", "min_size": [200, 200], "max_size": [200, 500], "color": [0, 0, 255], "privacy": "private"}}, "room2": {"value": 3, "cut_percentage": 0.6375006477181153, "children": [], "room_type": {"name": "bathroom", "min_size": [150, 200], "max_size": [150, 250], "color": [255, 155, 20], "privacy": "private"}}}]}, [{"node": {"value": 4, "cut_percentage": 0.46659923539210946, "children": [], "room_type": {"name": "bedroom", "min_size": [200, 200], "max_size": [200, 500], "color": [0, 0, 255], "privacy": "private"}}, "rect": [0, 396, 295, 403], "neighbors": [{"value": 1, "cut_percentage": 0.4709281149158185, "children": [], "room_type": {"name": "bedroom", "min_size": [200, 200], "max_size": [200, 500], "color": [0, 0, 255], "privacy": "private"}}, {"value": 3, "cut_percentage": 0.6375006477181153, "children": [], "room_type": {"name": "bathroom", "min_size": [150, 200], "max_size": [150, 250], "color": [255, 155, 20], "privacy": "private"}}], "objects": [{"name": "Bed", "object_type": {"name": "Bed", "effect": {"energy": 50}}, "interaction_time": 4.1, "position": [73.75, 698.25]}], "doors": [{"position": [147.5, 396], "orientation": "horizontal", "room1": {"value": 1, "cut_percentage": 0.4709281149158185, "children": [], "room_type": {"name": "bedroom", "min_size": [200, 200], "max_size": [200, 500], "color": [0, 0, 255], "privacy": "private"}}, "room2": {"value": 4, "cut_percentage": 0.46659923539210946, "children": [], "room_type": {"name": "bedroom", "min_size": [200, 200], "max_size": [200, 500], "color": [0, 0, 255], "privacy": "private"}}}, {"position": [295, 597.5], "orientation": "vertical", "room1": {"value": 4, "cut_percentage": 0.46659923539210946, "children": [], "room_type": {"name": "bedroom", "min_size": [200, 200], "max_size": [200, 500], "color": [0, 0, 255], "privacy": "private"}}, "room2": {"value": 3, "cut_percentage": 0.6375006477181153, "children": [], "room_type": {"name": "bathroom", "min_size": [150, 200], "max_size": [150, 250], "color": [255, 155, 20], "privacy": "private"}}}]}, {"node": {"value": 1, "cut_percentage": 0.4709281149158185, "children": [], "room_type": {"name": "bedroom", "min_size": [200, 200], "max_size": [200, 500], "color": [0, 0, 255], "privacy": "private"}}, "rect": [0, 0, 295, 396], "neighbors": [{"value": 4, "cut_percentage": 0.46659923539210946, "children": [], "room_type": {"name": "bedroom", "min_size": [200, 200], "max_size": [200, 500], "color": [0, 0, 255], "privacy": "private"}}, {"value": 3, "cut_percentage": 0.6375006477181153, "children": [], "room_type": {"name": "bathroom", "min_size": [150, 200], "max_size": [150, 250], "color": [255, 155, 20], "privacy": "private"}}], "objects": [{"name": "Bed", "object_type": {"name": "Bed", "effect": {"energy": 50}}, "interaction_time": 4.1, "position": [221.25, 99.0]}], "doors": [{"position": [147.5, 396], "orientation": "horizontal", "room1": {"value": 1, "cut_percentage": 0.4709281149158185, "children": [], "room_type": {"name": "bedroom", "min_size": [200, 200], "max_size": [200, 500], "color": [0, 0, 255], "privacy": "private"}}, "room2": {"value": 4, "cut_percentage": 0.46659923539210946, "children": [], "room_type": {"name": "bedroom", "min_size": [200, 200], "max_size": [200, 500], "color": [0, 0, 255], "privacy": "private"}}}, {"position": [295, 198.0], "orientation": "vertical", "room1": {"value": 3, "cut_percentage": 0.6375006477181153, "children": [], "room_type": {"name": "bathroom", "min_size": [150, 200], "max_size": [150, 250], "color": [255, 155, 20], "privacy": "private"}}, "room2": {"value": 1, "cut_percentage": 0.4709281149158185, "children": [], "room_type": {"name": "bedroom", "min_size": [200, 200], "max_size": [200, 500], "color": [0, 0, 255], "privacy": "private"}}}]}, {"node": {"value": 5, "cut_percentage": 0.45316670998671743, "children": [], "room_type": {"name": "bedroom", "min_size": [200, 200], "max_size": [200, 500], "color": [0, 0, 255], "privacy": "private"}}, "rect": [741, 0, 257, 464], "neighbors": [{"value": 3, "cut_percentage": 0.6375006477181153, "children": [], "room_type": {"name": "bathroom", "min_size": [150, 200], "max_size": [150, 250], "color": [255, 155, 20], "privacy": "private"}}, {"value": 2, "cut_percentage": 0.4551228027482337, "children": [], "room_type": {"name": "bedroom", "min_size": [200, 200], "max_size": [200, 500], "color": [0, 0, 255], "privacy": "private"}}], "objects": [{"name": "Bed", "object_type": {"name": "Bed", "effect": {"energy": 50}}, "interaction_time": 4.1, "position": [933.75, 348.0]}], "doors": [{"position": [741, 232.0], "orientation": "vertical", "room1": {"value": 5, "cut_percentage": 0.45316670998671743, "children": [], "room_type": {"name": "bedroom", "min_size": [200, 200], "max_size": [200, 500], "color": [0, 0, 255], "privacy": "private"}}, "room2": {"value": 3, "cut_percentage": 0.6375006477181153, "children": [], "room_type": {"name": "bathroom", "min_size": [150, 200], "max_size": [150, 250], "color": [255, 155, 20], "privacy": "private"}}}]}, {"node": {"value": 2, "cut_percentage": 0.4551228027482337, "children": [], "room_type": {"name": "bedroom", "min_size": [200, 200], "max_size": [200, 500], "color": [0, 0, 255], "privacy": "private"}}, "rect": [741, 464, 257, 335], "neighbors": [{"value": 3, "cut_percentage": 0.6375006477181153, "children": [], "room_type": {"name": "bathroom", "min_size": [150, 200], "max_size": [150, 250], "color": [255, 155, 20], "privacy": "private"}}, {"value": 5, "cut_percentage": 0.45316670998671743, "children": [], "room_type": {"name": "bedroom", "min_size": [200, 200], "max_size": [200, 500], "color": [0, 0, 255], "privacy": "private"}}], "objects": [{"name": "Bed", "object_type": {"name": "Bed", "effect": {"energy": 50}}, "interaction_time": 4.1, "position": [805.25, 715.25]}], "doors": [{"position": [741, 631.5], "orientation": "vertical", "room1": {"value": 2, "cut_percentage": 0.4551228027482337, "children": [], "room_type": {"name": "bedroom", "min_size": [200, 200], "max_size": [200, 500], "color": [0, 0, 255], "privacy": "private"}}, "room2": {"value": 3, "cut_percentage": 0.6375006477181153, "children": [], "room_type": {"name": "bathroom", "min_size": [150, 200], "max_size": [150, 250], "color": [255, 155, 20], "privacy": "private"}}}]}]], [{"node": {"value": 5, "cut_percentage": 0.45316670998671743, "children": [], "room_type": {"name": "bedroom", "min_size": [200, 200], "max_size": [200, 500], "color": [0, 0, 255], "privacy": "private"}}, "rect": [741, 0, 257, 464], "neighbors": [{"value": 3, "cut_percentage": 0.6375006477181153, "children": [], "room_type": {"name": "bathroom", "min_size": [150, 200], "max_size": [150, 250], "color": [255, 155, 20], "privacy": "private"}}, {"value": 2, "cut_percentage": 0.4551228027482337, "children": [], "room_type": {"name": "bedroom", "min_size": [200, 200], "max_size": [200, 500], "color": [0, 0, 255], "privacy": "private"}}], "objects": [{"name": "Bed", "object_type": {"name": "Bed", "effect": {"energy": 50}}, "interaction_time": 4.1, "position": [933.75, 348.0]}], "doors": [{"position": [741, 232.0], "orientation": "vertical", "room1": {"value": 5, "cut_percentage": 0.45316670998671743, "children": [], "room_type": {"name": "bedroom", "min_size": [200, 200], "max_size": [200, 500], "color": [0, 0, 255], "privacy": "private"}}, "room2": {"value": 3, "cut_percentage": 0.6375006477181153, "children": [], "room_type": {"name": "bathroom", "min_size": [150, 200], "max_size": [150, 250], "color": [255, 155, 20], "privacy": "private"}}}]}, [{"node": {"value": 3, "cut_percentage": 0.6375006477181153, "children": [], "room_type": {"name": "bathroom", "min_size": [150, 200], "max_size": [150, 250], "color": [255, 155, 20], "privacy": "private"}}, "rect": [295, 0, 446, 800], "neighbors": [{"value": 1, "cut_percentage": 0.4709281149158185, "children": [], "room_type": {"name": "bedroom", "min_size": [200, 200], "max_size": [200, 500], "color": [0, 0, 255], "privacy": "private"}}, {"value": 4, "cut_percentage": 0.46659923539210946, "children": [], "room_type": {"name": "bedroom", "min_size": [200, 200], "max_size": [200, 500], "color": [0, 0, 255], "privacy": "private"}}, {"value": 5, "cut_percentage": 0.45316670998671743, "children": [], "room_type": {"name": "bedroom", "min_size": [200, 200], "max_size": [200, 500], "color": [0, 0, 255], "privacy": "private"}}, {"value": 2, "cut_percentage": 0.4551228027482337, "children": [], "room_type": {"name": "bedroom", "min_size": [200, 200], "max_size": [200, 500], "color": [0, 0, 255], "privacy": "private"}}], "objects": [{"name": "Toilet", "object_type": {"name": "Toilet", "effect": {"bladder": 60}}, "interaction_time": 0.4, "position": [629.5, 400.0]}, {"name": "Shower", "object_type": {"name": "Shower", "effect": {"hygiene": 60}}, "interaction_time": 0.4, "position": [629.5, 400.0]}], "doors": [{"position": [295, 597.5], "orientation": "vertical", "room1": {"value": 4, "cut_percentage": 0.46659923539210946, "children": [], "room_type": {"name": "bedroom", "min_size": [200, 200], "max_size": [200, 500], "color": [0, 0, 255], "privacy": "private"}}, "room2": {"value": 3, "cut_percentage": 0.6375006477181153, "children": [], "room_type": {"name": "bathroom", "min_size": [150, 200], "max_size": [150, 250], "color": [255, 155, 20], "privacy": "private"}}}, {"position": [295, 198.0], "orientation": "vertical", "room1": {"value": 3, "cut_percentage": 0.6375006477181153, "children": [], "room_type": {"name": "bathroom", "min_size": [150, 200], "max_size": [150, 250], "color": [255, 155, 20], "privacy": "private"}}, "room2": {"value": 1, "cut_percentage": 0.4709281149158185, "children": [], "room_type": {"name": "bedroom", "min_size": [200, 200], "max_size": [200, 500], "color": [0, 0, 255], "privacy": "private"}}}, {"position": [741, 232.0], "orientation": "vertical", "room1": {"value": 5, "cut_percentage": 0.45316670998671743, "children": [], "room_type": {"name": "bedroom", "min_size": [200, 200], "max_size": [200, 500], "color": [0, 0, 255], "privacy": "private"}}, "room2": {"value": 3, "cut_percentage": 0.6375006477181153, "children": [], "room_type": {"name": "bathroom", "min_size": [150, 200], "max_size": [150, 250], "color": [255, 155, 20], "privacy": "private"}}}, {"position": [741, 631.5], "orientation": "vertical", "room1": {"value": 2, "cut_percentage": 0.4551228027482337, "children": [], "room_type": {"name": "bedroom", "min_size": [200, 200], "max_size": [200, 500], "color": [0, 0, 255], "privacy": "private"}}, "room2": {"value": 3, "cut_percentage": 0.6375006477181153, "children": [], "room_type": {"name": "bathroom", "min_size": [150, 200], "max_size": [150, 250], "color": [255, 155, 20], "privacy": "private"}}}]}]], [{"node": {"value": 2, "cut_percentage": 0.4551228027482337, "children": [], "room_type": {"name": "bedroom", "min_size": [200, 200], "max_size": [200, 500], "color": [0, 0, 255], "privacy": "private"}}, "rect": [741, 464, 257, 335], "neighbors": [{"value": 3, "cut_percentage": 0.6375006477181153, "children": [], "room_type": {"name": "bathroom", "min_size": [150, 200], "max_size": [150, 250], "color": [255, 155, 20], "privacy": "private"}}, {"value": 5, "cut_percentage": 0.45316670998671743, "children": [], "room_type": {"name": "bedroom", "min_size": [200, 200], "max_size": [200, 500], "color": [0, 0, 255], "privacy": "private"}}], "objects": [{"name": "Bed", "object_type": {"name": "Bed", "effect": {"energy": 50}}, "interaction_time": 4.1, "position": [805.25, 715.25]}], "doors": [{"position": [741, 631.5], "orientation": "vertical", "room1": {"value": 2, "cut_percentage": 0.4551228027482337, "children": [], "room_type": {"name": "bedroom", "min_size": [200, 200], "max_size": [200, 500], "color": [0, 0, 255], "privacy": "private"}}, "room2": {"value": 3, "cut_percentage": 0.6375006477181153, "children": [], "room_type": {"name": "bathroom", "min_size": [150, 200], "max_size": [150, 250], "color": [255, 155, 20], "privacy": "private"}}}]}, [{"node": {"value": 3, "cut_percentage": 0.6375006477181153, "children": [], "room_type": {"name": "bathroom", "min_size": [150, 200], "max_size": [150, 250], "color": [255, 155, 20], "privacy": "private"}}, "rect": [295, 0, 446, 800], "neighbors": [{"value": 1, "cut_percentage": 0.4709281149158185, "children": [], "room_type": {"name": "bedroom", "min_size": [200, 200], "max_size": [200, 500], "color": [0, 0, 255], "privacy": "private"}}, {"value": 4, "cut_percentage": 0.46659923539210946, "children": [], "room_type": {"name": "bedroom", "min_size": [200, 200], "max_size": [200, 500], "color": [0, 0, 255], "privacy": "private"}}, {"value": 5, "cut_percentage": 0.45316670998671743, "children": [], "room_type": {"name": "bedroom", "min_size": [200, 200], "max_size": [200, 500], "color": [0, 0, 255], "privacy": "private"}}, {"value": 2, "cut_percentage": 0.4551228027482337, "children": [], "room_type": {"name": "bedroom", "min_size": [200, 200], "max_size": [200, 500], "color": [0, 0, 255], "privacy": "private"}}], "objects": [{"name": "Toilet", "object_type": {"name": "Toilet", "effect": {"bladder": 60}}, "interaction_time": 0.4, "position": [629.5, 400.0]}, {"name": "Shower", "object_type": {"name": "Shower", "effect": {"hygiene": 60}}, "interaction_time": 0.4, "position": [629.5, 400.0]}], "doors": [{"position": [295, 597.5], "orientation": "vertical", "room1": {"value": 4, "cut_percentage": 0.46659923539210946, "children": [], "room_type": {"name": "bedroom", "min_size": [200, 200], "max_size": [200, 500], "color": [0, 0, 255], "privacy": "private"}}, "room2": {"value": 3, "cut_percentage": 0.6375006477181153, "children": [], "room_type": {"name": "bathroom", "min_size": [150, 200], "max_size": [150, 250], "color": [255, 155, 20], "privacy": "private"}}}, {"position": [295, 198.0], "orientation": "vertical", "room1": {"value": 3, "cut_percentage": 0.6375006477181153, "children": [], "room_type": {"name": "bathroom", "min_size": [150, 200], "max_size": [150, 250], "color": [255, 155, 20], "privacy": "private"}}, "room2": {"value": 1, "cut_percentage": 0.4709281149158185, "children": [], "room_type": {"name": "bedroom", "min_size": [200, 200], "max_size": [200, 500], "color": [0, 0, 255], "privacy": "private"}}}, {"position": [741, 232.0], "orientation": "vertical", "room1": {"value": 5, "cut_percentage": 0.45316670998671743, "children": [], "room_type": {"name": "bedroom", "min_size": [200, 200], "max_size": [200, 500], "color": [0, 0, 255], "privacy": "private"}}, "room2": {"value": 3, "cut_percentage": 0.6375006477181153, "children": [], "room_type": {"name": "bathroom", "min_size": [150, 200], "max_size": [150, 250], "color": [255, 155, 20], "privacy": "private"}}}, {"position": [741, 631.5], "orientation": "vertical", "room1": {"value": 2, "cut_percentage": 0.4551228027482337, "children": [], "room_type": {"name": "bedroom", "min_size": [200, 200], "max_size": [200, 500], "color": [0, 0, 255], "privacy": "private"}}, "room2": {"value": 3, "cut_percentage": 0.6375006477181153, "children": [], "room_type": {"name": "bathroom", "min_size": [150, 200], "max_size": [150, 250], "color": [255, 155, 20], "privacy": "private"}}}]}]]], "fitness": 6, "agents_paths": {"Agent 1": [[["private", "bedroom"], ["private", "bathroom"]], [["private", "bathroom"]], [["private", "bathroom"], ["private", "bedroom"]], [["private", "bedroom"], ["private", "bathroom"], ["private", "bedroom"]], [["private", "bedroom"], ["private", "bathroom"]], [["private", "bathroom"]], [["private", "bathroom"]], [["private", "bathroom"]], [["private", "bathroom"]], [["private", "bathroom"]], [["private", "bathroom"], ["private", "bedroom"]], [["private", "bedroom"], ["private", "bathroom"]], [["private", "bathroom"], ["private", "bedroom"]], [["private", "bedroom"], ["private", "bathroom"]], [["private", "bathroom"]], [["private", "bathroom"]], [["private", "bathroom"], ["private", "bedroom"]], [["private", "bedroom"], ["private", "bathroom"]], [["private", "bathroom"]], [["private", "bathroom"]], [["private", "bathroom"], ["private", "bedroom"]]], "Agent 2": [[["private", "bedroom"], ["private", "bathroom"]], [["private", "bathroom"], ["private", "bedroom"]], [["private", "bedroom"], ["private", "bathroom"]], [["private", "bathroom"]], [["private", "bathroom"]], [["private", "bathroom"]], [["private", "bathroom"], ["private", "bedroom"]], [["private", "bedroom"], ["private", "bathroom"]], [["private", "bathroom"]], [["private", "bathroom"]], [["private", "bathroom"]], [["private", "bathroom"]], [["private", "bathroom"], ["private", "bedroom"]], [["private", "bedroom"], ["private", "bathroom"]], [["private", "bathroom"]], [["private", "bathroom"]], [["private", "bathroom"]], [["private", "bathroom"], ["private", "bedroom"]]]}, "agents_activites": {"Agent 1": [["Agent 1", " interacting with ", "Shower", " current time in minutes ", "29", " expected interaction finish time ", "53.0", " the interaction in hours: ", "0.4"], ["Agent 1", " interacting with ", "Toilet", " current time in minutes ", "60", " expected interaction finish time ", "84.0", " the interaction in hours: ", "0.4"], ["Agent 1", " interacting with ", "Bed", " current time in minutes ", "122", " expected interaction finish time ", "368.0", " the interaction in hours: ", "4.1"], ["Agent 1", " interacting with ", "Toilet", " current time in minutes ", "379", " expected interaction finish time ", "403.0", " the interaction in hours: ", "0.4"], ["Agent 1", " interacting with ", "Shower", " current time in minutes ", "411", " expected interaction finish time ", "435.0", " the interaction in hours: ", "0.4"], ["Agent 1", " interacting with ", "Toilet", " current time in minutes ", "439", " expected interaction finish time ", "463.0", " the interaction in hours: ", "0.4"], ["Agent 1", " interacting with ", "Toilet", " current time in minutes ", "469", " expected interaction finish time ", "493.0", " the interaction in hours: ", "0.4"], ["Agent 1", " interacting with ", "Toilet", " current time in minutes ", "498", " expected interaction finish time ", "522.0", " the interaction in hours: ", "0.4"], ["Agent 1", " interacting with ", "Shower", " current time in minutes ", "530", " expected interaction finish time ", "554.0", " the interaction in hours: ", "0.4"], ["Agent 1", " interacting with ", "Toilet", " current time in minutes ", "586", " expected interaction finish time ", "610.0", " the interaction in hours: ", "0.4"], ["Agent 1", " interacting with ", "Bed", " current time in minutes ", "621", " expected interaction finish time ", "867.0", " the interaction in hours: ", "4.1"], ["Agent 1", " interacting with ", "Toilet", " current time in minutes ", "880", " expected interaction finish time ", "904.0", " the interaction in hours: ", "0.4"], ["Agent 1", " interacting with ", "Shower", " current time in minutes ", "919", " expected interaction finish time ", "943.0", " the interaction in hours: ", "0.4"], ["Agent 1", " interacting with ", "Toilet", " current time in minutes ", "947", " expected interaction finish time ", "971.0", " the interaction in hours: ", "0.4"], ["Agent 1", " interacting with ", "Bed", " current time in minutes ", "994", " expected interaction finish time ", "1240.0", " the interaction in hours: ", "4.1"], ["Agent 1", " interacting with ", "Shower", " current time in minutes ", "1255", " expected interaction finish time ", "1279.0", " the interaction in hours: ", "0.4"], ["Agent 1", " interacting with ", "Toilet", " current time in minutes ", "1288", " expected interaction finish time ", "1312.0", " the interaction in hours: ", "0.4"], ["Agent 1", " interacting with ", "Shower", " current time in minutes ", "1315", " expected interaction finish time ", "1339.0", " the interaction in hours: ", "0.4"], ["Agent 1", " interacting with ", "Bed", " current time in minutes ", "1360", " expected interaction finish time ", "1606.0", " the interaction in hours: ", "4.1"]], "Agent 2": [["Agent 2", " interacting with ", "Toilet", " current time in minutes ", "29", " expected interaction finish time ", "53.0", " the interaction in hours: ", "0.4"], ["Agent 2", " interacting with ", "Bed", " current time in minutes ", "64", " expected interaction finish time ", "310.0", " the interaction in hours: ", "4.1"], ["Agent 2", " interacting with ", "Toilet", " current time in minutes ", "320", " expected interaction finish time ", "344.0", " the interaction in hours: ", "0.4"], ["Agent 2", " interacting with ", "Shower", " current time in minutes ", "348", " expected interaction finish time ", "372.0", " the interaction in hours: ", "0.4"], ["Agent 2", " interacting with ", "Shower", " current time in minutes ", "376", " expected interaction finish time ", "400.0", " the interaction in hours: ", "0.4"], ["Agent 2", " interacting with ", "Toilet", " current time in minutes ", "406", " expected interaction finish time ", "430.0", " the interaction in hours: ", "0.4"], ["Agent 2", " interacting with ", "Bed", " current time in minutes ", "448", " expected interaction finish time ", "694.0", " the interaction in hours: ", "4.1"], ["Agent 2", " interacting with ", "Shower", " current time in minutes ", "706", " expected interaction finish time ", "730.0", " the interaction in hours: ", "0.4"], ["Agent 2", " interacting with ", "Shower", " current time in minutes ", "739", " expected interaction finish time ", "763.0", " the interaction in hours: ", "0.4"], ["Agent 2", " interacting with ", "Toilet", " current time in minutes ", "768", " expected interaction finish time ", "792.0", " the interaction in hours: ", "0.4"], ["Agent 2", " interacting with ", "Shower", " current time in minutes ", "799", " expected interaction finish time ", "823.0", " the interaction in hours: ", "0.4"], ["Agent 2", " interacting with ", "Toilet", " current time in minutes ", "835", " expected interaction finish time ", "859.0", " the interaction in hours: ", "0.4"], ["Agent 2", " interacting with ", "Bed", " current time in minutes ", "880", " expected interaction finish time ", "1126.0", " the interaction in hours: ", "4.1"], ["Agent 2", " interacting with ", "Toilet", " current time in minutes ", "1137", " expected interaction finish time ", "1161.0", " the interaction in hours: ", "0.4"], ["Agent 2", " interacting with ", "Shower", " current time in minutes ", "1167", " expected interaction finish time ", "1191.0", " the interaction in hours: ", "0.4"], ["Agent 2", " interacting with ", "Shower", " current time in minutes ", "1196", " expected interaction finish time ", "1220.0", " the interaction in hours: ", "0.4"], ["Agent 2", " interacting with ", "Shower", " current time in minutes ", "1227", " expected interaction finish time ", "1251.0", " the interaction in hours: ", "0.4"], ["Agent 2", " interacting with ", "Bed", " current time in minutes ", "1207", " expected interaction finish time ", "1453.0", " the interaction in hours: ", "4.1"]]}, "neighbouring_rooms": {"bedroom": ["bathroom", "bedroom"], "bathroom": ["bedroom", "bedroom", "bedroom", "bedroom"]}, "mutated": false, "crossover": false, "parent1": null, "parent2": null, "mutation_probability": null, "agents_have_bedrooms": 0}